{
  "XAUUSD_2M": {
    "f1": 0.1224,
    "f2": 0.2952,
    "f3": -0.033,
    "f4": 1.0,
    "f5": 0.0964,
    "f6": -0.3978,
    "f7": 0.2498,
    "f8": 0.0815,
    "f9": 0.0,
    "f10": 1.0,
    "f11": 0.0,
    "f12": 0.0,
    "f13": -0.5442,
    "f14": 0.0,
    "f15": 1.0,
    "f16": -1.0,
    "f17": 1.0,
    "f18": 0.6348,
    "f19": 0.0,
    "f20": 0.5442,
    "f21": 0.2493,
    "f22": 0.8223,
    "f23": -0.0086,
    "f24": 0.0,
    "f25": -0.7826,
    "f26": 0.3978,
    "timestamp": "2026-06-11T15:30:03.986748+00:00"
  },
  "XAUUSD_5M": {
    "f1": 0.0588,
    "f2": 0.2783,
    "f3": -0.1146,
    "f4": 1.0,
    "f5": 1.0,
    "f6": -0.5343,
    "f7": 0.3427,
    "f8": -0.1726,
    "f9": 0.0,
    "f10": 0.0,
    "f11": 0.0,
    "f12": 0.0,
    "f13": -0.3307,
    "f14": -0.7,
    "f15": 1.0,
    "f16": -1.0,
    "f17": -1.0,
    "f18": 0.4676,
    "f19": 0.0,
    "f20": -0.8,
    "f21": 0.0755,
    "f22": -0.1879,
    "f23": -0.029,
    "f24": 0.0,
    "f25": -0.7716,
    "f26": 0.5343,
    "timestamp": "2026-06-11T15:30:03.986793+00:00"
  },
  "XAUUSD_1H": {
    "f1": -0.2526,
    "f2": -0.6436,
    "f3": -0.1306,
    "f4": 0.223,
    "f5": 1.0,
    "f6": 0.432,
    "f7": -0.0795,
    "f8": -1.0,
    "f9": 0.0,
    "f10": 0.0,
    "f11": 0.0,
    "f12": 1.0,
    "f13": 0.7217,
    "f14": 0.0,
    "f15": 1.0,
    "f16": -1.0,
    "f17": -1.0,
    "f18": 0.1737,
    "f19": 0.0,
    "f20": -0.7909,
    "f21": -0.0957,
    "f22": -0.4001,
    "f23": -0.0554,
    "f24": 0.0,
    "f25": -0.5075,
    "f26": -0.432,
    "timestamp": "2026-06-11T15:30:03.986801+00:00"
  },
  "STOCKS_QUALITY_30M": {
    "f1": -0.2483,
    "f2": -0.7046,
    "f3": 0.2529,
    "f4": -0.6212,
    "f5": -1.0,
    "f6": 0.2932,
    "f7": -0.2135,
    "f8": -0.7332,
    "f9": 0.0,
    "f10": 0.0,
    "f11": 0.0,
    "f12": 0.0,
    "f13": 0.5392,
    "f14": 0.0,
    "f15": 1.0,
    "f16": 0.0,
    "f17": -1.0,
    "f18": 0.5834,
    "f19": 0.0,
    "f20": -0.8374,
    "f21": 0.0178,
    "f22": 0.55,
    "f23": 0.0106,
    "f24": 0.0,
    "f25": -0.7071,
    "f26": -0.2932,
    "timestamp": "2026-06-11T15:30:03.986810+00:00"
  },
  "STOCKS_INDEX_30M": {
    "f1": -0.1848,
    "f2": -0.6712,
    "f3": 0.0162,
    "f4": -0.0092,
    "f5": 0.0475,
    "f6": 0.4386,
    "f7": -0.2726,
    "f8": -0.8109,
    "f9": 0.0,
    "f10": 0.0,
    "f11": 0.0,
    "f12": 1.0,
    "f13": 0.6206,
    "f14": 0.0,
    "f15": 1.0,
    "f16": 0.0,
    "f17": -1.0,
    "f18": 0.3283,
    "f19": 1.0,
    "f20": -0.7561,
    "f21": -0.0858,
    "f22": 0.3747,
    "f23": -0.0633,
    "f24": 0.0,
    "f25": -0.7071,
    "f26": -0.4386,
    "timestamp": "2026-06-11T15:30:03.986817+00:00"
  },
  "STOCKS_MOMENTUM_30M": {
    "f1": 0.0894,
    "f2": 0.2796,
    "f3": -0.0122,
    "f4": 1.0,
    "f5": 0.9101,
    "f6": -0.5556,
    "f7": 0.0443,
    "f8": -0.0332,
    "f9": 0.0,
    "f10": 0.0,
    "f11": 0.0,
    "f12": 0.0,
    "f13": -0.2486,
    "f14": 0.0,
    "f15": 1.0,
    "f16": 1.0,
    "f17": -1.0,
    "f18": 0.3783,
    "f19": 0.0,
    "f20": 0.8,
    "f21": 0.0424,
    "f22": 0.5068,
    "f23": -0.0121,
    "f24": 0.0,
    "f25": -0.7071,
    "f26": 0.5556,
    "timestamp": "2026-06-11T15:30:03.986825+00:00"
  },
  "STOCKS_QUALITY_4H": {
    "f1": -0.0156,
    "f2": -0.2907,
    "f3": 0.198,
    "f4": 0.4723,
    "f5": -0.8598,
    "f6": 0.379,
    "f7": -0.1945,
    "f8": 0.7039,
    "f9": 0.0,
    "f10": 0.0,
    "f11": 0.0,
    "f12": 0.0,
    "f13": -0.0495,
    "f14": -0.7,
    "f15": 0.5,
    "f16": 1.0,
    "f17": -1.0,
    "f18": -0.5658,
    "f19": 0.0,
    "f20": 0.5754,
    "f21": -0.1098,
    "f22": -0.5952,
    "f23": 0.0082,
    "f24": 0.0,
    "f25": -0.9914,
    "f26": 0.0,
    "timestamp": "2026-06-11T15:30:03.986832+00:00"
  },
  "XAUUSD_30M": {
    "f1": -0.1533,
    "f2": -0.5425,
    "f3": -0.0147,
    "f4": -0.4854,
    "f5": -0.3724,
    "f6": 0.3896,
    "f7": -0.3461,
    "f8": -1.0,
    "f9": 0.0,
    "f10": 0.0,
    "f11": 0.0,
    "f12": 0.0,
    "f13": 0.4177,
    "f14": 0.7,
    "f15": 1.0,
    "f16": -1.0,
    "f17": -1.0,
    "f18": -1.0,
    "f19": 0.0,
    "f20": -0.7217,
    "f21": -0.143,
    "f22": -0.1715,
    "f23": -0.0605,
    "f24": 0.0,
    "f25": -0.6157,
    "f26": -0.3896,
    "timestamp": "2026-06-11T15:30:03.986840+00:00"
  },
  "XAUUSD_4H": {
    "f1": -0.331,
    "f2": -0.3065,
    "f3": -0.1378,
    "f4": -1.0,
    "f5": -1.0,
    "f6": 0.9528,
    "f7": -0.5265,
    "f8": -0.553,
    "f9": 0.0,
    "f10": 0.0,
    "f11": -1.0,
    "f12": 0.0,
    "f13": 0.9758,
    "f14": 0.0,
    "f15": 1.0,
    "f16": -1.0,
    "f17": -1.0,
    "f18": -1.0,
    "f19": 0.0,
    "f20": -0.8,
    "f21": -0.1612,
    "f22": -0.9362,
    "f23": -0.2341,
    "f24": 0.0,
    "f25": -0.3827,
    "f26": 0.0,
    "timestamp": "2026-06-11T15:30:03.986846+00:00"
  },
  "STOCKS_MOMENTUM_4H": {
    "f1": -0.316,
    "f2": -0.405,
    "f3": -0.2494,
    "f4": -0.3804,
    "f5": -1.0,
    "f6": 0.8637,
    "f7": -0.66,
    "f8": -0.6904,
    "f9": 0.0,
    "f10": -1.0,
    "f11": 0.0,
    "f12": 0.0,
    "f13": 0.9333,
    "f14": 0.0,
    "f15": 0.5,
    "f16": -1.0,
    "f17": -1.0,
    "f18": -0.2076,
    "f19": 0.0,
    "f20": -0.3855,
    "f21": -0.1569,
    "f22": -0.6031,
    "f23": 0.0094,
    "f24": 0.0,
    "f25": -0.9914,
    "f26": 0.0,
    "timestamp": "2026-06-11T15:30:03.986853+00:00"
  },
  "STOCKS_INDEX_4H": {
    "f1": -0.3442,
    "f2": -0.7916,
    "f3": 0.7977,
    "f4": -1.0,
    "f5": -1.0,
    "f6": 0.8513,
    "f7": -0.5285,
    "f8": 0.5561,
    "f9": 0.0,
    "f10": 0.0,
    "f11": 0.0,
    "f12": 0.0,
    "f13": 0.8513,
    "f14": 0.0,
    "f15": 0.5,
    "f16": 0.0,
    "f17": -1.0,
    "f18": -0.8905,
    "f19": 0.0,
    "f20": 0.4284,
    "f21": -0.2287,
    "f22": -0.6511,
    "f23": 0.0005,
    "f24": 0.0,
    "f25": -0.9914,
    "f26": 0.0,
    "timestamp": "2026-06-11T15:30:03.986860+00:00"
  },
  "STOCKS_SPX500_15M": {
    "f1": -0.1355,
    "f2": -0.5518,
    "f3": 1.0,
    "f4": -0.2994,
    "f5": -1.0,
    "f6": 0.1834,
    "f7": -0.2171,
    "f8": -0.4753,
    "f9": 0.0,
    "f10": 0.0,
    "f11": 0.0,
    "f12": 1.0,
    "f13": 0.2185,
    "f14": 0.0,
    "f15": 1.0,
    "f16": -1.0,
    "f17": -1.0,
    "f18": 0.0,
    "f19": 1.0,
    "f20": -0.3001,
    "f21": 0.0,
    "f22": 0.5,
    "f23": -0.072,
    "f24": 0.0,
    "f25": -0.7071,
    "f26": -0.1834,
    "timestamp": "2026-06-11T15:30:03.986871+00:00"
  },
  "STOCKS_SPX500_30M": {
    "f1": -0.143,
    "f2": -0.4989,
    "f3": 0.7735,
    "f4": -0.7229,
    "f5": -1.0,
    "f6": 0.2649,
    "f7": -0.2982,
    "f8": -0.7979,
    "f9": 0.0,
    "f10": 0.0,
    "f11": 0.0,
    "f12": 1.0,
    "f13": 0.3204,
    "f14": 0.0,
    "f15": 1.0,
    "f16": -1.0,
    "f17": -1.0,
    "f18": 0.0,
    "f19": 1.0,
    "f20": -0.5457,
    "f21": 0.0,
    "f22": 0.3584,
    "f23": -0.1726,
    "f24": 0.0,
    "f25": -0.7071,
    "f26": -0.2649,
    "timestamp": "2026-06-11T15:30:03.986878+00:00"
  },
  "STOCKS_SPX500_4H": {
    "f1": -0.1827,
    "f2": -0.7974,
    "f3": 0.2382,
    "f4": 0.1099,
    "f5": 0.0819,
    "f6": 0.3511,
    "f7": -0.2187,
    "f8": -0.1885,
    "f9": 0.0,
    "f10": 0.0,
    "f11": 0.0,
    "f12": 0.0,
    "f13": 0.5772,
    "f14": 0.0,
    "f15": 0.8,
    "f16": -1.0,
    "f17": -1.0,
    "f18": 0.0,
    "f19": 0.0,
    "f20": -0.5772,
    "f21": 0.0,
    "f22": -0.3986,
    "f23": 0.1392,
    "f24": 0.0,
    "f25": 0.7071,
    "f26": 0.0,
    "timestamp": "2026-06-11T15:30:03.986885+00:00"
  },
  "STOCKS_QQQ_15M": {
    "f1": 0.0009,
    "f2": -0.3404,
    "f3": 0.1752,
    "f4": 1.0,
    "f5": 1.0,
    "f6": 0.0141,
    "f7": -0.0094,
    "f8": -0.8222,
    "f9": -1.0,
    "f10": 0.0,
    "f11": 0.0,
    "f12": 0.0,
    "f13": -0.0624,
    "f14": 0.0,
    "f15": 1.0,
    "f16": 0.0,
    "f17": -1.0,
    "f18": 1.0,
    "f19": 0.0,
    "f20": -0.3282,
    "f21": -0.0648,
    "f22": 0.5448,
    "f23": -0.1096,
    "f24": 0.0,
    "f25": -0.7071,
    "f26": -0.0141,
    "timestamp": "2026-06-11T15:30:03.986891+00:00"
  },
  "STOCKS_MOMENTUM_15M": {
    "f1": 0.1245,
    "f2": 0.359,
    "f3": 0.0224,
    "f4": 1.0,
    "f5": 1.0,
    "f6": -0.3002,
    "f7": 0.269,
    "f8": -0.3532,
    "f9": 0.0,
    "f10": 0.0,
    "f11": 0.0,
    "f12": 0.0,
    "f13": -0.474,
    "f14": 0.0,
    "f15": 1.0,
    "f16": 1.0,
    "f17": -1.0,
    "f18": -0.5468,
    "f19": 0.0,
    "f20": 0.8,
    "f21": -0.1032,
    "f22": -0.3089,
    "f23": -0.0864,
    "f24": 0.0,
    "f25": -0.7518,
    "f26": 0.3002,
    "timestamp": "2026-06-11T15:30:03.986898+00:00"
  },
  "STOCKS_QUALITY_15M": {
    "f1": -0.5893,
    "f2": -0.9334,
    "f3": 0.2852,
    "f4": -0.3302,
    "f5": -1.0,
    "f6": 0.8252,
    "f7": -0.6986,
    "f8": -1.0,
    "f9": 0.0,
    "f10": 0.0,
    "f11": 0.0,
    "f12": 0.0,
    "f13": 0.9125,
    "f14": 0.7,
    "f15": 1.0,
    "f16": -1.0,
    "f17": -1.0,
    "f18": -0.1814,
    "f19": 0.0,
    "f20": -0.9246,
    "f21": -0.254,
    "f22": 0.0307,
    "f23": 0.0112,
    "f24": 0.0,
    "f25": -0.7518,
    "f26": -0.8252,
    "timestamp": "2026-06-11T15:30:03.986906+00:00"
  },
  "STOCKS_QQQ_30M": {
    "f1": -0.1525,
    "f2": -0.6107,
    "f3": 0.0292,
    "f4": 0.0136,
    "f5": 0.9717,
    "f6": 0.5823,
    "f7": -0.3288,
    "f8": -0.7043,
    "f9": 0.0,
    "f10": 0.0,
    "f11": 0.0,
    "f12": 0.0,
    "f13": 0.4723,
    "f14": 0.0,
    "f15": 1.0,
    "f16": 0.0,
    "f17": -1.0,
    "f18": -0.8489,
    "f19": 0.0,
    "f20": -0.6672,
    "f21": -0.2436,
    "f22": -0.6691,
    "f23": 0.1547,
    "f24": 0.0,
    "f25": -0.6088,
    "f26": -0.5823,
    "timestamp": "2026-06-11T15:30:03.986912+00:00"
  },
  "STOCKS_INDEX_15M": {
    "f1": -0.108,
    "f2": -0.4052,
    "f3": 0.1526,
    "f4": 0.4194,
    "f5": 0.5608,
    "f6": 0.2162,
    "f7": -0.1241,
    "f8": -1.0,
    "f9": 0.0,
    "f10": 0.0,
    "f11": 0.0,
    "f12": 0.0,
    "f13": 0.4157,
    "f14": 0.7,
    "f15": 1.0,
    "f16": 0.0,
    "f17": -1.0,
    "f18": -0.3289,
    "f19": 0.0,
    "f20": -0.6206,
    "f21": -0.0893,
    "f22": -0.0739,
    "f23": -0.0477,
    "f24": 0.0,
    "f25": -0.7518,
    "f26": -0.2162,
    "timestamp": "2026-06-11T15:30:03.986918+00:00"
  },
  "STOCKS_QQQ_4H": {
    "f1": -0.2883,
    "f2": -0.729,
    "f3": 0.7854,
    "f4": -0.8742,
    "f5": -1.0,
    "f6": 0.761,
    "f7": -0.4641,
    "f8": 0.6831,
    "f9": 0.0,
    "f10": 0.0,
    "f11": 0.0,
    "f12": 0.0,
    "f13": 0.761,
    "f14": 0.0,
    "f15": 0.5,
    "f16": 0.0,
    "f17": -1.0,
    "f18": -0.6124,
    "f19": 0.0,
    "f20": 0.4055,
    "f21": -0.1845,
    "f22": -0.4579,
    "f23": 0.0071,
    "f24": 0.0,
    "f25": -0.9914,
    "f26": 0.0,
    "timestamp": "2026-06-11T15:30:03.986927+00:00"
  }
}