[
  {
    "source": "Mining.com",
    "headline": "Gold Fields, Cree First Nation sign IBA for Windfall project in\u00a0Quebec",
    "url": "https://www.mining.com/gold-fields-cree-first-nation-sign-iba-for-windfall-project-in-quebec/",
    "sentiment_score": 0.0,
    "impact": "LOW",
    "keywords": [
      "mining",
      "project development",
      "sector news"
    ],
    "fetched_at": "2026-06-03T03:39:32.606217+00:00"
  },
  {
    "source": "Mining.com",
    "headline": "Copper price: Goldman, Citi make bullish calls on supply woes",
    "url": "https://www.mining.com/copper-price-goldman-citi-make-bullish-calls-on-supply-woes/",
    "sentiment_score": 0.0,
    "impact": "LOW",
    "keywords": [
      "copper",
      "commodities",
      "sector news"
    ],
    "fetched_at": "2026-06-03T03:39:32.606217+00:00"
  },
  {
    "source": "Mining.com",
    "headline": "Aya logs bonanza silver hits at Zgounder mine in Morocco",
    "url": "https://www.mining.com/aya-logs-bonanza-silver-hits-at-zgounder-mine-in-morocco/",
    "sentiment_score": 0.0,
    "impact": "LOW",
    "keywords": [
      "silver",
      "mining",
      "sector news"
    ],
    "fetched_at": "2026-06-03T03:39:32.606217+00:00"
  },
  {
    "source": "Mining.com",
    "headline": "Tintina soars on $66M backing for Chile copper-gold project",
    "url": "https://www.mining.com/tintina-soars-to-new-high-on-66m-backing-for-chile-copper-gold-project/",
    "sentiment_score": 0.0,
    "impact": "LOW",
    "keywords": [
      "copper",
      "mining",
      "sector news"
    ],
    "fetched_at": "2026-06-03T03:39:32.606217+00:00"
  },
  {
    "source": "Mining.com",
    "headline": "Boroo\u2019s bid to buy former Eagle gold site raises questions among miners",
    "url": "https://www.mining.com/boroos-bid-to-buy-former-eagle-gold-site-raises-questions-among-miners/",
    "sentiment_score": 0.0,
    "impact": "LOW",
    "keywords": [
      "gold mining",
      "M&A",
      "sector news"
    ],
    "fetched_at": "2026-06-03T03:39:32.606217+00:00"
  },
  {
    "source": "Mining.com",
    "headline": "Gold overtakes US Treasuries in global reserve shift: ECB",
    "url": "https://www.mining.com/gold-overtakes-us-treasuries-in-global-reserve-shift-ecb/",
    "sentiment_score": 0.5,
    "impact": "MEDIUM",
    "keywords": [
      "gold demand",
      "reserve shift",
      "institutional"
    ],
    "fetched_at": "2026-06-03T03:39:32.606217+00:00"
  },
  {
    "source": "Mining.com",
    "headline": "Miners urge gov\u2019t aid to challenge China\u2019s rare earth dominance",
    "url": "https://www.mining.com/rare-earth-miners-say-market-needs-govt-support-to-break-chinas-grip/",
    "sentiment_score": 0.0,
    "impact": "LOW",
    "keywords": [
      "mining policy",
      "rare earths",
      "sector news"
    ],
    "fetched_at": "2026-06-03T03:39:32.606217+00:00"
  },
  {
    "source": "Mining.com",
    "headline": "Elliot pushes Australia\u2019s top gold miner to weigh sale option",
    "url": "https://www.mining.com/elliot-pushes-australias-top-gold-miner-to-weigh-sale-option/",
    "sentiment_score": 0.1,
    "impact": "LOW",
    "keywords": [
      "M&A",
      "gold miner",
      "sector news"
    ],
    "fetched_at": "2026-06-03T03:39:32.606217+00:00"
  },
  {
    "source": "FinancialJuice",
    "headline": "China finance ministry sells 1-month bills at 0.8087% yield: traders",
    "url": "https://www.financialjuice.com/News/9616619/China-finance-ministry-sells-1-month-bills-at-08087-yield-traders.aspx?xy=rss",
    "sentiment_score": 0.0,
    "impact": "LOW",
    "keywords": [],
    "fetched_at": "2026-06-03T03:39:49.270672+00:00"
  },
  {
    "source": "FinancialJuice",
    "headline": "China finance ministry issues 30-year ultra-long special treasury bonds at 2.2046% yield: traders",
    "url": "https://www.financialjuice.com/News/9616618/China-finance-ministry-issues-30-year-ultra-long-special-treasury-bonds-at-22046-yield-traders.aspx?xy=rss",
    "sentiment_score": 0.0,
    "impact": "LOW",
    "keywords": [],
    "fetched_at": "2026-06-03T03:39:49.270672+00:00"
  },
  {
    "source": "FinancialJuice",
    "headline": "Volume of China cbank's reverse repos via open market operations hits zero for first time since August 7, 2024: source calculation",
    "url": "https://www.financialjuice.com/News/9616593/Volume-of-China-cbanks-reverse-repos-via-open-market-operations-hits-zero-for-first-time-since-August-7-2024-source-calculation.aspx?xy=rss",
    "sentiment_score": 0.0,
    "impact": "LOW",
    "keywords": [],
    "fetched_at": "2026-06-03T03:39:49.270672+00:00"
  },
  {
    "source": "FinancialJuice",
    "headline": "Russia shoots down 30 drones over Leningrad region: governor",
    "url": "https://www.financialjuice.com/News/9616592/Russia-shoots-down-30-drones-over-Leningrad-region-governor.aspx?xy=rss",
    "sentiment_score": 0.0,
    "impact": "LOW",
    "keywords": [],
    "fetched_at": "2026-06-03T03:39:49.270672+00:00"
  },
  {
    "source": "FinancialJuice",
    "headline": "Drones strike Michurinsk in central Russia's Tambov region: governor",
    "url": "https://www.financialjuice.com/News/9616563/Drones-strike-Michurinsk-in-central-Russias-Tambov-region-governor.aspx?xy=rss",
    "sentiment_score": 0.0,
    "impact": "LOW",
    "keywords": [],
    "fetched_at": "2026-06-03T03:39:49.270672+00:00"
  },
  {
    "source": "FinancialJuice",
    "headline": "RatingDog: China general services PMI rises to 54.4 in May from 52.6 in April",
    "url": "https://www.financialjuice.com/News/9616436/RatingDog-China-general-services-PMI-rises-to-544-in-May-from-526-in-April.aspx?xy=rss",
    "sentiment_score": 0.0,
    "impact": "LOW",
    "keywords": [],
    "fetched_at": "2026-06-03T03:39:49.270672+00:00"
  },
  {
    "source": "FinancialJuice",
    "headline": "China's trade-weighted CFETS yuan basket index climbs to 101.05, highest since Jan. 20, 2025 - calculations",
    "url": "https://www.financialjuice.com/News/9616429/Chinas-trade-weighted-CFETS-yuan-basket-index-climbs-to-10105-highest-since-Jan-20-2025---calculations.aspx?xy=rss",
    "sentiment_score": 0.0,
    "impact": "LOW",
    "keywords": [],
    "fetched_at": "2026-06-03T03:39:49.270672+00:00"
  },
  {
    "source": "FinancialJuice",
    "headline": "Australia Q1 real GDP rises 0.3% quarter on quarter, seasonally adjusted (Poll: 0.5%)",
    "url": "https://www.financialjuice.com/News/9616425/Australia-Q1-real-GDP-rises-03-quarter-on-quarter-seasonally-adjusted-Poll-05.aspx?xy=rss",
    "sentiment_score": 0.0,
    "impact": "LOW",
    "keywords": [],
    "fetched_at": "2026-06-03T03:39:49.270672+00:00"
  },
  {
    "source": "FinancialJuice",
    "headline": "Australia Q1 real GDP rises 2.5% year on year, seasonally adjusted (Poll: 2.6%)",
    "url": "https://www.financialjuice.com/News/9616423/Australia-Q1-real-GDP-rises-25-year-on-year-seasonally-adjusted-Poll-26.aspx?xy=rss",
    "sentiment_score": 0.0,
    "impact": "LOW",
    "keywords": [],
    "fetched_at": "2026-06-03T03:39:49.270672+00:00"
  },
  {
    "source": "FinancialJuice",
    "headline": "Australian Real GDP YoY Actual 2.5% (Forecast 2.6%, Previous 2.6%)",
    "url": "https://www.financialjuice.com/News/9616420/Australian-Real-GDP-YoY-Actual-25-Forecast-26-Previous-26.aspx?xy=rss",
    "sentiment_score": 0.0,
    "impact": "LOW",
    "keywords": [],
    "fetched_at": "2026-06-03T03:39:49.270672+00:00"
  },
  {
    "source": "MarketWatch Top",
    "headline": "The S&P 500 climbs for a 9th straight day \u2014 but the \u2018breadth paradox\u2019 is sending a rare warning",
    "url": "https://www.marketwatch.com/story/s-p-500-climbing-for-9th-straight-day-but-breadth-sends-a-rare-warning-1577195d?mod=mw_rss_topstories",
    "sentiment_score": 0.0,
    "impact": "LOW",
    "keywords": [],
    "fetched_at": "2026-06-03T03:39:49.270672+00:00"
  },
  {
    "source": "Investing.com Forex",
    "headline": "U.S. dollar little changed as mixed messaging on Iran talks boost uncertainty",
    "url": "https://www.investing.com/news/forex-news/dollar-steady-amid-mixed-signals-on-usiran-talks-4720844",
    "sentiment_score": 0.0,
    "impact": "LOW",
    "keywords": [],
    "fetched_at": "2026-06-03T03:39:49.270672+00:00"
  },
  {
    "source": "Investing.com Forex",
    "headline": "Canadian dollar holds near multi-week low on weak data",
    "url": "https://www.investing.com/news/forex-news/canadian-dollar-holds-near-multiweek-low-on-weak-data-93CH-4722732",
    "sentiment_score": 0.0,
    "impact": "LOW",
    "keywords": [],
    "fetched_at": "2026-06-03T03:39:49.270672+00:00"
  },
  {
    "source": "Investing.com Forex",
    "headline": "Improving macro backdrop set to keep dollar resilient, BCA says",
    "url": "https://www.investing.com/news/forex-news/improving-macro-backdrop-set-to-keep-dollar-resilient-bca-says-4722053",
    "sentiment_score": 0.0,
    "impact": "LOW",
    "keywords": [],
    "fetched_at": "2026-06-03T03:39:49.270672+00:00"
  },
  {
    "source": "Investing.com Forex",
    "headline": "Sterling today: Pound edges higher as Dollar softens on Gulf uncertainty",
    "url": "https://www.investing.com/news/forex-news/sterling-today-pound-edges-higher-as-dollar-softens-on-gulf-uncertainty-4721662",
    "sentiment_score": 0.0,
    "impact": "LOW",
    "keywords": [],
    "fetched_at": "2026-06-03T03:39:49.270672+00:00"
  },
  {
    "source": "Investing.com Forex",
    "headline": "Dollar ticks up on safe haven demand amid uncertainty over U.S.-Iran peace talks",
    "url": "https://www.investing.com/news/forex-news/asia-fx-dollar-subdued-amid-iran-ceasefire-uncertainty-china-mixed-pmi-in-focus-4718007",
    "sentiment_score": 0.0,
    "impact": "LOW",
    "keywords": [],
    "fetched_at": "2026-06-03T03:39:49.270672+00:00"
  },
  {
    "source": "Mining.com",
    "headline": "Gold Fields, Cree First Nation sign IBA for Windfall project in\u00a0Quebec",
    "url": "https://www.mining.com/gold-fields-cree-first-nation-sign-iba-for-windfall-project-in-quebec/",
    "sentiment_score": 0.0,
    "impact": "LOW",
    "keywords": [],
    "fetched_at": "2026-06-03T03:39:49.270672+00:00"
  },
  {
    "source": "Mining.com",
    "headline": "Copper price: Goldman, Citi make bullish calls on supply woes",
    "url": "https://www.mining.com/copper-price-goldman-citi-make-bullish-calls-on-supply-woes/",
    "sentiment_score": 0.0,
    "impact": "LOW",
    "keywords": [],
    "fetched_at": "2026-06-03T03:39:49.270672+00:00"
  },
  {
    "source": "Mining.com",
    "headline": "Aya logs bonanza silver hits at Zgounder mine in Morocco",
    "url": "https://www.mining.com/aya-logs-bonanza-silver-hits-at-zgounder-mine-in-morocco/",
    "sentiment_score": 0.0,
    "impact": "LOW",
    "keywords": [],
    "fetched_at": "2026-06-03T03:39:49.270672+00:00"
  },
  {
    "source": "Mining.com",
    "headline": "Tintina soars on $66M backing for Chile copper-gold project",
    "url": "https://www.mining.com/tintina-soars-to-new-high-on-66m-backing-for-chile-copper-gold-project/",
    "sentiment_score": 0.0,
    "impact": "LOW",
    "keywords": [],
    "fetched_at": "2026-06-03T03:39:49.270672+00:00"
  },
  {
    "source": "Mining.com",
    "headline": "Boroo\u2019s bid to buy former Eagle gold site raises questions among miners",
    "url": "https://www.mining.com/boroos-bid-to-buy-former-eagle-gold-site-raises-questions-among-miners/",
    "sentiment_score": 0.0,
    "impact": "LOW",
    "keywords": [],
    "fetched_at": "2026-06-03T03:39:49.270672+00:00"
  },
  {
    "source": "Mining.com",
    "headline": "Gold overtakes US Treasuries in global reserve shift: ECB",
    "url": "https://www.mining.com/gold-overtakes-us-treasuries-in-global-reserve-shift-ecb/",
    "sentiment_score": 0.0,
    "impact": "LOW",
    "keywords": [],
    "fetched_at": "2026-06-03T03:39:49.270672+00:00"
  },
  {
    "source": "Mining.com",
    "headline": "Miners urge gov\u2019t aid to challenge China\u2019s rare earth dominance",
    "url": "https://www.mining.com/rare-earth-miners-say-market-needs-govt-support-to-break-chinas-grip/",
    "sentiment_score": 0.0,
    "impact": "LOW",
    "keywords": [],
    "fetched_at": "2026-06-03T03:39:49.270672+00:00"
  },
  {
    "source": "Mining.com",
    "headline": "Elliot pushes Australia\u2019s top gold miner to weigh sale option",
    "url": "https://www.mining.com/elliot-pushes-australias-top-gold-miner-to-weigh-sale-option/",
    "sentiment_score": 0.0,
    "impact": "LOW",
    "keywords": [],
    "fetched_at": "2026-06-03T03:39:49.270672+00:00"
  },
  {
    "source": "FinancialJuice",
    "headline": "Republican Jim Desmond projected to move forward to November general election in California's 48th congressional district, DDHQ says",
    "url": "https://www.financialjuice.com/News/9616627/Republican-Jim-Desmond-projected-to-move-forward-to-November-general-election-in-Californias-48th-congressional-district-DDHQ-says.aspx?xy=rss",
    "sentiment_score": 0.0,
    "impact": "LOW",
    "keywords": [
      "US politics",
      "congressional election",
      "domestic"
    ],
    "fetched_at": "2026-06-03T03:54:49.940908+00:00"
  },
  {
    "source": "FinancialJuice",
    "headline": "Pakistan federal budget unlikely to be presented on June 5: government source, local media",
    "url": "https://www.financialjuice.com/News/9616625/Pakistan-federal-budget-unlikely-to-be-presented-on-June-5-government-source-local-media.aspx?xy=rss",
    "sentiment_score": 0.0,
    "impact": "LOW",
    "keywords": [
      "Pakistan",
      "budget delay",
      "fiscal"
    ],
    "fetched_at": "2026-06-03T03:54:49.940908+00:00"
  },
  {
    "source": "FinancialJuice",
    "headline": "China finance ministry sells 1-month bills at 0.8087% yield: traders",
    "url": "https://www.financialjuice.com/News/9616619/China-finance-ministry-sells-1-month-bills-at-08087-yield-traders.aspx?xy=rss",
    "sentiment_score": -0.3,
    "impact": "MEDIUM",
    "keywords": [
      "China yields",
      "monetary tightening",
      "bills"
    ],
    "fetched_at": "2026-06-03T03:54:49.940908+00:00"
  },
  {
    "source": "FinancialJuice",
    "headline": "China finance ministry issues 30-year ultra-long special treasury bonds at 2.2046% yield: traders",
    "url": "https://www.financialjuice.com/News/9616618/China-finance-ministry-issues-30-year-ultra-long-special-treasury-bonds-at-22046-yield-traders.aspx?xy=rss",
    "sentiment_score": -0.2,
    "impact": "MEDIUM",
    "keywords": [
      "China bonds",
      "long-term yields",
      "treasury"
    ],
    "fetched_at": "2026-06-03T03:54:49.940908+00:00"
  },
  {
    "source": "FinancialJuice",
    "headline": "Volume of China cbank's reverse repos via open market operations hits zero for first time since August 7, 2024: source calculation",
    "url": "https://www.financialjuice.com/News/9616593/Volume-of-China-cbanks-reverse-repos-via-open-market-operations-hits-zero-for-first-time-since-August-7-2024-source-calculation.aspx?xy=rss",
    "sentiment_score": 0.4,
    "impact": "MEDIUM",
    "keywords": [
      "China liquidity",
      "reverse repos",
      "monetary easing"
    ],
    "fetched_at": "2026-06-03T03:54:49.940908+00:00"
  },
  {
    "source": "FinancialJuice",
    "headline": "Russia shoots down 30 drones over Leningrad region: governor",
    "url": "https://www.financialjuice.com/News/9616592/Russia-shoots-down-30-drones-over-Leningrad-region-governor.aspx?xy=rss",
    "sentiment_score": 0.0,
    "impact": "LOW",
    "keywords": [
      "Russia military",
      "geopolitical",
      "tactical"
    ],
    "fetched_at": "2026-06-03T03:54:49.940908+00:00"
  },
  {
    "source": "FinancialJuice",
    "headline": "Drones strike Michurinsk in central Russia's Tambov region: governor",
    "url": "https://www.financialjuice.com/News/9616563/Drones-strike-Michurinsk-in-central-Russias-Tambov-region-governor.aspx?xy=rss",
    "sentiment_score": 0.0,
    "impact": "LOW",
    "keywords": [
      "Russia military",
      "geopolitical",
      "tactical"
    ],
    "fetched_at": "2026-06-03T03:54:49.940908+00:00"
  },
  {
    "source": "FinancialJuice",
    "headline": "RatingDog: China general services PMI rises to 54.4 in May from 52.6 in April",
    "url": "https://www.financialjuice.com/News/9616436/RatingDog-China-general-services-PMI-rises-to-544-in-May-from-526-in-April.aspx?xy=rss",
    "sentiment_score": -0.4,
    "impact": "MEDIUM",
    "keywords": [
      "China PMI",
      "services growth",
      "economic strength"
    ],
    "fetched_at": "2026-06-03T03:54:49.940908+00:00"
  },
  {
    "source": "FinancialJuice",
    "headline": "China's trade-weighted CFETS yuan basket index climbs to 101.05, highest since Jan. 20, 2025 - calculations",
    "url": "https://www.financialjuice.com/News/9616429/Chinas-trade-weighted-CFETS-yuan-basket-index-climbs-to-10105-highest-since-Jan-20-2025---calculations.aspx?xy=rss",
    "sentiment_score": -0.3,
    "impact": "MEDIUM",
    "keywords": [
      "yuan strength",
      "currency appreciation",
      "safe haven"
    ],
    "fetched_at": "2026-06-03T03:54:49.940908+00:00"
  },
  {
    "source": "FinancialJuice",
    "headline": "Australia Q1 real GDP rises 0.3% quarter on quarter, seasonally adjusted (Poll: 0.5%)",
    "url": "https://www.financialjuice.com/News/9616425/Australia-Q1-real-GDP-rises-03-quarter-on-quarter-seasonally-adjusted-Poll-05.aspx?xy=rss",
    "sentiment_score": -0.2,
    "impact": "MEDIUM",
    "keywords": [
      "Australia GDP",
      "weak growth",
      "economic slowdown"
    ],
    "fetched_at": "2026-06-03T03:54:49.940908+00:00"
  },
  {
    "source": "MarketWatch Top",
    "headline": "The S&P 500 climbs for a 9th straight day \u2014 but the \u2018breadth paradox\u2019 is sending a rare warning",
    "url": "https://www.marketwatch.com/story/s-p-500-climbing-for-9th-straight-day-but-breadth-sends-a-rare-warning-1577195d?mod=mw_rss_topstories",
    "sentiment_score": -0.4,
    "impact": "MEDIUM",
    "keywords": [
      "stock rally",
      "risk appetite",
      "equity strength"
    ],
    "fetched_at": "2026-06-03T03:54:49.940908+00:00"
  },
  {
    "source": "Investing.com Forex",
    "headline": "U.S. dollar little changed as mixed messaging on Iran talks boost uncertainty",
    "url": "https://www.investing.com/news/forex-news/dollar-steady-amid-mixed-signals-on-usiran-talks-4720844",
    "sentiment_score": 0.2,
    "impact": "LOW",
    "keywords": [
      "dollar neutral",
      "geopolitical uncertainty",
      "Iran talks"
    ],
    "fetched_at": "2026-06-03T03:54:49.940908+00:00"
  },
  {
    "source": "Investing.com Forex",
    "headline": "Canadian dollar holds near multi-week low on weak data",
    "url": "https://www.investing.com/news/forex-news/canadian-dollar-holds-near-multiweek-low-on-weak-data-93CH-4722732",
    "sentiment_score": 0.0,
    "impact": "LOW",
    "keywords": [
      "Canadian dollar",
      "weak data",
      "currency weakness"
    ],
    "fetched_at": "2026-06-03T03:54:49.940908+00:00"
  },
  {
    "source": "Investing.com Forex",
    "headline": "Improving macro backdrop set to keep dollar resilient, BCA says",
    "url": "https://www.investing.com/news/forex-news/improving-macro-backdrop-set-to-keep-dollar-resilient-bca-says-4722053",
    "sentiment_score": -0.3,
    "impact": "MEDIUM",
    "keywords": [
      "dollar resilient",
      "macro strength",
      "risk off"
    ],
    "fetched_at": "2026-06-03T03:54:49.940908+00:00"
  },
  {
    "source": "Investing.com Forex",
    "headline": "Sterling today: Pound edges higher as Dollar softens on Gulf uncertainty",
    "url": "https://www.investing.com/news/forex-news/sterling-today-pound-edges-higher-as-dollar-softens-on-gulf-uncertainty-4721662",
    "sentiment_score": -0.2,
    "impact": "LOW",
    "keywords": [
      "pound strength",
      "dollar weakness",
      "safe haven"
    ],
    "fetched_at": "2026-06-03T03:54:49.940908+00:00"
  },
  {
    "source": "Investing.com Forex",
    "headline": "Dollar ticks up on safe haven demand amid uncertainty over U.S.-Iran peace talks",
    "url": "https://www.investing.com/news/forex-news/asia-fx-dollar-subdued-amid-iran-ceasefire-uncertainty-china-mixed-pmi-in-focus-4718007",
    "sentiment_score": -0.3,
    "impact": "MEDIUM",
    "keywords": [
      "dollar strength",
      "safe haven demand",
      "uncertainty"
    ],
    "fetched_at": "2026-06-03T03:54:49.940908+00:00"
  },
  {
    "source": "Mining.com",
    "headline": "Gold Fields, Cree First Nation sign IBA for Windfall project in\u00a0Quebec",
    "url": "https://www.mining.com/gold-fields-cree-first-nation-sign-iba-for-windfall-project-in-quebec/",
    "sentiment_score": 0.0,
    "impact": "LOW",
    "keywords": [
      "gold mining",
      "project development",
      "industry"
    ],
    "fetched_at": "2026-06-03T03:54:49.940908+00:00"
  },
  {
    "source": "Mining.com",
    "headline": "Copper price: Goldman, Citi make bullish calls on supply woes",
    "url": "https://www.mining.com/copper-price-goldman-citi-make-bullish-calls-on-supply-woes/",
    "sentiment_score": 0.0,
    "impact": "LOW",
    "keywords": [
      "copper",
      "commodities",
      "mining sector"
    ],
    "fetched_at": "2026-06-03T03:54:49.940908+00:00"
  },
  {
    "source": "Mining.com",
    "headline": "Aya logs bonanza silver hits at Zgounder mine in Morocco",
    "url": "https://www.mining.com/aya-logs-bonanza-silver-hits-at-zgounder-mine-in-morocco/",
    "sentiment_score": 0.0,
    "impact": "LOW",
    "keywords": [
      "silver mining",
      "exploration",
      "industry"
    ],
    "fetched_at": "2026-06-03T03:54:49.940908+00:00"
  },
  {
    "source": "Mining.com",
    "headline": "Tintina soars on $66M backing for Chile copper-gold project",
    "url": "https://www.mining.com/tintina-soars-to-new-high-on-66m-backing-for-chile-copper-gold-project/",
    "sentiment_score": 0.0,
    "impact": "LOW",
    "keywords": [
      "mining investment",
      "copper-gold",
      "project funding"
    ],
    "fetched_at": "2026-06-03T03:54:49.940908+00:00"
  },
  {
    "source": "Mining.com",
    "headline": "Boroo\u2019s bid to buy former Eagle gold site raises questions among miners",
    "url": "https://www.mining.com/boroos-bid-to-buy-former-eagle-gold-site-raises-questions-among-miners/",
    "sentiment_score": 0.0,
    "impact": "LOW",
    "keywords": [
      "gold mining",
      "asset acquisition",
      "industry M&A"
    ],
    "fetched_at": "2026-06-03T03:54:49.940908+00:00"
  },
  {
    "source": "Mining.com",
    "headline": "Gold overtakes US Treasuries in global reserve shift: ECB",
    "url": "https://www.mining.com/gold-overtakes-us-treasuries-in-global-reserve-shift-ecb/",
    "sentiment_score": 0.5,
    "impact": "MEDIUM",
    "keywords": [
      "gold reserves",
      "central bank",
      "monetary policy"
    ],
    "fetched_at": "2026-06-03T03:54:49.940908+00:00"
  },
  {
    "source": "Mining.com",
    "headline": "Miners urge gov\u2019t aid to challenge China\u2019s rare earth dominance",
    "url": "https://www.mining.com/rare-earth-miners-say-market-needs-govt-support-to-break-chinas-grip/",
    "sentiment_score": 0.0,
    "impact": "LOW",
    "keywords": [
      "rare earth",
      "industrial policy",
      "trade"
    ],
    "fetched_at": "2026-06-03T03:54:49.940908+00:00"
  },
  {
    "source": "Mining.com",
    "headline": "Elliot pushes Australia\u2019s top gold miner to weigh sale option",
    "url": "https://www.mining.com/elliot-pushes-australias-top-gold-miner-to-weigh-sale-option/",
    "sentiment_score": 0.1,
    "impact": "LOW",
    "keywords": [
      "gold mining",
      "asset sale",
      "industry restructuring"
    ],
    "fetched_at": "2026-06-03T03:54:49.940908+00:00"
  },
  {
    "source": "FinancialJuice",
    "headline": "Russia-installed Donetsk leader: 7 killed, 11 hurt after drone strikes bus",
    "url": "https://www.financialjuice.com/News/9616671/Russia-installed-Donetsk-leader-7-killed-11-hurt-after-drone-strikes-bus.aspx?xy=rss",
    "sentiment_score": 0.3,
    "impact": "LOW",
    "keywords": [
      "geopolitical",
      "Ukraine",
      "risk"
    ],
    "fetched_at": "2026-06-03T04:09:49.662664+00:00"
  },
  {
    "source": "FinancialJuice",
    "headline": "Iran peace deal would not derail case for ECB rate increase, says central banker Pierre Wunsch - FT",
    "url": "https://www.financialjuice.com/News/9616670/Iran-peace-deal-would-not-derail-case-for-ECB-rate-increase-says-central-banker-Pierre-Wunsch---FT.aspx?xy=rss",
    "sentiment_score": -0.4,
    "impact": "MEDIUM",
    "keywords": [
      "ECB",
      "rate increase",
      "hawkish"
    ],
    "fetched_at": "2026-06-03T04:09:49.662664+00:00"
  },
  {
    "source": "FinancialJuice",
    "headline": "Russia shoots down 50 drones over Leningrad region overnight: governor",
    "url": "https://www.financialjuice.com/News/9616629/Russia-shoots-down-50-drones-over-Leningrad-region-overnight-governor.aspx?xy=rss",
    "sentiment_score": 0.2,
    "impact": "LOW",
    "keywords": [
      "geopolitical",
      "Ukraine",
      "risk"
    ],
    "fetched_at": "2026-06-03T04:09:49.662664+00:00"
  },
  {
    "source": "FinancialJuice",
    "headline": "Republican Jim Desmond projected to move forward to November general election in California's 48th congressional district, DDHQ says",
    "url": "https://www.financialjuice.com/News/9616627/Republican-Jim-Desmond-projected-to-move-forward-to-November-general-election-in-Californias-48th-congressional-district-DDHQ-says.aspx?xy=rss",
    "sentiment_score": 0.0,
    "impact": "LOW",
    "keywords": [
      "US politics",
      "election",
      "domestic"
    ],
    "fetched_at": "2026-06-03T04:09:49.662664+00:00"
  },
  {
    "source": "FinancialJuice",
    "headline": "Pakistan federal budget unlikely to be presented on June 5: government source, local media",
    "url": "https://www.financialjuice.com/News/9616625/Pakistan-federal-budget-unlikely-to-be-presented-on-June-5-government-source-local-media.aspx?xy=rss",
    "sentiment_score": 0.0,
    "impact": "LOW",
    "keywords": [
      "Pakistan",
      "budget",
      "fiscal"
    ],
    "fetched_at": "2026-06-03T04:09:49.662664+00:00"
  },
  {
    "source": "FinancialJuice",
    "headline": "China finance ministry sells 1-month bills at 0.8087% yield: traders",
    "url": "https://www.financialjuice.com/News/9616619/China-finance-ministry-sells-1-month-bills-at-08087-yield-traders.aspx?xy=rss",
    "sentiment_score": -0.3,
    "impact": "MEDIUM",
    "keywords": [
      "China",
      "liquidity",
      "tightening"
    ],
    "fetched_at": "2026-06-03T04:09:49.662664+00:00"
  },
  {
    "source": "FinancialJuice",
    "headline": "China finance ministry issues 30-year ultra-long special treasury bonds at 2.2046% yield: traders",
    "url": "https://www.financialjuice.com/News/9616618/China-finance-ministry-issues-30-year-ultra-long-special-treasury-bonds-at-22046-yield-traders.aspx?xy=rss",
    "sentiment_score": -0.2,
    "impact": "MEDIUM",
    "keywords": [
      "China",
      "bonds",
      "supply"
    ],
    "fetched_at": "2026-06-03T04:09:49.662664+00:00"
  },
  {
    "source": "FinancialJuice",
    "headline": "Volume of China cbank's reverse repos via open market operations hits zero for first time since August 7, 2024: source calculation",
    "url": "https://www.financialjuice.com/News/9616593/Volume-of-China-cbanks-reverse-repos-via-open-market-operations-hits-zero-for-first-time-since-August-7-2024-source-calculation.aspx?xy=rss",
    "sentiment_score": -0.5,
    "impact": "MEDIUM",
    "keywords": [
      "China",
      "liquidity drain",
      "monetary"
    ],
    "fetched_at": "2026-06-03T04:09:49.662664+00:00"
  },
  {
    "source": "FinancialJuice",
    "headline": "Russia shoots down 30 drones over Leningrad region: governor",
    "url": "https://www.financialjuice.com/News/9616592/Russia-shoots-down-30-drones-over-Leningrad-region-governor.aspx?xy=rss",
    "sentiment_score": 0.2,
    "impact": "LOW",
    "keywords": [
      "geopolitical",
      "Ukraine",
      "risk"
    ],
    "fetched_at": "2026-06-03T04:09:49.662664+00:00"
  },
  {
    "source": "FinancialJuice",
    "headline": "Drones strike Michurinsk in central Russia's Tambov region: governor",
    "url": "https://www.financialjuice.com/News/9616563/Drones-strike-Michurinsk-in-central-Russias-Tambov-region-governor.aspx?xy=rss",
    "sentiment_score": 0.2,
    "impact": "LOW",
    "keywords": [
      "geopolitical",
      "Ukraine",
      "risk"
    ],
    "fetched_at": "2026-06-03T04:09:49.662664+00:00"
  },
  {
    "source": "MarketWatch Top",
    "headline": "The S&P 500 climbs for a 9th straight day \u2014 but the \u2018breadth paradox\u2019 is sending a rare warning",
    "url": "https://www.marketwatch.com/story/s-p-500-climbing-for-9th-straight-day-but-breadth-sends-a-rare-warning-1577195d?mod=mw_rss_topstories",
    "sentiment_score": -0.2,
    "impact": "LOW",
    "keywords": [
      "equity rally",
      "risk-on",
      "dollar"
    ],
    "fetched_at": "2026-06-03T04:09:49.662664+00:00"
  },
  {
    "source": "Investing.com Forex",
    "headline": "U.S. dollar little changed as mixed messaging on Iran talks boost uncertainty",
    "url": "https://www.investing.com/news/forex-news/dollar-steady-amid-mixed-signals-on-usiran-talks-4720844",
    "sentiment_score": 0.2,
    "impact": "MEDIUM",
    "keywords": [
      "Iran",
      "uncertainty",
      "safe-haven"
    ],
    "fetched_at": "2026-06-03T04:09:49.662664+00:00"
  },
  {
    "source": "Investing.com Forex",
    "headline": "Canadian dollar holds near multi-week low on weak data",
    "url": "https://www.investing.com/news/forex-news/canadian-dollar-holds-near-multiweek-low-on-weak-data-93CH-4722732",
    "sentiment_score": 0.1,
    "impact": "LOW",
    "keywords": [
      "CAD weakness",
      "dollar strength",
      "sentiment"
    ],
    "fetched_at": "2026-06-03T04:09:49.662664+00:00"
  },
  {
    "source": "Investing.com Forex",
    "headline": "Improving macro backdrop set to keep dollar resilient, BCA says",
    "url": "https://www.investing.com/news/forex-news/improving-macro-backdrop-set-to-keep-dollar-resilient-bca-says-4722053",
    "sentiment_score": -0.3,
    "impact": "MEDIUM",
    "keywords": [
      "dollar strength",
      "macro backdrop",
      "resilience"
    ],
    "fetched_at": "2026-06-03T04:09:49.662664+00:00"
  },
  {
    "source": "Investing.com Forex",
    "headline": "Sterling today: Pound edges higher as Dollar softens on Gulf uncertainty",
    "url": "https://www.investing.com/news/forex-news/sterling-today-pound-edges-higher-as-dollar-softens-on-gulf-uncertainty-4721662",
    "sentiment_score": 0.1,
    "impact": "LOW",
    "keywords": [
      "dollar weakness",
      "GBP",
      "sentiment"
    ],
    "fetched_at": "2026-06-03T04:09:49.662664+00:00"
  },
  {
    "source": "Investing.com Forex",
    "headline": "Dollar ticks up on safe haven demand amid uncertainty over U.S.-Iran peace talks",
    "url": "https://www.investing.com/news/forex-news/asia-fx-dollar-subdued-amid-iran-ceasefire-uncertainty-china-mixed-pmi-in-focus-4718007",
    "sentiment_score": -0.2,
    "impact": "MEDIUM",
    "keywords": [
      "safe-haven dollar",
      "Iran talks",
      "uncertainty"
    ],
    "fetched_at": "2026-06-03T04:09:49.662664+00:00"
  },
  {
    "source": "Mining.com",
    "headline": "Gold Fields, Cree First Nation sign IBA for Windfall project in\u00a0Quebec",
    "url": "https://www.mining.com/gold-fields-cree-first-nation-sign-iba-for-windfall-project-in-quebec/",
    "sentiment_score": 0.0,
    "impact": "LOW",
    "keywords": [
      "mining",
      "project",
      "development"
    ],
    "fetched_at": "2026-06-03T04:09:49.662664+00:00"
  },
  {
    "source": "Mining.com",
    "headline": "Copper price: Goldman, Citi make bullish calls on supply woes",
    "url": "https://www.mining.com/copper-price-goldman-citi-make-bullish-calls-on-supply-woes/",
    "sentiment_score": 0.0,
    "impact": "LOW",
    "keywords": [
      "copper",
      "commodities",
      "sector"
    ],
    "fetched_at": "2026-06-03T04:09:49.662664+00:00"
  },
  {
    "source": "Mining.com",
    "headline": "Aya logs bonanza silver hits at Zgounder mine in Morocco",
    "url": "https://www.mining.com/aya-logs-bonanza-silver-hits-at-zgounder-mine-in-morocco/",
    "sentiment_score": 0.0,
    "impact": "LOW",
    "keywords": [
      "silver",
      "mining",
      "sector"
    ],
    "fetched_at": "2026-06-03T04:09:49.662664+00:00"
  },
  {
    "source": "Mining.com",
    "headline": "Tintina soars on $66M backing for Chile copper-gold project",
    "url": "https://www.mining.com/tintina-soars-to-new-high-on-66m-backing-for-chile-copper-gold-project/",
    "sentiment_score": 0.1,
    "impact": "LOW",
    "keywords": [
      "gold mining",
      "investment",
      "project"
    ],
    "fetched_at": "2026-06-03T04:09:49.662664+00:00"
  },
  {
    "source": "Mining.com",
    "headline": "Boroo\u2019s bid to buy former Eagle gold site raises questions among miners",
    "url": "https://www.mining.com/boroos-bid-to-buy-former-eagle-gold-site-raises-questions-among-miners/",
    "sentiment_score": 0.0,
    "impact": "LOW",
    "keywords": [
      "mining",
      "acquisition",
      "sector"
    ],
    "fetched_at": "2026-06-03T04:09:49.662664+00:00"
  },
  {
    "source": "Mining.com",
    "headline": "Gold overtakes US Treasuries in global reserve shift: ECB",
    "url": "https://www.mining.com/gold-overtakes-us-treasuries-in-global-reserve-shift-ecb/",
    "sentiment_score": 0.5,
    "impact": "HIGH",
    "keywords": [
      "central bank demand",
      "reserves",
      "bullish"
    ],
    "fetched_at": "2026-06-03T04:09:49.662664+00:00"
  },
  {
    "source": "Mining.com",
    "headline": "Miners urge gov\u2019t aid to challenge China\u2019s rare earth dominance",
    "url": "https://www.mining.com/rare-earth-miners-say-market-needs-govt-support-to-break-chinas-grip/",
    "sentiment_score": 0.0,
    "impact": "LOW",
    "keywords": [
      "rare earth",
      "geopolitics",
      "sector"
    ],
    "fetched_at": "2026-06-03T04:09:49.662664+00:00"
  },
  {
    "source": "Mining.com",
    "headline": "Elliot pushes Australia\u2019s top gold miner to weigh sale option",
    "url": "https://www.mining.com/elliot-pushes-australias-top-gold-miner-to-weigh-sale-option/",
    "sentiment_score": 0.0,
    "impact": "LOW",
    "keywords": [
      "mining",
      "M&A",
      "sector"
    ],
    "fetched_at": "2026-06-03T04:09:49.662664+00:00"
  },
  {
    "source": "FinancialJuice",
    "headline": "Russia-installed Donetsk leader: 7 killed, 11 hurt after drone strikes bus",
    "url": "https://www.financialjuice.com/News/9616671/Russia-installed-Donetsk-leader-7-killed-11-hurt-after-drone-strikes-bus.aspx?xy=rss",
    "sentiment_score": 0.3,
    "impact": "LOW",
    "keywords": [
      "geopolitical",
      "Russia",
      "conflict"
    ],
    "fetched_at": "2026-06-03T04:11:49.118999+00:00"
  },
  {
    "source": "FinancialJuice",
    "headline": "Iran peace deal would not derail case for ECB rate increase, says central banker Pierre Wunsch - FT",
    "url": "https://www.financialjuice.com/News/9616670/Iran-peace-deal-would-not-derail-case-for-ECB-rate-increase-says-central-banker-Pierre-Wunsch---FT.aspx?xy=rss",
    "sentiment_score": -0.4,
    "impact": "MEDIUM",
    "keywords": [
      "ECB",
      "rate increase",
      "hawkish"
    ],
    "fetched_at": "2026-06-03T04:11:49.118999+00:00"
  },
  {
    "source": "FinancialJuice",
    "headline": "Russia shoots down 50 drones over Leningrad region overnight: governor",
    "url": "https://www.financialjuice.com/News/9616629/Russia-shoots-down-50-drones-over-Leningrad-region-overnight-governor.aspx?xy=rss",
    "sentiment_score": 0.2,
    "impact": "LOW",
    "keywords": [
      "geopolitical",
      "Russia",
      "conflict"
    ],
    "fetched_at": "2026-06-03T04:11:49.118999+00:00"
  },
  {
    "source": "FinancialJuice",
    "headline": "Republican Jim Desmond projected to move forward to November general election in California's 48th congressional district, DDHQ says",
    "url": "https://www.financialjuice.com/News/9616627/Republican-Jim-Desmond-projected-to-move-forward-to-November-general-election-in-Californias-48th-congressional-district-DDHQ-says.aspx?xy=rss",
    "sentiment_score": 0.0,
    "impact": "LOW",
    "keywords": [
      "US politics",
      "election",
      "domestic"
    ],
    "fetched_at": "2026-06-03T04:11:49.118999+00:00"
  },
  {
    "source": "FinancialJuice",
    "headline": "Pakistan federal budget unlikely to be presented on June 5: government source, local media",
    "url": "https://www.financialjuice.com/News/9616625/Pakistan-federal-budget-unlikely-to-be-presented-on-June-5-government-source-local-media.aspx?xy=rss",
    "sentiment_score": 0.0,
    "impact": "LOW",
    "keywords": [
      "Pakistan",
      "budget",
      "domestic"
    ],
    "fetched_at": "2026-06-03T04:11:49.118999+00:00"
  },
  {
    "source": "FinancialJuice",
    "headline": "China finance ministry sells 1-month bills at 0.8087% yield: traders",
    "url": "https://www.financialjuice.com/News/9616619/China-finance-ministry-sells-1-month-bills-at-08087-yield-traders.aspx?xy=rss",
    "sentiment_score": -0.2,
    "impact": "LOW",
    "keywords": [
      "China",
      "monetary tightening",
      "rates"
    ],
    "fetched_at": "2026-06-03T04:11:49.118999+00:00"
  },
  {
    "source": "FinancialJuice",
    "headline": "China finance ministry issues 30-year ultra-long special treasury bonds at 2.2046% yield: traders",
    "url": "https://www.financialjuice.com/News/9616618/China-finance-ministry-issues-30-year-ultra-long-special-treasury-bonds-at-22046-yield-traders.aspx?xy=rss",
    "sentiment_score": -0.3,
    "impact": "MEDIUM",
    "keywords": [
      "China",
      "bond issuance",
      "liquidity"
    ],
    "fetched_at": "2026-06-03T04:11:49.118999+00:00"
  },
  {
    "source": "FinancialJuice",
    "headline": "Volume of China cbank's reverse repos via open market operations hits zero for first time since August 7, 2024: source calculation",
    "url": "https://www.financialjuice.com/News/9616593/Volume-of-China-cbanks-reverse-repos-via-open-market-operations-hits-zero-for-first-time-since-August-7-2024-source-calculation.aspx?xy=rss",
    "sentiment_score": -0.5,
    "impact": "MEDIUM",
    "keywords": [
      "China",
      "liquidity withdrawal",
      "monetary tightening"
    ],
    "fetched_at": "2026-06-03T04:11:49.118999+00:00"
  },
  {
    "source": "FinancialJuice",
    "headline": "Russia shoots down 30 drones over Leningrad region: governor",
    "url": "https://www.financialjuice.com/News/9616592/Russia-shoots-down-30-drones-over-Leningrad-region-governor.aspx?xy=rss",
    "sentiment_score": 0.2,
    "impact": "LOW",
    "keywords": [
      "geopolitical",
      "Russia",
      "conflict"
    ],
    "fetched_at": "2026-06-03T04:11:49.118999+00:00"
  },
  {
    "source": "FinancialJuice",
    "headline": "Drones strike Michurinsk in central Russia's Tambov region: governor",
    "url": "https://www.financialjuice.com/News/9616563/Drones-strike-Michurinsk-in-central-Russias-Tambov-region-governor.aspx?xy=rss",
    "sentiment_score": 0.2,
    "impact": "LOW",
    "keywords": [
      "geopolitical",
      "Russia",
      "conflict"
    ],
    "fetched_at": "2026-06-03T04:11:49.118999+00:00"
  },
  {
    "source": "MarketWatch Top",
    "headline": "The S&P 500 climbs for a 9th straight day \u2014 but the \u2018breadth paradox\u2019 is sending a rare warning",
    "url": "https://www.marketwatch.com/story/s-p-500-climbing-for-9th-straight-day-but-breadth-sends-a-rare-warning-1577195d?mod=mw_rss_topstories",
    "sentiment_score": -0.3,
    "impact": "MEDIUM",
    "keywords": [
      "equity rally",
      "risk appetite",
      "stocks"
    ],
    "fetched_at": "2026-06-03T04:11:49.118999+00:00"
  },
  {
    "source": "Investing.com Forex",
    "headline": "U.S. dollar little changed as mixed messaging on Iran talks boost uncertainty",
    "url": "https://www.investing.com/news/forex-news/dollar-steady-amid-mixed-signals-on-usiran-talks-4720844",
    "sentiment_score": 0.4,
    "impact": "MEDIUM",
    "keywords": [
      "USD weakness",
      "Iran uncertainty",
      "safe haven"
    ],
    "fetched_at": "2026-06-03T04:11:49.118999+00:00"
  },
  {
    "source": "Investing.com Forex",
    "headline": "Canadian dollar holds near multi-week low on weak data",
    "url": "https://www.investing.com/news/forex-news/canadian-dollar-holds-near-multiweek-low-on-weak-data-93CH-4722732",
    "sentiment_score": 0.3,
    "impact": "MEDIUM",
    "keywords": [
      "CAD weakness",
      "risk off",
      "safe haven"
    ],
    "fetched_at": "2026-06-03T04:11:49.118999+00:00"
  },
  {
    "source": "Investing.com Forex",
    "headline": "Improving macro backdrop set to keep dollar resilient, BCA says",
    "url": "https://www.investing.com/news/forex-news/improving-macro-backdrop-set-to-keep-dollar-resilient-bca-says-4722053",
    "sentiment_score": -0.5,
    "impact": "MEDIUM",
    "keywords": [
      "dollar strength",
      "macro resilience",
      "USD"
    ],
    "fetched_at": "2026-06-03T04:11:49.118999+00:00"
  },
  {
    "source": "Investing.com Forex",
    "headline": "Sterling today: Pound edges higher as Dollar softens on Gulf uncertainty",
    "url": "https://www.investing.com/news/forex-news/sterling-today-pound-edges-higher-as-dollar-softens-on-gulf-uncertainty-4721662",
    "sentiment_score": 0.3,
    "impact": "MEDIUM",
    "keywords": [
      "dollar weakness",
      "GBP strength",
      "risk off"
    ],
    "fetched_at": "2026-06-03T04:11:49.118999+00:00"
  },
  {
    "source": "Investing.com Forex",
    "headline": "Dollar ticks up on safe haven demand amid uncertainty over U.S.-Iran peace talks",
    "url": "https://www.investing.com/news/forex-news/asia-fx-dollar-subdued-amid-iran-ceasefire-uncertainty-china-mixed-pmi-in-focus-4718007",
    "sentiment_score": -0.3,
    "impact": "MEDIUM",
    "keywords": [
      "dollar strength",
      "safe haven",
      "USD"
    ],
    "fetched_at": "2026-06-03T04:11:49.118999+00:00"
  },
  {
    "source": "Mining.com",
    "headline": "Gold Fields, Cree First Nation sign IBA for Windfall project in\u00a0Quebec",
    "url": "https://www.mining.com/gold-fields-cree-first-nation-sign-iba-for-windfall-project-in-quebec/",
    "sentiment_score": 0.0,
    "impact": "LOW",
    "keywords": [
      "gold mining",
      "project development",
      "sector"
    ],
    "fetched_at": "2026-06-03T04:11:49.118999+00:00"
  },
  {
    "source": "Mining.com",
    "headline": "Copper price: Goldman, Citi make bullish calls on supply woes",
    "url": "https://www.mining.com/copper-price-goldman-citi-make-bullish-calls-on-supply-woes/",
    "sentiment_score": 0.0,
    "impact": "LOW",
    "keywords": [
      "copper",
      "mining sector",
      "commodities"
    ],
    "fetched_at": "2026-06-03T04:11:49.118999+00:00"
  },
  {
    "source": "Mining.com",
    "headline": "Aya logs bonanza silver hits at Zgounder mine in Morocco",
    "url": "https://www.mining.com/aya-logs-bonanza-silver-hits-at-zgounder-mine-in-morocco/",
    "sentiment_score": 0.0,
    "impact": "LOW",
    "keywords": [
      "silver mining",
      "sector news",
      "exploration"
    ],
    "fetched_at": "2026-06-03T04:11:49.118999+00:00"
  },
  {
    "source": "Mining.com",
    "headline": "Tintina soars on $66M backing for Chile copper-gold project",
    "url": "https://www.mining.com/tintina-soars-to-new-high-on-66m-backing-for-chile-copper-gold-project/",
    "sentiment_score": 0.0,
    "impact": "LOW",
    "keywords": [
      "mining",
      "copper-gold project",
      "sector"
    ],
    "fetched_at": "2026-06-03T04:11:49.118999+00:00"
  },
  {
    "source": "Mining.com",
    "headline": "Boroo\u2019s bid to buy former Eagle gold site raises questions among miners",
    "url": "https://www.mining.com/boroos-bid-to-buy-former-eagle-gold-site-raises-questions-among-miners/",
    "sentiment_score": 0.0,
    "impact": "LOW",
    "keywords": [
      "gold mining",
      "M&A",
      "sector"
    ],
    "fetched_at": "2026-06-03T04:11:49.118999+00:00"
  },
  {
    "source": "Mining.com",
    "headline": "Gold overtakes US Treasuries in global reserve shift: ECB",
    "url": "https://www.mining.com/gold-overtakes-us-treasuries-in-global-reserve-shift-ecb/",
    "sentiment_score": 0.7,
    "impact": "HIGH",
    "keywords": [
      "reserve diversification",
      "ECB",
      "gold demand"
    ],
    "fetched_at": "2026-06-03T04:11:49.118999+00:00"
  },
  {
    "source": "Mining.com",
    "headline": "Miners urge gov\u2019t aid to challenge China\u2019s rare earth dominance",
    "url": "https://www.mining.com/rare-earth-miners-say-market-needs-govt-support-to-break-chinas-grip/",
    "sentiment_score": 0.0,
    "impact": "LOW",
    "keywords": [
      "rare earth",
      "mining sector",
      "geopolitics"
    ],
    "fetched_at": "2026-06-03T04:11:49.118999+00:00"
  },
  {
    "source": "Mining.com",
    "headline": "Elliot pushes Australia\u2019s top gold miner to weigh sale option",
    "url": "https://www.mining.com/elliot-pushes-australias-top-gold-miner-to-weigh-sale-option/",
    "sentiment_score": 0.0,
    "impact": "LOW",
    "keywords": [
      "gold mining",
      "M&A",
      "activist investor"
    ],
    "fetched_at": "2026-06-03T04:11:49.118999+00:00"
  },
  {
    "source": "FinancialJuice",
    "headline": "Russia-installed Donetsk leader: 7 killed, 11 hurt after drone strikes bus",
    "url": "https://www.financialjuice.com/News/9616671/Russia-installed-Donetsk-leader-7-killed-11-hurt-after-drone-strikes-bus.aspx?xy=rss",
    "sentiment_score": 0.6,
    "impact": "MEDIUM",
    "keywords": [
      "geopolitical risk",
      "Russia",
      "conflict"
    ],
    "fetched_at": "2026-06-03T04:13:25.257025+00:00"
  },
  {
    "source": "FinancialJuice",
    "headline": "Iran peace deal would not derail case for ECB rate increase, says central banker Pierre Wunsch - FT",
    "url": "https://www.financialjuice.com/News/9616670/Iran-peace-deal-would-not-derail-case-for-ECB-rate-increase-says-central-banker-Pierre-Wunsch---FT.aspx?xy=rss",
    "sentiment_score": -0.5,
    "impact": "MEDIUM",
    "keywords": [
      "ECB rate increase",
      "stronger euro",
      "hawkish"
    ],
    "fetched_at": "2026-06-03T04:13:25.257025+00:00"
  },
  {
    "source": "FinancialJuice",
    "headline": "Russia shoots down 50 drones over Leningrad region overnight: governor",
    "url": "https://www.financialjuice.com/News/9616629/Russia-shoots-down-50-drones-over-Leningrad-region-overnight-governor.aspx?xy=rss",
    "sentiment_score": 0.5,
    "impact": "MEDIUM",
    "keywords": [
      "geopolitical tension",
      "Russia",
      "safe haven"
    ],
    "fetched_at": "2026-06-03T04:13:25.257025+00:00"
  },
  {
    "source": "FinancialJuice",
    "headline": "Republican Jim Desmond projected to move forward to November general election in California's 48th congressional district, DDHQ says",
    "url": "https://www.financialjuice.com/News/9616627/Republican-Jim-Desmond-projected-to-move-forward-to-November-general-election-in-Californias-48th-congressional-district-DDHQ-says.aspx?xy=rss",
    "sentiment_score": 0.0,
    "impact": "LOW",
    "keywords": [
      "US election",
      "domestic politics"
    ],
    "fetched_at": "2026-06-03T04:13:25.257025+00:00"
  },
  {
    "source": "FinancialJuice",
    "headline": "Pakistan federal budget unlikely to be presented on June 5: government source, local media",
    "url": "https://www.financialjuice.com/News/9616625/Pakistan-federal-budget-unlikely-to-be-presented-on-June-5-government-source-local-media.aspx?xy=rss",
    "sentiment_score": 0.0,
    "impact": "LOW",
    "keywords": [
      "Pakistan budget",
      "emerging market"
    ],
    "fetched_at": "2026-06-03T04:13:25.257025+00:00"
  },
  {
    "source": "FinancialJuice",
    "headline": "China finance ministry sells 1-month bills at 0.8087% yield: traders",
    "url": "https://www.financialjuice.com/News/9616619/China-finance-ministry-sells-1-month-bills-at-08087-yield-traders.aspx?xy=rss",
    "sentiment_score": -0.3,
    "impact": "LOW",
    "keywords": [
      "China liquidity tightening",
      "economic slowdown"
    ],
    "fetched_at": "2026-06-03T04:13:25.257025+00:00"
  },
  {
    "source": "FinancialJuice",
    "headline": "China finance ministry issues 30-year ultra-long special treasury bonds at 2.2046% yield: traders",
    "url": "https://www.financialjuice.com/News/9616618/China-finance-ministry-issues-30-year-ultra-long-special-treasury-bonds-at-22046-yield-traders.aspx?xy=rss",
    "sentiment_score": -0.2,
    "impact": "LOW",
    "keywords": [
      "China bond yield",
      "monetary policy"
    ],
    "fetched_at": "2026-06-03T04:13:25.257025+00:00"
  },
  {
    "source": "FinancialJuice",
    "headline": "Volume of China cbank's reverse repos via open market operations hits zero for first time since August 7, 2024: source calculation",
    "url": "https://www.financialjuice.com/News/9616593/Volume-of-China-cbanks-reverse-repos-via-open-market-operations-hits-zero-for-first-time-since-August-7-2024-source-calculation.aspx?xy=rss",
    "sentiment_score": -0.5,
    "impact": "MEDIUM",
    "keywords": [
      "China liquidity withdrawal",
      "monetary tightening"
    ],
    "fetched_at": "2026-06-03T04:13:25.257025+00:00"
  },
  {
    "source": "FinancialJuice",
    "headline": "Russia shoots down 30 drones over Leningrad region: governor",
    "url": "https://www.financialjuice.com/News/9616592/Russia-shoots-down-30-drones-over-Leningrad-region-governor.aspx?xy=rss",
    "sentiment_score": 0.5,
    "impact": "MEDIUM",
    "keywords": [
      "geopolitical risk",
      "Russia",
      "safe haven"
    ],
    "fetched_at": "2026-06-03T04:13:25.257025+00:00"
  },
  {
    "source": "FinancialJuice",
    "headline": "Drones strike Michurinsk in central Russia's Tambov region: governor",
    "url": "https://www.financialjuice.com/News/9616563/Drones-strike-Michurinsk-in-central-Russias-Tambov-region-governor.aspx?xy=rss",
    "sentiment_score": 0.5,
    "impact": "MEDIUM",
    "keywords": [
      "geopolitical tension",
      "conflict",
      "safe haven"
    ],
    "fetched_at": "2026-06-03T04:13:25.257025+00:00"
  },
  {
    "source": "MarketWatch Top",
    "headline": "The S&P 500 climbs for a 9th straight day \u2014 but the \u2018breadth paradox\u2019 is sending a rare warning",
    "url": "https://www.marketwatch.com/story/s-p-500-climbing-for-9th-straight-day-but-breadth-sends-a-rare-warning-1577195d?mod=mw_rss_topstories",
    "sentiment_score": -0.3,
    "impact": "LOW",
    "keywords": [
      "stock market strength",
      "risk appetite"
    ],
    "fetched_at": "2026-06-03T04:13:25.257025+00:00"
  },
  {
    "source": "Investing.com Forex",
    "headline": "U.S. dollar little changed as mixed messaging on Iran talks boost uncertainty",
    "url": "https://www.investing.com/news/forex-news/dollar-steady-amid-mixed-signals-on-usiran-talks-4720844",
    "sentiment_score": 0.3,
    "impact": "MEDIUM",
    "keywords": [
      "dollar weakness",
      "Iran uncertainty",
      "safe haven"
    ],
    "fetched_at": "2026-06-03T04:13:25.257025+00:00"
  },
  {
    "source": "Investing.com Forex",
    "headline": "Canadian dollar holds near multi-week low on weak data",
    "url": "https://www.investing.com/news/forex-news/canadian-dollar-holds-near-multiweek-low-on-weak-data-93CH-4722732",
    "sentiment_score": -0.2,
    "impact": "LOW",
    "keywords": [
      "CAD weakness",
      "dollar strength"
    ],
    "fetched_at": "2026-06-03T04:13:25.257025+00:00"
  },
  {
    "source": "Investing.com Forex",
    "headline": "Improving macro backdrop set to keep dollar resilient, BCA says",
    "url": "https://www.investing.com/news/forex-news/improving-macro-backdrop-set-to-keep-dollar-resilient-bca-says-4722053",
    "sentiment_score": -0.4,
    "impact": "MEDIUM",
    "keywords": [
      "dollar resilience",
      "strong macro",
      "risk off"
    ],
    "fetched_at": "2026-06-03T04:13:25.257025+00:00"
  },
  {
    "source": "Investing.com Forex",
    "headline": "Sterling today: Pound edges higher as Dollar softens on Gulf uncertainty",
    "url": "https://www.investing.com/news/forex-news/sterling-today-pound-edges-higher-as-dollar-softens-on-gulf-uncertainty-4721662",
    "sentiment_score": 0.2,
    "impact": "LOW",
    "keywords": [
      "dollar weakness",
      "uncertainty",
      "gold support"
    ],
    "fetched_at": "2026-06-03T04:13:25.257025+00:00"
  },
  {
    "source": "Investing.com Forex",
    "headline": "Dollar ticks up on safe haven demand amid uncertainty over U.S.-Iran peace talks",
    "url": "https://www.investing.com/news/forex-news/asia-fx-dollar-subdued-amid-iran-ceasefire-uncertainty-china-mixed-pmi-in-focus-4718007",
    "sentiment_score": -0.4,
    "impact": "MEDIUM",
    "keywords": [
      "safe haven dollar",
      "risk off",
      "Iran talks"
    ],
    "fetched_at": "2026-06-03T04:13:25.257025+00:00"
  },
  {
    "source": "Mining.com",
    "headline": "Gold Fields, Cree First Nation sign IBA for Windfall project in\u00a0Quebec",
    "url": "https://www.mining.com/gold-fields-cree-first-nation-sign-iba-for-windfall-project-in-quebec/",
    "sentiment_score": 0.0,
    "impact": "LOW",
    "keywords": [
      "mining project",
      "sector specific"
    ],
    "fetched_at": "2026-06-03T04:13:25.257025+00:00"
  },
  {
    "source": "Mining.com",
    "headline": "Copper price: Goldman, Citi make bullish calls on supply woes",
    "url": "https://www.mining.com/copper-price-goldman-citi-make-bullish-calls-on-supply-woes/",
    "sentiment_score": 0.0,
    "impact": "LOW",
    "keywords": [
      "copper",
      "different commodity"
    ],
    "fetched_at": "2026-06-03T04:13:25.257025+00:00"
  },
  {
    "source": "Mining.com",
    "headline": "Aya logs bonanza silver hits at Zgounder mine in Morocco",
    "url": "https://www.mining.com/aya-logs-bonanza-silver-hits-at-zgounder-mine-in-morocco/",
    "sentiment_score": 0.0,
    "impact": "LOW",
    "keywords": [
      "silver",
      "mining exploration"
    ],
    "fetched_at": "2026-06-03T04:13:25.257025+00:00"
  },
  {
    "source": "Mining.com",
    "headline": "Tintina soars on $66M backing for Chile copper-gold project",
    "url": "https://www.mining.com/tintina-soars-to-new-high-on-66m-backing-for-chile-copper-gold-project/",
    "sentiment_score": 0.1,
    "impact": "LOW",
    "keywords": [
      "gold project",
      "mining development"
    ],
    "fetched_at": "2026-06-03T04:13:25.257025+00:00"
  },
  {
    "source": "Mining.com",
    "headline": "Boroo\u2019s bid to buy former Eagle gold site raises questions among miners",
    "url": "https://www.mining.com/boroos-bid-to-buy-former-eagle-gold-site-raises-questions-among-miners/",
    "sentiment_score": 0.0,
    "impact": "LOW",
    "keywords": [
      "mining M&A",
      "sector specific"
    ],
    "fetched_at": "2026-06-03T04:13:25.257025+00:00"
  },
  {
    "source": "Mining.com",
    "headline": "Gold overtakes US Treasuries in global reserve shift: ECB",
    "url": "https://www.mining.com/gold-overtakes-us-treasuries-in-global-reserve-shift-ecb/",
    "sentiment_score": 0.8,
    "impact": "HIGH",
    "keywords": [
      "gold reserves",
      "currency shift",
      "central bank demand"
    ],
    "fetched_at": "2026-06-03T04:13:25.257025+00:00"
  },
  {
    "source": "Mining.com",
    "headline": "Miners urge gov\u2019t aid to challenge China\u2019s rare earth dominance",
    "url": "https://www.mining.com/rare-earth-miners-say-market-needs-govt-support-to-break-chinas-grip/",
    "sentiment_score": 0.0,
    "impact": "LOW",
    "keywords": [
      "rare earth",
      "different sector"
    ],
    "fetched_at": "2026-06-03T04:13:25.257025+00:00"
  },
  {
    "source": "Mining.com",
    "headline": "Elliot pushes Australia\u2019s top gold miner to weigh sale option",
    "url": "https://www.mining.com/elliot-pushes-australias-top-gold-miner-to-weigh-sale-option/",
    "sentiment_score": 0.1,
    "impact": "LOW",
    "keywords": [
      "mining M&A",
      "industry consolidation"
    ],
    "fetched_at": "2026-06-03T04:13:25.257025+00:00"
  },
  {
    "source": "FinancialJuice",
    "headline": "Russia-installed Donetsk leader: 7 killed, 11 hurt after drone strikes bus",
    "url": "https://www.financialjuice.com/News/9616671/Russia-installed-Donetsk-leader-7-killed-11-hurt-after-drone-strikes-bus.aspx?xy=rss",
    "sentiment_score": 0.6,
    "impact": "MEDIUM",
    "keywords": [
      "geopolitical risk",
      "Russia-Ukraine",
      "safe haven"
    ],
    "fetched_at": "2026-06-03T04:28:26.246523+00:00"
  },
  {
    "source": "FinancialJuice",
    "headline": "Iran peace deal would not derail case for ECB rate increase, says central banker Pierre Wunsch - FT",
    "url": "https://www.financialjuice.com/News/9616670/Iran-peace-deal-would-not-derail-case-for-ECB-rate-increase-says-central-banker-Pierre-Wunsch---FT.aspx?xy=rss",
    "sentiment_score": -0.5,
    "impact": "MEDIUM",
    "keywords": [
      "ECB rate increase",
      "stronger dollar",
      "hawkish"
    ],
    "fetched_at": "2026-06-03T04:28:26.246523+00:00"
  },
  {
    "source": "FinancialJuice",
    "headline": "Russia shoots down 50 drones over Leningrad region overnight: governor",
    "url": "https://www.financialjuice.com/News/9616629/Russia-shoots-down-50-drones-over-Leningrad-region-overnight-governor.aspx?xy=rss",
    "sentiment_score": 0.5,
    "impact": "MEDIUM",
    "keywords": [
      "geopolitical tension",
      "safe haven",
      "Russia"
    ],
    "fetched_at": "2026-06-03T04:28:26.246523+00:00"
  },
  {
    "source": "FinancialJuice",
    "headline": "Republican Jim Desmond projected to move forward to November general election in California's 48th congressional district, DDHQ says",
    "url": "https://www.financialjuice.com/News/9616627/Republican-Jim-Desmond-projected-to-move-forward-to-November-general-election-in-Californias-48th-congressional-district-DDHQ-says.aspx?xy=rss",
    "sentiment_score": 0.0,
    "impact": "LOW",
    "keywords": [
      "US politics",
      "domestic election",
      "irrelevant"
    ],
    "fetched_at": "2026-06-03T04:28:26.246523+00:00"
  },
  {
    "source": "FinancialJuice",
    "headline": "Pakistan federal budget unlikely to be presented on June 5: government source, local media",
    "url": "https://www.financialjuice.com/News/9616625/Pakistan-federal-budget-unlikely-to-be-presented-on-June-5-government-source-local-media.aspx?xy=rss",
    "sentiment_score": 0.0,
    "impact": "LOW",
    "keywords": [
      "Pakistan budget",
      "emerging market",
      "unrelated"
    ],
    "fetched_at": "2026-06-03T04:28:26.246523+00:00"
  },
  {
    "source": "FinancialJuice",
    "headline": "China finance ministry sells 1-month bills at 0.8087% yield: traders",
    "url": "https://www.financialjuice.com/News/9616619/China-finance-ministry-sells-1-month-bills-at-08087-yield-traders.aspx?xy=rss",
    "sentiment_score": -0.3,
    "impact": "LOW",
    "keywords": [
      "China rates",
      "yield",
      "monetary tightening"
    ],
    "fetched_at": "2026-06-03T04:28:26.246523+00:00"
  },
  {
    "source": "FinancialJuice",
    "headline": "China finance ministry issues 30-year ultra-long special treasury bonds at 2.2046% yield: traders",
    "url": "https://www.financialjuice.com/News/9616618/China-finance-ministry-issues-30-year-ultra-long-special-treasury-bonds-at-22046-yield-traders.aspx?xy=rss",
    "sentiment_score": -0.4,
    "impact": "MEDIUM",
    "keywords": [
      "China bonds",
      "yields rising",
      "tighter policy"
    ],
    "fetched_at": "2026-06-03T04:28:26.246523+00:00"
  },
  {
    "source": "FinancialJuice",
    "headline": "Volume of China cbank's reverse repos via open market operations hits zero for first time since August 7, 2024: source calculation",
    "url": "https://www.financialjuice.com/News/9616593/Volume-of-China-cbanks-reverse-repos-via-open-market-operations-hits-zero-for-first-time-since-August-7-2024-source-calculation.aspx?xy=rss",
    "sentiment_score": -0.6,
    "impact": "MEDIUM",
    "keywords": [
      "China liquidity",
      "monetary tightening",
      "no stimulus"
    ],
    "fetched_at": "2026-06-03T04:28:26.246523+00:00"
  },
  {
    "source": "FinancialJuice",
    "headline": "Russia shoots down 30 drones over Leningrad region: governor",
    "url": "https://www.financialjuice.com/News/9616592/Russia-shoots-down-30-drones-over-Leningrad-region-governor.aspx?xy=rss",
    "sentiment_score": 0.5,
    "impact": "MEDIUM",
    "keywords": [
      "geopolitical risk",
      "Russia",
      "safe haven"
    ],
    "fetched_at": "2026-06-03T04:28:26.246523+00:00"
  },
  {
    "source": "FinancialJuice",
    "headline": "Drones strike Michurinsk in central Russia's Tambov region: governor",
    "url": "https://www.financialjuice.com/News/9616563/Drones-strike-Michurinsk-in-central-Russias-Tambov-region-governor.aspx?xy=rss",
    "sentiment_score": 0.5,
    "impact": "MEDIUM",
    "keywords": [
      "geopolitical tension",
      "Russia",
      "safe haven"
    ],
    "fetched_at": "2026-06-03T04:28:26.246523+00:00"
  },
  {
    "source": "MarketWatch Top",
    "headline": "The S&P 500 climbs for a 9th straight day \u2014 but the \u2018breadth paradox\u2019 is sending a rare warning",
    "url": "https://www.marketwatch.com/story/s-p-500-climbing-for-9th-straight-day-but-breadth-sends-a-rare-warning-1577195d?mod=mw_rss_topstories",
    "sentiment_score": -0.4,
    "impact": "MEDIUM",
    "keywords": [
      "equity strength",
      "risk appetite",
      "dollar demand"
    ],
    "fetched_at": "2026-06-03T04:28:26.246523+00:00"
  },
  {
    "source": "Investing.com Forex",
    "headline": "U.S. dollar little changed as mixed messaging on Iran talks boost uncertainty",
    "url": "https://www.investing.com/news/forex-news/dollar-steady-amid-mixed-signals-on-usiran-talks-4720844",
    "sentiment_score": 0.3,
    "impact": "MEDIUM",
    "keywords": [
      "dollar weakness",
      "Iran uncertainty",
      "safe haven"
    ],
    "fetched_at": "2026-06-03T04:28:26.246523+00:00"
  },
  {
    "source": "Investing.com Forex",
    "headline": "Canadian dollar holds near multi-week low on weak data",
    "url": "https://www.investing.com/news/forex-news/canadian-dollar-holds-near-multiweek-low-on-weak-data-93CH-4722732",
    "sentiment_score": -0.2,
    "impact": "LOW",
    "keywords": [
      "CAD weakness",
      "commodity currency",
      "minor impact"
    ],
    "fetched_at": "2026-06-03T04:28:26.246523+00:00"
  },
  {
    "source": "Investing.com Forex",
    "headline": "Improving macro backdrop set to keep dollar resilient, BCA says",
    "url": "https://www.investing.com/news/forex-news/improving-macro-backdrop-set-to-keep-dollar-resilient-bca-says-4722053",
    "sentiment_score": -0.5,
    "impact": "MEDIUM",
    "keywords": [
      "strong dollar",
      "resilient macro",
      "bearish gold"
    ],
    "fetched_at": "2026-06-03T04:28:26.246523+00:00"
  },
  {
    "source": "Investing.com Forex",
    "headline": "Sterling today: Pound edges higher as Dollar softens on Gulf uncertainty",
    "url": "https://www.investing.com/news/forex-news/sterling-today-pound-edges-higher-as-dollar-softens-on-gulf-uncertainty-4721662",
    "sentiment_score": -0.3,
    "impact": "LOW",
    "keywords": [
      "dollar softness",
      "Gulf uncertainty",
      "minor impact"
    ],
    "fetched_at": "2026-06-03T04:28:26.246523+00:00"
  },
  {
    "source": "Investing.com Forex",
    "headline": "Dollar ticks up on safe haven demand amid uncertainty over U.S.-Iran peace talks",
    "url": "https://www.investing.com/news/forex-news/asia-fx-dollar-subdued-amid-iran-ceasefire-uncertainty-china-mixed-pmi-in-focus-4718007",
    "sentiment_score": -0.4,
    "impact": "MEDIUM",
    "keywords": [
      "dollar strength",
      "safe haven",
      "less gold appeal"
    ],
    "fetched_at": "2026-06-03T04:28:26.246523+00:00"
  },
  {
    "source": "Mining.com",
    "headline": "Gold Fields, Cree First Nation sign IBA for Windfall project in\u00a0Quebec",
    "url": "https://www.mining.com/gold-fields-cree-first-nation-sign-iba-for-windfall-project-in-quebec/",
    "sentiment_score": 0.1,
    "impact": "LOW",
    "keywords": [
      "gold mining",
      "project development",
      "sector news"
    ],
    "fetched_at": "2026-06-03T04:28:26.246523+00:00"
  },
  {
    "source": "Mining.com",
    "headline": "Copper price: Goldman, Citi make bullish calls on supply woes",
    "url": "https://www.mining.com/copper-price-goldman-citi-make-bullish-calls-on-supply-woes/",
    "sentiment_score": 0.0,
    "impact": "LOW",
    "keywords": [
      "copper",
      "mining sector",
      "unrelated commodity"
    ],
    "fetched_at": "2026-06-03T04:28:26.246523+00:00"
  },
  {
    "source": "Mining.com",
    "headline": "Aya logs bonanza silver hits at Zgounder mine in Morocco",
    "url": "https://www.mining.com/aya-logs-bonanza-silver-hits-at-zgounder-mine-in-morocco/",
    "sentiment_score": 0.0,
    "impact": "LOW",
    "keywords": [
      "silver mining",
      "sector news",
      "unrelated"
    ],
    "fetched_at": "2026-06-03T04:28:26.246523+00:00"
  },
  {
    "source": "Mining.com",
    "headline": "Tintina soars on $66M backing for Chile copper-gold project",
    "url": "https://www.mining.com/tintina-soars-to-new-high-on-66m-backing-for-chile-copper-gold-project/",
    "sentiment_score": 0.2,
    "impact": "LOW",
    "keywords": [
      "gold mining",
      "project funding",
      "sector positive"
    ],
    "fetched_at": "2026-06-03T04:28:26.246523+00:00"
  },
  {
    "source": "Mining.com",
    "headline": "Boroo\u2019s bid to buy former Eagle gold site raises questions among miners",
    "url": "https://www.mining.com/boroos-bid-to-buy-former-eagle-gold-site-raises-questions-among-miners/",
    "sentiment_score": 0.0,
    "impact": "LOW",
    "keywords": [
      "gold mining M&A",
      "sector news",
      "neutral"
    ],
    "fetched_at": "2026-06-03T04:28:26.246523+00:00"
  },
  {
    "source": "Mining.com",
    "headline": "Gold overtakes US Treasuries in global reserve shift: ECB",
    "url": "https://www.mining.com/gold-overtakes-us-treasuries-in-global-reserve-shift-ecb/",
    "sentiment_score": 0.7,
    "impact": "HIGH",
    "keywords": [
      "reserve diversification",
      "ECB",
      "bullish structural"
    ],
    "fetched_at": "2026-06-03T04:28:26.246523+00:00"
  },
  {
    "source": "Mining.com",
    "headline": "Miners urge gov\u2019t aid to challenge China\u2019s rare earth dominance",
    "url": "https://www.mining.com/rare-earth-miners-say-market-needs-govt-support-to-break-chinas-grip/",
    "sentiment_score": 0.0,
    "impact": "LOW",
    "keywords": [
      "rare earth",
      "mining policy",
      "unrelated"
    ],
    "fetched_at": "2026-06-03T04:28:26.246523+00:00"
  },
  {
    "source": "Mining.com",
    "headline": "Elliot pushes Australia\u2019s top gold miner to weigh sale option",
    "url": "https://www.mining.com/elliot-pushes-australias-top-gold-miner-to-weigh-sale-option/",
    "sentiment_score": 0.1,
    "impact": "LOW",
    "keywords": [
      "mining M&A",
      "gold sector",
      "minor positive"
    ],
    "fetched_at": "2026-06-03T04:28:26.246523+00:00"
  },
  {
    "source": "FinancialJuice",
    "headline": "Russia-installed Donetsk leader: 7 killed, 11 hurt after drone strikes bus",
    "url": "https://www.financialjuice.com/News/9616671/Russia-installed-Donetsk-leader-7-killed-11-hurt-after-drone-strikes-bus.aspx?xy=rss",
    "sentiment_score": 0.6,
    "impact": "MEDIUM",
    "keywords": [
      "geopolitical risk",
      "Russia-Ukraine",
      "safe haven"
    ],
    "fetched_at": "2026-06-03T04:31:02.178339+00:00"
  },
  {
    "source": "FinancialJuice",
    "headline": "Iran peace deal would not derail case for ECB rate increase, says central banker Pierre Wunsch - FT",
    "url": "https://www.financialjuice.com/News/9616670/Iran-peace-deal-would-not-derail-case-for-ECB-rate-increase-says-central-banker-Pierre-Wunsch---FT.aspx?xy=rss",
    "sentiment_score": -0.4,
    "impact": "MEDIUM",
    "keywords": [
      "ECB rate increase",
      "stronger dollar",
      "monetary tightening"
    ],
    "fetched_at": "2026-06-03T04:31:02.178339+00:00"
  },
  {
    "source": "FinancialJuice",
    "headline": "Russia shoots down 50 drones over Leningrad region overnight: governor",
    "url": "https://www.financialjuice.com/News/9616629/Russia-shoots-down-50-drones-over-Leningrad-region-overnight-governor.aspx?xy=rss",
    "sentiment_score": 0.5,
    "impact": "MEDIUM",
    "keywords": [
      "geopolitical tension",
      "Russia conflict",
      "risk-off"
    ],
    "fetched_at": "2026-06-03T04:31:02.178339+00:00"
  },
  {
    "source": "FinancialJuice",
    "headline": "Republican Jim Desmond projected to move forward to November general election in California's 48th congressional district, DDHQ says",
    "url": "https://www.financialjuice.com/News/9616627/Republican-Jim-Desmond-projected-to-move-forward-to-November-general-election-in-Californias-48th-congressional-district-DDHQ-says.aspx?xy=rss",
    "sentiment_score": 0.0,
    "impact": "LOW",
    "keywords": [
      "US politics",
      "election",
      "domestic"
    ],
    "fetched_at": "2026-06-03T04:31:02.178339+00:00"
  },
  {
    "source": "FinancialJuice",
    "headline": "Pakistan federal budget unlikely to be presented on June 5: government source, local media",
    "url": "https://www.financialjuice.com/News/9616625/Pakistan-federal-budget-unlikely-to-be-presented-on-June-5-government-source-local-media.aspx?xy=rss",
    "sentiment_score": 0.0,
    "impact": "LOW",
    "keywords": [
      "Pakistan budget",
      "fiscal policy",
      "emerging market"
    ],
    "fetched_at": "2026-06-03T04:31:02.178339+00:00"
  },
  {
    "source": "FinancialJuice",
    "headline": "China finance ministry sells 1-month bills at 0.8087% yield: traders",
    "url": "https://www.financialjuice.com/News/9616619/China-finance-ministry-sells-1-month-bills-at-08087-yield-traders.aspx?xy=rss",
    "sentiment_score": -0.3,
    "impact": "LOW",
    "keywords": [
      "China yields",
      "monetary easing",
      "currency pressure"
    ],
    "fetched_at": "2026-06-03T04:31:02.178339+00:00"
  },
  {
    "source": "FinancialJuice",
    "headline": "China finance ministry issues 30-year ultra-long special treasury bonds at 2.2046% yield: traders",
    "url": "https://www.financialjuice.com/News/9616618/China-finance-ministry-issues-30-year-ultra-long-special-treasury-bonds-at-22046-yield-traders.aspx?xy=rss",
    "sentiment_score": -0.2,
    "impact": "LOW",
    "keywords": [
      "China bonds",
      "long-term yields",
      "economic outlook"
    ],
    "fetched_at": "2026-06-03T04:31:02.178339+00:00"
  },
  {
    "source": "FinancialJuice",
    "headline": "Volume of China cbank's reverse repos via open market operations hits zero for first time since August 7, 2024: source calculation",
    "url": "https://www.financialjuice.com/News/9616593/Volume-of-China-cbanks-reverse-repos-via-open-market-operations-hits-zero-for-first-time-since-August-7-2024-source-calculation.aspx?xy=rss",
    "sentiment_score": -0.5,
    "impact": "MEDIUM",
    "keywords": [
      "China liquidity tightening",
      "monetary policy",
      "risk-off equities"
    ],
    "fetched_at": "2026-06-03T04:31:02.178339+00:00"
  },
  {
    "source": "FinancialJuice",
    "headline": "Russia shoots down 30 drones over Leningrad region: governor",
    "url": "https://www.financialjuice.com/News/9616592/Russia-shoots-down-30-drones-over-Leningrad-region-governor.aspx?xy=rss",
    "sentiment_score": 0.5,
    "impact": "MEDIUM",
    "keywords": [
      "geopolitical risk",
      "Russia conflict",
      "safe haven"
    ],
    "fetched_at": "2026-06-03T04:31:02.178339+00:00"
  },
  {
    "source": "FinancialJuice",
    "headline": "Drones strike Michurinsk in central Russia's Tambov region: governor",
    "url": "https://www.financialjuice.com/News/9616563/Drones-strike-Michurinsk-in-central-Russias-Tambov-region-governor.aspx?xy=rss",
    "sentiment_score": 0.6,
    "impact": "MEDIUM",
    "keywords": [
      "geopolitical tension",
      "Russia Ukraine",
      "risk-off"
    ],
    "fetched_at": "2026-06-03T04:31:02.178339+00:00"
  },
  {
    "source": "MarketWatch Top",
    "headline": "The S&P 500 climbs for a 9th straight day \u2014 but the \u2018breadth paradox\u2019 is sending a rare warning",
    "url": "https://www.marketwatch.com/story/s-p-500-climbing-for-9th-straight-day-but-breadth-sends-a-rare-warning-1577195d?mod=mw_rss_topstories",
    "sentiment_score": 0.3,
    "impact": "LOW",
    "keywords": [
      "equity weakness",
      "market breadth",
      "correction signal"
    ],
    "fetched_at": "2026-06-03T04:31:02.178339+00:00"
  },
  {
    "source": "Investing.com Forex",
    "headline": "U.S. dollar little changed as mixed messaging on Iran talks boost uncertainty",
    "url": "https://www.investing.com/news/forex-news/dollar-steady-amid-mixed-signals-on-usiran-talks-4720844",
    "sentiment_score": 0.5,
    "impact": "MEDIUM",
    "keywords": [
      "geopolitical uncertainty",
      "Iran talks",
      "dollar weakness"
    ],
    "fetched_at": "2026-06-03T04:31:02.178339+00:00"
  },
  {
    "source": "Investing.com Forex",
    "headline": "Canadian dollar holds near multi-week low on weak data",
    "url": "https://www.investing.com/news/forex-news/canadian-dollar-holds-near-multiweek-low-on-weak-data-93CH-4722732",
    "sentiment_score": 0.1,
    "impact": "LOW",
    "keywords": [
      "Canadian dollar",
      "weak data",
      "commodity currency"
    ],
    "fetched_at": "2026-06-03T04:31:02.178339+00:00"
  },
  {
    "source": "Investing.com Forex",
    "headline": "Improving macro backdrop set to keep dollar resilient, BCA says",
    "url": "https://www.investing.com/news/forex-news/improving-macro-backdrop-set-to-keep-dollar-resilient-bca-says-4722053",
    "sentiment_score": -0.5,
    "impact": "MEDIUM",
    "keywords": [
      "dollar strength",
      "macro resilience",
      "hawkish outlook"
    ],
    "fetched_at": "2026-06-03T04:31:02.178339+00:00"
  },
  {
    "source": "Investing.com Forex",
    "headline": "Sterling today: Pound edges higher as Dollar softens on Gulf uncertainty",
    "url": "https://www.investing.com/news/forex-news/sterling-today-pound-edges-higher-as-dollar-softens-on-gulf-uncertainty-4721662",
    "sentiment_score": 0.3,
    "impact": "LOW",
    "keywords": [
      "dollar weakness",
      "Gulf uncertainty",
      "safe haven"
    ],
    "fetched_at": "2026-06-03T04:31:02.178339+00:00"
  },
  {
    "source": "Investing.com Forex",
    "headline": "Dollar ticks up on safe haven demand amid uncertainty over U.S.-Iran peace talks",
    "url": "https://www.investing.com/news/forex-news/asia-fx-dollar-subdued-amid-iran-ceasefire-uncertainty-china-mixed-pmi-in-focus-4718007",
    "sentiment_score": -0.4,
    "impact": "MEDIUM",
    "keywords": [
      "safe haven dollar",
      "geopolitical risk",
      "risk aversion"
    ],
    "fetched_at": "2026-06-03T04:31:02.178339+00:00"
  },
  {
    "source": "Mining.com",
    "headline": "Gold Fields, Cree First Nation sign IBA for Windfall project in\u00a0Quebec",
    "url": "https://www.mining.com/gold-fields-cree-first-nation-sign-iba-for-windfall-project-in-quebec/",
    "sentiment_score": 0.0,
    "impact": "LOW",
    "keywords": [
      "gold mining",
      "project development",
      "sectoral"
    ],
    "fetched_at": "2026-06-03T04:31:02.178339+00:00"
  },
  {
    "source": "Mining.com",
    "headline": "Copper price: Goldman, Citi make bullish calls on supply woes",
    "url": "https://www.mining.com/copper-price-goldman-citi-make-bullish-calls-on-supply-woes/",
    "sentiment_score": 0.0,
    "impact": "LOW",
    "keywords": [
      "copper",
      "commodities",
      "mining sector"
    ],
    "fetched_at": "2026-06-03T04:31:02.178339+00:00"
  },
  {
    "source": "Mining.com",
    "headline": "Aya logs bonanza silver hits at Zgounder mine in Morocco",
    "url": "https://www.mining.com/aya-logs-bonanza-silver-hits-at-zgounder-mine-in-morocco/",
    "sentiment_score": 0.0,
    "impact": "LOW",
    "keywords": [
      "silver mining",
      "exploration",
      "sectoral"
    ],
    "fetched_at": "2026-06-03T04:31:02.178339+00:00"
  },
  {
    "source": "Mining.com",
    "headline": "Tintina soars on $66M backing for Chile copper-gold project",
    "url": "https://www.mining.com/tintina-soars-to-new-high-on-66m-backing-for-chile-copper-gold-project/",
    "sentiment_score": 0.0,
    "impact": "LOW",
    "keywords": [
      "copper mining",
      "Chile project",
      "sectoral"
    ],
    "fetched_at": "2026-06-03T04:31:02.178339+00:00"
  },
  {
    "source": "Mining.com",
    "headline": "Boroo\u2019s bid to buy former Eagle gold site raises questions among miners",
    "url": "https://www.mining.com/boroos-bid-to-buy-former-eagle-gold-site-raises-questions-among-miners/",
    "sentiment_score": 0.0,
    "impact": "LOW",
    "keywords": [
      "gold mining",
      "M&A",
      "sectoral"
    ],
    "fetched_at": "2026-06-03T04:31:02.178339+00:00"
  },
  {
    "source": "Mining.com",
    "headline": "Gold overtakes US Treasuries in global reserve shift: ECB",
    "url": "https://www.mining.com/gold-overtakes-us-treasuries-in-global-reserve-shift-ecb/",
    "sentiment_score": 0.8,
    "impact": "HIGH",
    "keywords": [
      "reserve diversification",
      "ECB",
      "institutional demand"
    ],
    "fetched_at": "2026-06-03T04:31:02.178339+00:00"
  },
  {
    "source": "Mining.com",
    "headline": "Miners urge gov\u2019t aid to challenge China\u2019s rare earth dominance",
    "url": "https://www.mining.com/rare-earth-miners-say-market-needs-govt-support-to-break-chinas-grip/",
    "sentiment_score": 0.0,
    "impact": "LOW",
    "keywords": [
      "rare earth",
      "geopolitics",
      "China dominance"
    ],
    "fetched_at": "2026-06-03T04:31:02.178339+00:00"
  },
  {
    "source": "Mining.com",
    "headline": "Elliot pushes Australia\u2019s top gold miner to weigh sale option",
    "url": "https://www.mining.com/elliot-pushes-australias-top-gold-miner-to-weigh-sale-option/",
    "sentiment_score": 0.1,
    "impact": "LOW",
    "keywords": [
      "gold mining",
      "activist pressure",
      "M&A speculation"
    ],
    "fetched_at": "2026-06-03T04:31:02.178339+00:00"
  },
  {
    "source": "FinancialJuice",
    "headline": "Russia shoots down 354 drones overnight: Russian news agencies cite Defense Ministry",
    "url": "https://www.financialjuice.com/News/9616690/Russia-shoots-down-354-drones-overnight-Russian-news-agencies-cite-Defense-Ministry.aspx?xy=rss",
    "sentiment_score": 0.6,
    "impact": "MEDIUM",
    "keywords": [
      "geopolitical risk",
      "Ukraine conflict",
      "safe haven"
    ],
    "fetched_at": "2026-06-03T04:35:18.265391+00:00"
  },
  {
    "source": "FinancialJuice",
    "headline": "Russia-installed Donetsk leader: 7 killed, 11 hurt after drone strikes bus",
    "url": "https://www.financialjuice.com/News/9616671/Russia-installed-Donetsk-leader-7-killed-11-hurt-after-drone-strikes-bus.aspx?xy=rss",
    "sentiment_score": 0.5,
    "impact": "MEDIUM",
    "keywords": [
      "geopolitical tension",
      "risk sentiment",
      "safe haven"
    ],
    "fetched_at": "2026-06-03T04:35:18.265391+00:00"
  },
  {
    "source": "FinancialJuice",
    "headline": "Iran peace deal would not derail case for ECB rate increase, says central banker Pierre Wunsch - FT",
    "url": "https://www.financialjuice.com/News/9616670/Iran-peace-deal-would-not-derail-case-for-ECB-rate-increase-says-central-banker-Pierre-Wunsch---FT.aspx?xy=rss",
    "sentiment_score": -0.3,
    "impact": "LOW",
    "keywords": [
      "ECB rate hike",
      "stronger dollar",
      "rate expectations"
    ],
    "fetched_at": "2026-06-03T04:35:18.265391+00:00"
  },
  {
    "source": "FinancialJuice",
    "headline": "Russia shoots down 50 drones over Leningrad region overnight: governor",
    "url": "https://www.financialjuice.com/News/9616629/Russia-shoots-down-50-drones-over-Leningrad-region-overnight-governor.aspx?xy=rss",
    "sentiment_score": 0.5,
    "impact": "MEDIUM",
    "keywords": [
      "geopolitical risk",
      "conflict escalation",
      "safe haven"
    ],
    "fetched_at": "2026-06-03T04:35:18.265391+00:00"
  },
  {
    "source": "FinancialJuice",
    "headline": "Republican Jim Desmond projected to move forward to November general election in California's 48th congressional district, DDHQ says",
    "url": "https://www.financialjuice.com/News/9616627/Republican-Jim-Desmond-projected-to-move-forward-to-November-general-election-in-Californias-48th-congressional-district-DDHQ-says.aspx?xy=rss",
    "sentiment_score": 0.0,
    "impact": "LOW",
    "keywords": [
      "US politics",
      "domestic election",
      "unrelated"
    ],
    "fetched_at": "2026-06-03T04:35:18.265391+00:00"
  },
  {
    "source": "FinancialJuice",
    "headline": "Pakistan federal budget unlikely to be presented on June 5: government source, local media",
    "url": "https://www.financialjuice.com/News/9616625/Pakistan-federal-budget-unlikely-to-be-presented-on-June-5-government-source-local-media.aspx?xy=rss",
    "sentiment_score": 0.0,
    "impact": "LOW",
    "keywords": [
      "Pakistan budget",
      "emerging market",
      "unrelated"
    ],
    "fetched_at": "2026-06-03T04:35:18.265391+00:00"
  },
  {
    "source": "FinancialJuice",
    "headline": "China finance ministry sells 1-month bills at 0.8087% yield: traders",
    "url": "https://www.financialjuice.com/News/9616619/China-finance-ministry-sells-1-month-bills-at-08087-yield-traders.aspx?xy=rss",
    "sentiment_score": -0.2,
    "impact": "LOW",
    "keywords": [
      "China liquidity",
      "tight monetary",
      "yuan strength"
    ],
    "fetched_at": "2026-06-03T04:35:18.265391+00:00"
  },
  {
    "source": "FinancialJuice",
    "headline": "China finance ministry issues 30-year ultra-long special treasury bonds at 2.2046% yield: traders",
    "url": "https://www.financialjuice.com/News/9616618/China-finance-ministry-issues-30-year-ultra-long-special-treasury-bonds-at-22046-yield-traders.aspx?xy=rss",
    "sentiment_score": -0.3,
    "impact": "MEDIUM",
    "keywords": [
      "China debt issuance",
      "monetary tightening",
      "yuan support"
    ],
    "fetched_at": "2026-06-03T04:35:18.265391+00:00"
  },
  {
    "source": "FinancialJuice",
    "headline": "Volume of China cbank's reverse repos via open market operations hits zero for first time since August 7, 2024: source calculation",
    "url": "https://www.financialjuice.com/News/9616593/Volume-of-China-cbanks-reverse-repos-via-open-market-operations-hits-zero-for-first-time-since-August-7-2024-source-calculation.aspx?xy=rss",
    "sentiment_score": -0.4,
    "impact": "MEDIUM",
    "keywords": [
      "China liquidity drain",
      "monetary tightening",
      "yuan strength"
    ],
    "fetched_at": "2026-06-03T04:35:18.265391+00:00"
  },
  {
    "source": "FinancialJuice",
    "headline": "Russia shoots down 30 drones over Leningrad region: governor",
    "url": "https://www.financialjuice.com/News/9616592/Russia-shoots-down-30-drones-over-Leningrad-region-governor.aspx?xy=rss",
    "sentiment_score": 0.5,
    "impact": "MEDIUM",
    "keywords": [
      "geopolitical risk",
      "conflict",
      "safe haven"
    ],
    "fetched_at": "2026-06-03T04:35:18.265391+00:00"
  },
  {
    "source": "MarketWatch Top",
    "headline": "The S&P 500 climbs for a 9th straight day \u2014 but the \u2018breadth paradox\u2019 is sending a rare warning",
    "url": "https://www.marketwatch.com/story/s-p-500-climbing-for-9th-straight-day-but-breadth-sends-a-rare-warning-1577195d?mod=mw_rss_topstories",
    "sentiment_score": -0.2,
    "impact": "LOW",
    "keywords": [
      "equity strength",
      "risk on",
      "dollar demand"
    ],
    "fetched_at": "2026-06-03T04:35:18.265391+00:00"
  },
  {
    "source": "Investing.com Forex",
    "headline": "U.S. dollar little changed as mixed messaging on Iran talks boost uncertainty",
    "url": "https://www.investing.com/news/forex-news/dollar-steady-amid-mixed-signals-on-usiran-talks-4720844",
    "sentiment_score": 0.3,
    "impact": "MEDIUM",
    "keywords": [
      "Iran uncertainty",
      "geopolitical risk",
      "safe haven"
    ],
    "fetched_at": "2026-06-03T04:35:18.265391+00:00"
  },
  {
    "source": "Investing.com Forex",
    "headline": "Canadian dollar holds near multi-week low on weak data",
    "url": "https://www.investing.com/news/forex-news/canadian-dollar-holds-near-multiweek-low-on-weak-data-93CH-4722732",
    "sentiment_score": 0.2,
    "impact": "LOW",
    "keywords": [
      "currency weakness",
      "risk sentiment",
      "safe haven"
    ],
    "fetched_at": "2026-06-03T04:35:18.265391+00:00"
  },
  {
    "source": "Investing.com Forex",
    "headline": "Improving macro backdrop set to keep dollar resilient, BCA says",
    "url": "https://www.investing.com/news/forex-news/improving-macro-backdrop-set-to-keep-dollar-resilient-bca-says-4722053",
    "sentiment_score": -0.5,
    "impact": "MEDIUM",
    "keywords": [
      "strong dollar",
      "macro improvement",
      "risk on"
    ],
    "fetched_at": "2026-06-03T04:35:18.265391+00:00"
  },
  {
    "source": "Investing.com Forex",
    "headline": "Sterling today: Pound edges higher as Dollar softens on Gulf uncertainty",
    "url": "https://www.investing.com/news/forex-news/sterling-today-pound-edges-higher-as-dollar-softens-on-gulf-uncertainty-4721662",
    "sentiment_score": 0.2,
    "impact": "LOW",
    "keywords": [
      "dollar weakness",
      "safe haven",
      "uncertainty"
    ],
    "fetched_at": "2026-06-03T04:35:18.265391+00:00"
  },
  {
    "source": "Investing.com Forex",
    "headline": "Dollar ticks up on safe haven demand amid uncertainty over U.S.-Iran peace talks",
    "url": "https://www.investing.com/news/forex-news/asia-fx-dollar-subdued-amid-iran-ceasefire-uncertainty-china-mixed-pmi-in-focus-4718007",
    "sentiment_score": -0.3,
    "impact": "MEDIUM",
    "keywords": [
      "safe haven dollar",
      "risk off",
      "uncertainty"
    ],
    "fetched_at": "2026-06-03T04:35:18.265391+00:00"
  },
  {
    "source": "Mining.com",
    "headline": "Gold Fields, Cree First Nation sign IBA for Windfall project in\u00a0Quebec",
    "url": "https://www.mining.com/gold-fields-cree-first-nation-sign-iba-for-windfall-project-in-quebec/",
    "sentiment_score": 0.0,
    "impact": "LOW",
    "keywords": [
      "gold mining",
      "project development",
      "sector specific"
    ],
    "fetched_at": "2026-06-03T04:35:18.265391+00:00"
  },
  {
    "source": "Mining.com",
    "headline": "Copper price: Goldman, Citi make bullish calls on supply woes",
    "url": "https://www.mining.com/copper-price-goldman-citi-make-bullish-calls-on-supply-woes/",
    "sentiment_score": 0.0,
    "impact": "LOW",
    "keywords": [
      "copper outlook",
      "mining sector",
      "unrelated"
    ],
    "fetched_at": "2026-06-03T04:35:18.265391+00:00"
  },
  {
    "source": "Mining.com",
    "headline": "Aya logs bonanza silver hits at Zgounder mine in Morocco",
    "url": "https://www.mining.com/aya-logs-bonanza-silver-hits-at-zgounder-mine-in-morocco/",
    "sentiment_score": 0.0,
    "impact": "LOW",
    "keywords": [
      "silver mining",
      "project news",
      "sector specific"
    ],
    "fetched_at": "2026-06-03T04:35:18.265391+00:00"
  },
  {
    "source": "Mining.com",
    "headline": "Tintina soars on $66M backing for Chile copper-gold project",
    "url": "https://www.mining.com/tintina-soars-to-new-high-on-66m-backing-for-chile-copper-gold-project/",
    "sentiment_score": 0.1,
    "impact": "LOW",
    "keywords": [
      "gold-copper project",
      "mining investment",
      "sector specific"
    ],
    "fetched_at": "2026-06-03T04:35:18.265391+00:00"
  },
  {
    "source": "Mining.com",
    "headline": "Boroo\u2019s bid to buy former Eagle gold site raises questions among miners",
    "url": "https://www.mining.com/boroos-bid-to-buy-former-eagle-gold-site-raises-questions-among-miners/",
    "sentiment_score": 0.0,
    "impact": "LOW",
    "keywords": [
      "mining M&A",
      "sector news",
      "unrelated"
    ],
    "fetched_at": "2026-06-03T04:35:18.265391+00:00"
  },
  {
    "source": "Mining.com",
    "headline": "Gold overtakes US Treasuries in global reserve shift: ECB",
    "url": "https://www.mining.com/gold-overtakes-us-treasuries-in-global-reserve-shift-ecb/",
    "sentiment_score": 0.7,
    "impact": "HIGH",
    "keywords": [
      "reserve diversification",
      "central banks",
      "gold demand"
    ],
    "fetched_at": "2026-06-03T04:35:18.265391+00:00"
  },
  {
    "source": "Mining.com",
    "headline": "Miners urge gov\u2019t aid to challenge China\u2019s rare earth dominance",
    "url": "https://www.mining.com/rare-earth-miners-say-market-needs-govt-support-to-break-chinas-grip/",
    "sentiment_score": 0.0,
    "impact": "LOW",
    "keywords": [
      "rare earths",
      "mining policy",
      "unrelated"
    ],
    "fetched_at": "2026-06-03T04:35:18.265391+00:00"
  },
  {
    "source": "Mining.com",
    "headline": "Elliot pushes Australia\u2019s top gold miner to weigh sale option",
    "url": "https://www.mining.com/elliot-pushes-australias-top-gold-miner-to-weigh-sale-option/",
    "sentiment_score": 0.2,
    "impact": "LOW",
    "keywords": [
      "mining M&A",
      "gold sector",
      "sector specific"
    ],
    "fetched_at": "2026-06-03T04:35:18.265391+00:00"
  }
]