[
  {
    "source": "FinancialJuice",
    "headline": "China June official non-manufacturing PMI climbs to 50.2 from 50.1 in May",
    "url": "https://www.financialjuice.com/News/9657368/China-June-official-non-manufacturing-PMI-climbs-to-502-from-501-in-May.aspx?xy=rss",
    "sentiment_score": 0.2,
    "impact": "LOW",
    "keywords": [
      "China PMI",
      "non-manufacturing",
      "stable"
    ],
    "fetched_at": "2026-06-30T05:36:37.044933+00:00"
  },
  {
    "source": "FinancialJuice",
    "headline": "China June official composite PMI at 50.6",
    "url": "https://www.financialjuice.com/News/9657367/China-June-official-composite-PMI-at-506.aspx?xy=rss",
    "sentiment_score": 0.2,
    "impact": "LOW",
    "keywords": [
      "China",
      "composite PMI",
      "economic stability"
    ],
    "fetched_at": "2026-06-30T05:36:37.044933+00:00"
  },
  {
    "source": "FinancialJuice",
    "headline": "Chinese Composite PMI Actual 50.6 (Forecast -, Previous 50.5)",
    "url": "https://www.financialjuice.com/News/9657365/Chinese-Composite-PMI-Actual-506-Forecast---Previous-505.aspx?xy=rss",
    "sentiment_score": 0.2,
    "impact": "LOW",
    "keywords": [
      "China PMI",
      "composite",
      "resilience"
    ],
    "fetched_at": "2026-06-30T05:36:37.044933+00:00"
  },
  {
    "source": "FinancialJuice",
    "headline": "Chinese NBS Manufacturing PMI Actual 50.3 (Forecast 50.1, Previous 50.0)",
    "url": "https://www.financialjuice.com/News/9657364/Chinese-NBS-Manufacturing-PMI-Actual-503-Forecast-501-Previous-500.aspx?xy=rss",
    "sentiment_score": 0.2,
    "impact": "LOW",
    "keywords": [
      "China PMI",
      "manufacturing",
      "slight beat"
    ],
    "fetched_at": "2026-06-30T05:36:37.044933+00:00"
  },
  {
    "source": "FinancialJuice",
    "headline": "Australia May housing credit rises 0.5% month-on-month, seasonally adjusted: central bank",
    "url": "https://www.financialjuice.com/News/9657362/Australia-May-housing-credit-rises-05-month-on-month-seasonally-adjusted-central-bank.aspx?xy=rss",
    "sentiment_score": 0.1,
    "impact": "LOW",
    "keywords": [
      "Australia",
      "housing credit",
      "modest growth"
    ],
    "fetched_at": "2026-06-30T05:36:37.044933+00:00"
  },
  {
    "source": "FinancialJuice",
    "headline": "Australia may see private-sector credit rise 0.7% month on month, seasonally adjusted: central bank",
    "url": "https://www.financialjuice.com/News/9657361/Australia-may-see-private-sector-credit-rise-07-month-on-month-seasonally-adjusted-central-bank.aspx?xy=rss",
    "sentiment_score": 0.1,
    "impact": "LOW",
    "keywords": [
      "Australia",
      "credit growth",
      "stable"
    ],
    "fetched_at": "2026-06-30T05:36:37.044933+00:00"
  },
  {
    "source": "FinancialJuice",
    "headline": "Australian Private Sector Credit Actual 0.7% (Forecast 0.6%, Previous 0.7%)",
    "url": "https://www.financialjuice.com/News/9657359/Australian-Private-Sector-Credit-Actual-07-Forecast-06-Previous-07.aspx?xy=rss",
    "sentiment_score": 0.2,
    "impact": "LOW",
    "keywords": [
      "credit expansion",
      "Australia",
      "above forecast"
    ],
    "fetched_at": "2026-06-30T05:36:37.044933+00:00"
  },
  {
    "source": "FinancialJuice",
    "headline": "Rba: Household spending increase has not eased significantly",
    "url": "https://www.financialjuice.com/News/9657358/Rba-Household-spending-increase-has-not-eased-significantly.aspx?xy=rss",
    "sentiment_score": -0.3,
    "impact": "MEDIUM",
    "keywords": [
      "household spending",
      "persistent demand",
      "inflation pressure"
    ],
    "fetched_at": "2026-06-30T05:36:37.044933+00:00"
  },
  {
    "source": "FinancialJuice",
    "headline": "RBA: sustained high oil prices may influence price and wage-setting behavior",
    "url": "https://www.financialjuice.com/News/9657357/RBA-sustained-high-oil-prices-may-influence-price-and-wage-setting-behavior.aspx?xy=rss",
    "sentiment_score": -0.4,
    "impact": "MEDIUM",
    "keywords": [
      "oil prices",
      "inflation",
      "wage pressures"
    ],
    "fetched_at": "2026-06-30T05:36:37.044933+00:00"
  },
  {
    "source": "FinancialJuice",
    "headline": "RBA: members highlight risks of possible significant decline in housing markets",
    "url": "https://www.financialjuice.com/News/9657356/RBA-members-highlight-risks-of-possible-significant-decline-in-housing-markets.aspx?xy=rss",
    "sentiment_score": 0.3,
    "impact": "MEDIUM",
    "keywords": [
      "housing decline",
      "growth risk",
      "softer demand"
    ],
    "fetched_at": "2026-06-30T05:36:37.044933+00:00"
  },
  {
    "source": "FinancialJuice",
    "headline": "RBA Discussed Whether Robust Data Centre Activity Might Worsen Capacity Strains in Economy",
    "url": "https://www.financialjuice.com/News/9657355/RBA-Discussed-Whether-Robust-Data-Centre-Activity-Might-Worsen-Capacity-Strains-in-Economy.aspx?xy=rss",
    "sentiment_score": -0.2,
    "impact": "LOW",
    "keywords": [
      "data centre",
      "capacity constraints",
      "demand strength"
    ],
    "fetched_at": "2026-06-30T05:36:37.044933+00:00"
  },
  {
    "source": "FinancialJuice",
    "headline": "RBA: Will take necessary steps to ensure price stability, including potential rate hikes",
    "url": "https://www.financialjuice.com/News/9657354/RBA-Will-take-necessary-steps-to-ensure-price-stability-including-potential-rate-hikes.aspx?xy=rss",
    "sentiment_score": -0.6,
    "impact": "HIGH",
    "keywords": [
      "rate hikes",
      "tightening",
      "hawkish RBA"
    ],
    "fetched_at": "2026-06-30T05:36:37.044933+00:00"
  },
  {
    "source": "FinancialJuice",
    "headline": "RBA: Middle East conflict continues to present significant upside risks for inflation, downside risks for growth",
    "url": "https://www.financialjuice.com/News/9657353/RBA-Middle-East-conflict-continues-to-present-significant-upside-risks-for-inflation-downside-risks-for-growth.aspx?xy=rss",
    "sentiment_score": 0.4,
    "impact": "MEDIUM",
    "keywords": [
      "Middle East",
      "inflation risk",
      "geopolitical"
    ],
    "fetched_at": "2026-06-30T05:36:37.044933+00:00"
  },
  {
    "source": "FinancialJuice",
    "headline": "Rba: Economy running with excess demand, broad inflationary pressures",
    "url": "https://www.financialjuice.com/News/9657352/Rba-Economy-running-with-excess-demand-broad-inflationary-pressures.aspx?xy=rss",
    "sentiment_score": -0.5,
    "impact": "HIGH",
    "keywords": [
      "excess demand",
      "inflationary pressures",
      "rate hike bias"
    ],
    "fetched_at": "2026-06-30T05:36:37.044933+00:00"
  },
  {
    "source": "FinancialJuice",
    "headline": "Rba: weakening housing market, anticipated slowdown in housing credit indicate tighter conditions",
    "url": "https://www.financialjuice.com/News/9657351/Rba-weakening-housing-market-anticipated-slowdown-in-housing-credit-indicate-tighter-conditions.aspx?xy=rss",
    "sentiment_score": 0.3,
    "impact": "MEDIUM",
    "keywords": [
      "tighter conditions",
      "housing weakness",
      "credit slowdown"
    ],
    "fetched_at": "2026-06-30T05:36:37.044933+00:00"
  },
  {
    "source": "FinancialJuice",
    "headline": "RBA board noted housing market softer than expected amid rate increases, tax adjustments",
    "url": "https://www.financialjuice.com/News/9657350/RBA-board-noted-housing-market-softer-than-expected-amid-rate-increases-tax-adjustments.aspx?xy=rss",
    "sentiment_score": 0.2,
    "impact": "LOW",
    "keywords": [
      "housing softer",
      "rate impact",
      "mixed signals"
    ],
    "fetched_at": "2026-06-30T05:36:37.044933+00:00"
  },
  {
    "source": "FinancialJuice",
    "headline": "RBA: Recent data varied, indicates economy slowing broadly as anticipated",
    "url": "https://www.financialjuice.com/News/9657349/RBA-Recent-data-varied-indicates-economy-slowing-broadly-as-anticipated.aspx?xy=rss",
    "sentiment_score": 0.4,
    "impact": "MEDIUM",
    "keywords": [
      "economy slowing",
      "growth softening",
      "dovish tilt"
    ],
    "fetched_at": "2026-06-30T05:36:37.044933+00:00"
  },
  {
    "source": "FinancialJuice",
    "headline": "RBA board agrees financial conditions are likely somewhat tight",
    "url": "https://www.financialjuice.com/News/9657348/RBA-board-agrees-financial-conditions-are-likely-somewhat-tight.aspx?xy=rss",
    "sentiment_score": -0.2,
    "impact": "MEDIUM",
    "keywords": [
      "tight conditions",
      "restrictive policy",
      "hawkish"
    ],
    "fetched_at": "2026-06-30T05:36:37.044933+00:00"
  },
  {
    "source": "FinancialJuice",
    "headline": "China\u2019s central bank pumps 600 billion yuan via overnight reverse repos: statement",
    "url": "https://www.financialjuice.com/News/9657347/Chinas-central-bank-pumps-600-billion-yuan-via-overnight-reverse-repos-statement.aspx?xy=rss",
    "sentiment_score": 0.5,
    "impact": "MEDIUM",
    "keywords": [
      "liquidity injection",
      "stimulus",
      "easing"
    ],
    "fetched_at": "2026-06-30T05:36:37.044933+00:00"
  },
  {
    "source": "FinancialJuice",
    "headline": "China c.bank pumps 69.5 billion yuan through 7-day reverse repos at 1.40%: statement",
    "url": "https://www.financialjuice.com/News/9657346/China-cbank-pumps-695-billion-yuan-through-7-day-reverse-repos-at-140-statement.aspx?xy=rss",
    "sentiment_score": 0.5,
    "impact": "MEDIUM",
    "keywords": [
      "monetary stimulus",
      "reverse repos",
      "easing"
    ],
    "fetched_at": "2026-06-30T05:36:37.044933+00:00"
  },
  {
    "source": "FinancialJuice",
    "headline": "Japan Industry Minister: China's export restrictions affecting Japanese firms with delayed approvals and extended customs checks",
    "url": "https://www.financialjuice.com/News/9657345/Japan-Industry-Minister-Chinas-export-restrictions-affecting-Japanese-firms-with-delayed-approvals-and-extended-customs-checks.aspx?xy=rss",
    "sentiment_score": -0.2,
    "impact": "LOW",
    "keywords": [
      "export restrictions",
      "trade tensions",
      "slower growth"
    ],
    "fetched_at": "2026-06-30T05:36:37.044933+00:00"
  },
  {
    "source": "FinancialJuice",
    "headline": "China's interbank dollar lending sentiment index climbs to record-high 74, indicating improved liquidity conditions",
    "url": "https://www.financialjuice.com/News/9657344/Chinas-interbank-dollar-lending-sentiment-index-climbs-to-record-high-74-indicating-improved-liquidity-conditions.aspx?xy=rss",
    "sentiment_score": 0.4,
    "impact": "MEDIUM",
    "keywords": [
      "dollar liquidity",
      "improved conditions",
      "easing signal"
    ],
    "fetched_at": "2026-06-30T05:36:37.044933+00:00"
  },
  {
    "source": "FinancialJuice",
    "headline": "Japan finance minister Katayama: measures could include decisive steps as agreed in joint statement with US",
    "url": "https://www.financialjuice.com/News/9657327/Japan-finance-minister-Katayama-measures-could-include-decisive-steps-as-agreed-in-joint-statement-with-US.aspx?xy=rss",
    "sentiment_score": -0.4,
    "impact": "MEDIUM",
    "keywords": [
      "intervention",
      "yen support",
      "currency volatility"
    ],
    "fetched_at": "2026-06-30T05:36:37.044933+00:00"
  },
  {
    "source": "FinancialJuice",
    "headline": "Japan Finmin Katayama: will act suitably on currency fluctuations whenever required",
    "url": "https://www.financialjuice.com/News/9657326/Japan-Finmin-Katayama-will-act-suitably-on-currency-fluctuations-whenever-required.aspx?xy=rss",
    "sentiment_score": 0.3,
    "impact": "LOW",
    "keywords": [
      "BoJ",
      "currency intervention",
      "yen support"
    ],
    "fetched_at": "2026-06-30T05:36:37.044933+00:00"
  },
  {
    "source": "FinancialJuice",
    "headline": "Japan Finance Minister Katayama: declines to comment on specific currency levels",
    "url": "https://www.financialjuice.com/News/9657325/Japan-Finance-Minister-Katayama-declines-to-comment-on-specific-currency-levels.aspx?xy=rss",
    "sentiment_score": 0.0,
    "impact": "LOW",
    "keywords": [
      "no comment",
      "currency",
      "neutral"
    ],
    "fetched_at": "2026-06-30T05:36:37.044933+00:00"
  },
  {
    "source": "FinancialJuice",
    "headline": "South Korea President Lee: all ships but two leave Strait of Hormuz",
    "url": "https://www.financialjuice.com/News/9657324/South-Korea-President-Lee-all-ships-but-two-leave-Strait-of-Hormuz.aspx?xy=rss",
    "sentiment_score": 0.2,
    "impact": "LOW",
    "keywords": [
      "geopolitical",
      "Hormuz",
      "minor impact"
    ],
    "fetched_at": "2026-06-30T05:36:37.044933+00:00"
  },
  {
    "source": "FinancialJuice",
    "headline": "Taiwan overnight Interbank rate starts at 0.805%, unchanged from prior session",
    "url": "https://www.financialjuice.com/News/9657323/Taiwan-overnight-Interbank-rate-starts-at-0805-unchanged-from-prior-session.aspx?xy=rss",
    "sentiment_score": 0.0,
    "impact": "LOW",
    "keywords": [
      "interbank rate",
      "unchanged",
      "neutral"
    ],
    "fetched_at": "2026-06-30T05:36:37.044933+00:00"
  },
  {
    "source": "FinancialJuice",
    "headline": "Taiwan shares climb over 2.2%",
    "url": "https://www.financialjuice.com/News/9657314/Taiwan-shares-climb-over-22.aspx?xy=rss",
    "sentiment_score": 0.2,
    "impact": "LOW",
    "keywords": [
      "risk sentiment",
      "equity rally",
      "weak gold"
    ],
    "fetched_at": "2026-06-30T05:36:37.044933+00:00"
  },
  {
    "source": "FinancialJuice",
    "headline": "NBNZ Business Outlook Actual 36.6 (Forecast -, Previous 10.0)",
    "url": "https://www.financialjuice.com/News/9657313/NBNZ-Business-Outlook-Actual-366-Forecast---Previous-100.aspx?xy=rss",
    "sentiment_score": 0.4,
    "impact": "MEDIUM",
    "keywords": [
      "business confidence",
      "NBNZ",
      "economic strength"
    ],
    "fetched_at": "2026-06-30T05:36:37.044933+00:00"
  },
  {
    "source": "FinancialJuice",
    "headline": "NBNZ Own Activity Actual 36.9 (Forecast -, Previous 25.6)",
    "url": "https://www.financialjuice.com/News/9657312/NBNZ-Own-Activity-Actual-369-Forecast---Previous-256.aspx?xy=rss",
    "sentiment_score": 0.4,
    "impact": "MEDIUM",
    "keywords": [
      "activity rebound",
      "NBNZ",
      "growth signal"
    ],
    "fetched_at": "2026-06-30T05:36:37.044933+00:00"
  },
  {
    "source": "FinancialJuice",
    "headline": "Japan Chief Cabinet Secretary Kihara: always prepared to take necessary steps on currency market",
    "url": "https://www.financialjuice.com/News/9657303/Japan-Chief-Cabinet-Secretary-Kihara-always-prepared-to-take-necessary-steps-on-currency-market.aspx?xy=rss",
    "sentiment_score": 0.3,
    "impact": "LOW",
    "keywords": [
      "BoJ",
      "currency vigilance",
      "yen support"
    ],
    "fetched_at": "2026-06-30T05:36:37.044933+00:00"
  },
  {
    "source": "FinancialJuice",
    "headline": "Japan chief cabinet secretary Kihara: no comment on currency valuation",
    "url": "https://www.financialjuice.com/News/9657302/Japan-chief-cabinet-secretary-Kihara-no-comment-on-currency-valuation.aspx?xy=rss",
    "sentiment_score": 0.0,
    "impact": "LOW",
    "keywords": [
      "no comment",
      "currency",
      "neutral"
    ],
    "fetched_at": "2026-06-30T05:36:37.044933+00:00"
  },
  {
    "source": "FinancialJuice",
    "headline": "Bank of Japan: new board member Sato to hold press conference at 0800 GMT",
    "url": "https://www.financialjuice.com/News/9657300/Bank-of-Japan-new-board-member-Sato-to-hold-press-conference-at-0800-GMT.aspx?xy=rss",
    "sentiment_score": 0.2,
    "impact": "LOW",
    "keywords": [
      "BoJ",
      "policy clarity",
      "minor event"
    ],
    "fetched_at": "2026-06-30T05:36:37.044933+00:00"
  },
  {
    "source": "MarketWatch Top",
    "headline": "\u2018I claimed Social Security at 62\u2019: At 76, I\u2019m working at Walmart. Why do I still owe payroll taxes?",
    "url": "https://www.marketwatch.com/story/i-claimed-social-security-at-62-at-76-im-working-at-walmart-why-do-i-still-owe-payroll-taxes-8e22a97c?mod=mw_rss_topstories",
    "sentiment_score": 0.0,
    "impact": "LOW",
    "keywords": [
      "social security",
      "unrelated",
      "neutral"
    ],
    "fetched_at": "2026-06-30T05:36:37.044933+00:00"
  },
  {
    "source": "MarketWatch Top",
    "headline": "Value stocks beat growth when inflation is high. Here are 13 stocks top newsletters are betting on now.",
    "url": "https://www.marketwatch.com/story/value-stocks-beat-growth-when-inflation-is-high-here-are-13-stocks-top-newsletters-are-betting-on-now-f6f4a265?mod=mw_rss_topstories",
    "sentiment_score": -0.2,
    "impact": "LOW",
    "keywords": [
      "value stocks",
      "inflation hedge",
      "equity preference"
    ],
    "fetched_at": "2026-06-30T05:36:37.044933+00:00"
  },
  {
    "source": "Investing.com Comm",
    "headline": "Asia stocks rise on upbeat China PMI; tech spurs bumper quarter",
    "url": "https://www.investing.com/news/stock-market-news/asian-stocks-mixed-as-china-pmi-offsets-caution-ahead-of-us-jobs-data-4766836",
    "sentiment_score": 0.3,
    "impact": "LOW",
    "keywords": [
      "risk-on",
      "China PMI",
      "equity strength"
    ],
    "fetched_at": "2026-06-30T05:36:37.044933+00:00"
  },
  {
    "source": "Investing.com Comm",
    "headline": "Warren Buffett skips donation to Gates Foundation amid Epstein review, WSJ reports",
    "url": "https://www.investing.com/news/stock-market-news/warren-buffett-skips-donation-to-gates-foundation-amid-epstein-review-wsj-reports-4766827",
    "sentiment_score": 0.0,
    "impact": "LOW",
    "keywords": [
      "philanthropy",
      "unrelated",
      "neutral"
    ],
    "fetched_at": "2026-06-30T05:36:37.044933+00:00"
  },
  {
    "source": "Investing.com Forex",
    "headline": "Dollar snaps two-week win streak as traders eye labor market data for rate cues",
    "url": "https://www.investing.com/news/forex-news/asia-fx-steady-as-traders-weigh-fragile-iran-ceasefire-busy-data-week-4764221",
    "sentiment_score": 0.6,
    "impact": "MEDIUM",
    "keywords": [
      "dollar weakness",
      "rate expectations",
      "gold bullish"
    ],
    "fetched_at": "2026-06-30T05:36:37.044933+00:00"
  },
  {
    "source": "Investing.com Forex",
    "headline": "Natixis says dollar rally has peaked, recommends selling greenback",
    "url": "https://www.investing.com/news/forex-news/natixis-says-dollar-rally-has-peaked-recommends-selling-greenback-93CH-4766005",
    "sentiment_score": 0.7,
    "impact": "MEDIUM",
    "keywords": [
      "dollar peak",
      "sell signal",
      "gold support"
    ],
    "fetched_at": "2026-06-30T05:36:37.044933+00:00"
  },
  {
    "source": "Investing.com Forex",
    "headline": "Canadian dollar falls as speculators increase bearish bets",
    "url": "https://www.investing.com/news/forex-news/canadian-dollar-falls-as-speculators-increase-bearish-bets-93CH-4765929",
    "sentiment_score": 0.5,
    "impact": "MEDIUM",
    "keywords": [
      "CAD weakness",
      "risk-off",
      "safe haven"
    ],
    "fetched_at": "2026-06-30T05:36:37.044933+00:00"
  },
  {
    "source": "Investing.com Forex",
    "headline": "Japanese Yen falls to 40-year low against dollar",
    "url": "https://www.investing.com/news/forex-news/japanese-yen-falls-to-40year-low-against-dollar-4765727",
    "sentiment_score": 0.8,
    "impact": "HIGH",
    "keywords": [
      "yen weakness",
      "BoJ divergence",
      "gold strength"
    ],
    "fetched_at": "2026-06-30T05:36:37.044933+00:00"
  },
  {
    "source": "Investing.com Forex",
    "headline": "Yen falls to weakest level versus dollar since December 1986",
    "url": "https://www.investing.com/news/forex-news/yen-falls-to-weakest-level-versus-dollar-since-december-1986-93CH-4765678",
    "sentiment_score": 0.8,
    "impact": "HIGH",
    "keywords": [
      "yen collapse",
      "currency crisis",
      "gold rally"
    ],
    "fetched_at": "2026-06-30T05:36:37.044933+00:00"
  },
  {
    "source": "Investing.com Forex",
    "headline": "Sterling today: Pound gains as dollar weakness persists",
    "url": "https://www.investing.com/news/forex-news/sterling-today-pound-gains-as-dollar-weakness-persists-4765416",
    "sentiment_score": 0.6,
    "impact": "MEDIUM",
    "keywords": [
      "dollar weakness",
      "pound strength",
      "gold bullish"
    ],
    "fetched_at": "2026-06-30T05:36:37.044933+00:00"
  },
  {
    "source": "Investing.com Forex",
    "headline": "Euro yields edge up as Middle East tension fuels oil, inflation fears",
    "url": "https://www.investing.com/news/forex-news/euro-yields-edge-up-as-middle-east-tension-fuels-oil-inflation-fears-4764282",
    "sentiment_score": 0.7,
    "impact": "HIGH",
    "keywords": [
      "Middle East tension",
      "inflation fears",
      "geopolitical risk"
    ],
    "fetched_at": "2026-06-30T05:36:37.044933+00:00"
  },
  {
    "source": "Mining.com",
    "headline": "Gold price falls nearly 2% as rebound proves short-lived",
    "url": "https://www.mining.com/gold-price-falls-back-to-4000-on-renewed-mideast-tensions/",
    "sentiment_score": -0.8,
    "impact": "HIGH",
    "keywords": [
      "price decline",
      "momentum loss",
      "technical reversal"
    ],
    "fetched_at": "2026-06-30T05:36:37.044933+00:00"
  },
  {
    "source": "Mining.com",
    "headline": "Bunker Hill\u00a0rebuild\u00a0ships first Idaho ore,\u00a0eyes silver",
    "url": "https://www.mining.com/bunker-hill-rebuild-ships-first-idaho-ore-eyes-silver/",
    "sentiment_score": 0.1,
    "impact": "LOW",
    "keywords": [
      "mining production",
      "silver",
      "commodity supply"
    ],
    "fetched_at": "2026-06-30T05:36:37.044933+00:00"
  },
  {
    "source": "Mining.com",
    "headline": "Freeman Gold triples Lemhi project value, builds 1Moz reserve",
    "url": "https://www.mining.com/freeman-gold-triples-lemhi-project-value-builds-1moz-reserve/",
    "sentiment_score": 0.1,
    "impact": "LOW",
    "keywords": [
      "gold reserve",
      "mining exploration",
      "supply side"
    ],
    "fetched_at": "2026-06-30T05:36:37.044933+00:00"
  },
  {
    "source": "Mining.com",
    "headline": "Integra grows reserve by 74% at Florida Canyon gold mine",
    "url": "https://www.mining.com/integra-grows-reserve-74-at-florida-canyon-gold-mine/",
    "sentiment_score": 0.1,
    "impact": "LOW",
    "keywords": [
      "reserve growth",
      "mining production",
      "supply side"
    ],
    "fetched_at": "2026-06-30T05:36:37.044933+00:00"
  },
  {
    "source": "Reuters",
    "headline": "Trump urges gasoline retailers to lower prices, warns of 'big problems' if they don't - Reuters",
    "url": "https://news.google.com/rss/articles/CBMixgFBVV95cUxQVlowVWxKdUhheXVNdWdVeDNkb1k2MHJFaExPdFVyMVVqNU1MZW9sQXhzaTNmdi1qNlFHamhFalRkcHo4TEdOZnMzLW5xVmZGZVdtbkp6NHJBVWNhS0FwVTQ3NmNVclk4YVpkYmM4T1pDZU1BLXk3a2p1SnBEOWxGSG9MUnpCWlc1U2kzZ2lwbEhOOWpHVW9wZFd2dDd2cXJOU0otR19CbEtCTW9HMXZqX0JvZ0RjNDFMQnBscUExQzFObUw0Mmc?oc=5",
    "sentiment_score": -0.3,
    "impact": "MEDIUM",
    "keywords": [
      "price control",
      "inflation concern",
      "policy pressure"
    ],
    "fetched_at": "2026-06-30T05:36:37.044933+00:00"
  },
  {
    "source": "CNBC",
    "headline": "Chip stocks rebound, and Goldman racks up a series of M&A wins",
    "url": "https://www.cnbc.com/2026/06/29/chip-stocks-rebound-and-goldman-racks-up-a-series-of-ma-wins-.html",
    "sentiment_score": -0.4,
    "impact": "MEDIUM",
    "keywords": [
      "equity rebound",
      "risk appetite",
      "M&A activity"
    ],
    "fetched_at": "2026-06-30T05:36:37.044933+00:00"
  },
  {
    "source": "Reuters",
    "headline": "Israel-Lebanon deal may entrench stalemate rather than end war, analysts say - Reuters",
    "url": "https://news.google.com/rss/articles/CBMiyAFBVV95cUxOQzVPS3VRVGFsSElBdURJN0sxVEZaalUtNGpETS1FQXJLNkhkeTJ5M1VaR19HcmpoZXpWY3FhX0F2S2RLWjlMNVM1UWJzbllJcGZic3VnLVJYMWMtRk1GcVFGa2RZREpvY3JadXJScDZCVVdwRmYwY0lPVGRiOVQyLWI4MUJnY28zWW43TmJoRUM5dkRaUUpwRGhUNFB5MWVDV3hCY1lDUHJzUVpsSXI3QUlwR0puQkU0R3BMMXFHTm9hUmU0QURWTQ?oc=5",
    "sentiment_score": -0.2,
    "impact": "LOW",
    "keywords": [
      "geopolitical resolution",
      "conflict de-escalation",
      "risk-off fade"
    ],
    "fetched_at": "2026-06-30T05:36:37.044933+00:00"
  },
  {
    "source": "Reuters",
    "headline": "Senior Lebanese official slams US-brokered deal with Israel, warns of divisions - Reuters",
    "url": "https://news.google.com/rss/articles/CBMiyAFBVV95cUxNdEcxa2lmSEt3VTljemt3NzlwaGdLWVZCTHdjYUJEVjlzZkNSTDUzUXRaQThvc1d1MTJBVVdERzF2Qno3YWthLWRDVGtKbHZxQ2xuVmNkWG43Ri1mWHM0TGJrX3F4TXlyaTdwYXBxQzRDaHNSOFhSZDhtS04tRGRIejNOZTdLSHBaS293OWNIMC12bV83anZQdDRra204aU0wSFI4NGZ1LTdHRHBfM1pSYWdXOHpZMUZzUnlwd0tGS3p6N3dsYzRxYQ?oc=5",
    "sentiment_score": -0.2,
    "impact": "LOW",
    "keywords": [
      "deal skepticism",
      "regional tension",
      "ceasefire doubt"
    ],
    "fetched_at": "2026-06-30T05:36:37.044933+00:00"
  },
  {
    "source": "Reuters",
    "headline": "How 5 weeks of war shattered some of Iran\u2019s cherished monuments - Reuters",
    "url": "https://news.google.com/rss/articles/CBMiigFBVV95cUxQZDF2cmU1OXB5Q1VfV0ZUM1VhZE51WVlXTnlrS2VUaC1oMldhNUYzUkFpRGdTNDg3b1RRSEZtYUVHamtJODBvMUFkMnpwZkhGS1NPMFp3TUlkdWs1VUhzN1Z4dEpybndfNDJEN1YtUnJXYXVlMDlkdVQ4d0JxRUxtdEx5QXE1NTN5OHc?oc=5",
    "sentiment_score": 0.5,
    "impact": "MEDIUM",
    "keywords": [
      "war damages",
      "Middle East conflict",
      "geopolitical risk"
    ],
    "fetched_at": "2026-06-30T05:36:37.044933+00:00"
  },
  {
    "source": "Reuters",
    "headline": "Gold slips as US-Iran tensions spark inflation, rate hike fears - Reuters",
    "url": "https://news.google.com/rss/articles/CBMitgFBVV95cUxPSTVKRTRyZTc4cndMX2E0Mzd3UlROU1FJMWFsaWpkbDVuSUFiVldPeE1GRVFLbDVYeTZ5RTFXd08wUkYwU205amR5a1BIOTFTNGE1T01qMjNGSkJ2OXpjQVhWQ1JXSTdOeDBGb3I5czNDQ1VYck9ENEZJNVZMQk5Rc19tTWgzM3hGaC1uSlltSktpNWtyM3AtTTk3RkZJaFNpNjVFRXJUSWhuWEJGcnNUb1ZGVWstUQ?oc=5",
    "sentiment_score": 0.6,
    "impact": "HIGH",
    "keywords": [
      "US-Iran tensions",
      "inflation fears",
      "rate hike risk"
    ],
    "fetched_at": "2026-06-30T05:36:37.044933+00:00"
  },
  {
    "source": "Reuters",
    "headline": "Stocks and oil prices rise with eyes on Iran; yen touches 40-year low vs dollar - Reuters",
    "url": "https://news.google.com/rss/articles/CBMigAFBVV95cUxPYUFwVXVYYUk3ZXZGYUhac1BmQjhYN1JiSHM5SlhvWW9taHVTRkFZeVlrNFVfTl8wQVY0VTc3ekNEd1EyX2NMYjdNZXFwWi1WMFJWTHVIaE8yNTNNVWR4NkFHelBmSFlwYWdjRTZQREo4elhtYnNhZ3RMMjg2ckttSw?oc=5",
    "sentiment_score": -0.5,
    "impact": "MEDIUM",
    "keywords": [
      "oil rally",
      "risk appetite",
      "dollar strength"
    ],
    "fetched_at": "2026-06-30T05:36:37.044933+00:00"
  },
  {
    "source": "Reuters",
    "headline": "Iran war developments, Fed rate path cues in focus for Indian rupee and bonds - Reuters",
    "url": "https://news.google.com/rss/articles/CBMiuwFBVV95cUxNU0tnYmloaHpIVTVmYUZHSUljRy1XNHN2VU8wSDVxSk5DRmJFUkNDWjNzOXJ6ejd0a0hGWmoxMWJncnZOQm5taGpMU09TMjBTMEFkUWlTZXVDMXRoUkhoZGRTWVdUTnVzaXhoRHlQUmloSnpPUTVBYU9rbFV0ZE1VTUFnZGZ2RkRTTWRjQ1dqVE9Telg2c285TlBTRFYyVDNFc1pxcUExa0lkZ3ZUTy1MZEp0N2pOTzg4ZFo4?oc=5",
    "sentiment_score": 0.4,
    "impact": "MEDIUM",
    "keywords": [
      "Iran tensions",
      "rate uncertainty",
      "currency volatility"
    ],
    "fetched_at": "2026-06-30T05:36:37.044933+00:00"
  },
  {
    "source": "CNBC",
    "headline": "Trading in these two ETFs suggests inflation fears are overblown",
    "url": "https://www.cnbc.com/2026/06/27/trading-in-these-two-etfs-suggests-inflation-fears-are-overblown.html",
    "sentiment_score": -0.6,
    "impact": "MEDIUM",
    "keywords": [
      "inflation overblown",
      "rate hike doubts",
      "risk appetite"
    ],
    "fetched_at": "2026-06-30T05:36:37.044933+00:00"
  },
  {
    "source": "Reuters",
    "headline": "Gold gains as dollar weakens; still on track for fourth straight weekly loss - Reuters",
    "url": "https://news.google.com/rss/articles/CBMipwFBVV95cUxQRXc4NjVKdS0yVG1sdzYzZEIwNno3QXhNVzFKRktkSHJZa3l0dUZFTmd2blZtbVVSM2MzR0dNX0VTR1VzMEd2d3NxQjROYU5LdF9zMVY3SkNsZzRSSUVPOFdnMEZ6Qm9CdmlNVWx4V2Z6UlhianlDVUZxMGw4WlNOUjlhS2VwcGRqZmEtTHJMTXlhUG1CdWhUR0w1WmhxZ1ZOSTFNdUI2NA?oc=5",
    "sentiment_score": 0.5,
    "impact": "MEDIUM",
    "keywords": [
      "dollar weakness",
      "weekly losses",
      "technical support"
    ],
    "fetched_at": "2026-06-30T05:36:37.044933+00:00"
  },
  {
    "source": "Reuters",
    "headline": "US diesel refining economics remain firm despite Iran war truce - Reuters",
    "url": "https://news.google.com/rss/articles/CBMitgFBVV95cUxQaktNajNVTlRkTm1nVkRyMHNDc3FBTk5BRjRVVy16cjRNbFdhSFhYWkYtcy1wNlJkMzRjTWhnakNiUmJjZ3V1c2luUG9lNVcyaG1Semg3UkhQOHEtY2tFS1lQbkkwZll4U3MzU2J3QmJuQnRKUzFuVVJPQXpJNzRjNmd2Rzc2aC1XRDMxck1OcXlxd3dNM1pJQnFHb3Z1S2U5VmVMYWtNY190WmdtNmtKd29fQm8zZw?oc=5",
    "sentiment_score": -0.3,
    "impact": "MEDIUM",
    "keywords": [
      "refining stability",
      "oil price normalization",
      "inflation fade"
    ],
    "fetched_at": "2026-06-30T05:36:37.044933+00:00"
  },
  {
    "source": "Reuters",
    "headline": "UAE stresses Hormuz security in rare call with Iran after war tensions - Reuters",
    "url": "https://news.google.com/rss/articles/CBMivgFBVV95cUxOTFhOWjA0b0NFVmItV25IVHhmdUw2WmtfeGU1SXZ1ZjFsaHF4bnJrTVVVR0M5QlFfS3Z1Vk5Scm5CTjFCaXB3SVREeXctT1h4QlhwaDJKc2dQNGhTbTV2U243Q0kwUjhzUEJnak5RdzdLNkpyMUNVcjNOdWFsRXFYVUFlZFpzMm9fMmR3dXJpem1wMWhOWm5OVDJfd3NzX1hhOFlnYjJZMzNId2UyOUxMS3VrdmJCWmxsVnlpZ3NB?oc=5",
    "sentiment_score": 0.3,
    "impact": "MEDIUM",
    "keywords": [
      "Hormuz security",
      "geopolitical risk",
      "supply concerns"
    ],
    "fetched_at": "2026-06-30T05:36:37.044933+00:00"
  },
  {
    "source": "Reuters",
    "headline": "UAE says false public warning caused by technical malfunction - Reuters",
    "url": "https://news.google.com/rss/articles/CBMitwFBVV95cUxQYTA4WmxkQjRfQjJKWUlDVzZuU0p0Sm8wS2g5c3JXay1qSXdTVHpsdVdDN3NwVEV3TnJZQ0RaV0htWm5xcnZ6LU96bXAza1RXeEhJUEN5UzNYN1IzTWZCeEFrUVdYNzRmdTNzaFAzNW9LWGQ1akpXOFlOdXI2NjA0UjVaSVJnenlsa2xmQ1lSTGZ3LTNVbWRJTG40aERIMjF4TGloTVcxRGFYMUhrMjdVdWExZHQyVW8?oc=5",
    "sentiment_score": -0.1,
    "impact": "LOW",
    "keywords": [
      "technical malfunction",
      "false alarm",
      "de-escalation signal"
    ],
    "fetched_at": "2026-06-30T05:36:37.044933+00:00"
  },
  {
    "source": "FinancialJuice",
    "headline": "Finland May GDP rises 2.8% year on year: Statistics Finland",
    "url": "https://www.financialjuice.com/News/9657653/Finland-May-GDP-rises-28-year-on-year-Statistics-Finland.aspx?xy=rss",
    "sentiment_score": 0.0,
    "impact": "LOW",
    "keywords": [
      "Finland GDP",
      "eurozone growth",
      "minor economy"
    ],
    "fetched_at": "2026-06-30T05:51:24.126547+00:00"
  },
  {
    "source": "FinancialJuice",
    "headline": "Finland's May GDP growth at 2.8% year on year: Statistics Finland",
    "url": "https://www.financialjuice.com/News/9657652/Finlands-May-GDP-growth-at-28-year-on-year-Statistics-Finland.aspx?xy=rss",
    "sentiment_score": 0.0,
    "impact": "LOW",
    "keywords": [
      "Finland GDP",
      "eurozone growth",
      "minor economy"
    ],
    "fetched_at": "2026-06-30T05:51:24.126547+00:00"
  },
  {
    "source": "FinancialJuice",
    "headline": "Central banks plan to boost euro holdings, but 60% hesitate over lower returns: OMFIF finds",
    "url": "https://www.financialjuice.com/News/9657650/Central-banks-plan-to-boost-euro-holdings-but-60-hesitate-over-lower-returns-OMFIF-finds.aspx?xy=rss",
    "sentiment_score": 0.3,
    "impact": "MEDIUM",
    "keywords": [
      "central banks",
      "euro holdings",
      "reserve diversification"
    ],
    "fetched_at": "2026-06-30T05:51:24.126547+00:00"
  },
  {
    "source": "FinancialJuice",
    "headline": "For first time, more central banks plan to reduce dollar allocations than raise them in next decade: OMFIF survey finds",
    "url": "https://www.financialjuice.com/News/9657649/For-first-time-more-central-banks-plan-to-reduce-dollar-allocations-than-raise-them-in-next-decade-OMFIF-survey-finds.aspx?xy=rss",
    "sentiment_score": 0.6,
    "impact": "HIGH",
    "keywords": [
      "de-dollarisation",
      "dollar reduction",
      "reserve shift"
    ],
    "fetched_at": "2026-06-30T05:51:24.126547+00:00"
  },
  {
    "source": "FinancialJuice",
    "headline": "Survey finds 93% of central banks see renminbi as diversification tool, but market structure hinders uptake",
    "url": "https://www.financialjuice.com/News/9657648/Survey-finds-93-of-central-banks-see-renminbi-as-diversification-tool-but-market-structure-hinders-uptake.aspx?xy=rss",
    "sentiment_score": 0.4,
    "impact": "MEDIUM",
    "keywords": [
      "renminbi",
      "diversification",
      "central banks"
    ],
    "fetched_at": "2026-06-30T05:51:24.126547+00:00"
  },
  {
    "source": "FinancialJuice",
    "headline": "82% of central banks hold physical gold in 2026, up from 71% last year: OMFIF survey",
    "url": "https://www.financialjuice.com/News/9657647/82-of-central-banks-hold-physical-gold-in-2026-up-from-71-last-year-OMFIF-survey.aspx?xy=rss",
    "sentiment_score": 0.8,
    "impact": "HIGH",
    "keywords": [
      "central bank gold",
      "bullion demand",
      "reserve accumulation"
    ],
    "fetched_at": "2026-06-30T05:51:24.126547+00:00"
  },
  {
    "source": "FinancialJuice",
    "headline": "Two-thirds of central banks plan to boost AI adoption in next one to two years, survey finds",
    "url": "https://www.financialjuice.com/News/9657646/Two-thirds-of-central-banks-plan-to-boost-AI-adoption-in-next-one-to-two-years-survey-finds.aspx?xy=rss",
    "sentiment_score": 0.0,
    "impact": "LOW",
    "keywords": [
      "AI adoption",
      "technology",
      "banking ops"
    ],
    "fetched_at": "2026-06-30T05:51:24.126547+00:00"
  },
  {
    "source": "FinancialJuice",
    "headline": "Central banks indicate gradual shift toward de-dollarisation: OMFIF survey finds",
    "url": "https://www.financialjuice.com/News/9657645/Central-banks-indicate-gradual-shift-toward-de-dollarisation-OMFIF-survey-finds.aspx?xy=rss",
    "sentiment_score": 0.6,
    "impact": "HIGH",
    "keywords": [
      "de-dollarisation",
      "dollar weakness",
      "reserve shift"
    ],
    "fetched_at": "2026-06-30T05:51:24.126547+00:00"
  },
  {
    "source": "FinancialJuice",
    "headline": "Two Revolutionary Guards killed in attack by unidentified gunmen in western Iran: state media",
    "url": "https://www.financialjuice.com/News/9657644/Two-Revolutionary-Guards-killed-in-attack-by-unidentified-gunmen-in-western-Iran-state-media.aspx?xy=rss",
    "sentiment_score": -0.3,
    "impact": "MEDIUM",
    "keywords": [
      "Iran geopolitics",
      "Middle East tensions",
      "risk sentiment"
    ],
    "fetched_at": "2026-06-30T05:51:24.126547+00:00"
  },
  {
    "source": "FinancialJuice",
    "headline": "Russia downs 419 Ukrainian drones overnight: Russian newswires cite defense ministry",
    "url": "https://www.financialjuice.com/News/9657610/Russia-downs-419-Ukrainian-drones-overnight-Russian-newswires-cite-defense-ministry.aspx?xy=rss",
    "sentiment_score": -0.2,
    "impact": "LOW",
    "keywords": [
      "Russia Ukraine",
      "geopolitical risk",
      "safe haven"
    ],
    "fetched_at": "2026-06-30T05:51:24.126547+00:00"
  },
  {
    "source": "MarketWatch Top",
    "headline": "\u2018I claimed Social Security at 62\u2019: At 76, I\u2019m working at Walmart. Why do I still owe payroll taxes?",
    "url": "https://www.marketwatch.com/story/i-claimed-social-security-at-62-at-76-im-working-at-walmart-why-do-i-still-owe-payroll-taxes-8e22a97c?mod=mw_rss_topstories",
    "sentiment_score": 0.0,
    "impact": "LOW",
    "keywords": [
      "social security",
      "US domestic",
      "unrelated"
    ],
    "fetched_at": "2026-06-30T05:51:24.126547+00:00"
  },
  {
    "source": "MarketWatch Top",
    "headline": "Value stocks beat growth when inflation is high. Here are 13 stocks top newsletters are betting on now.",
    "url": "https://www.marketwatch.com/story/value-stocks-beat-growth-when-inflation-is-high-here-are-13-stocks-top-newsletters-are-betting-on-now-f6f4a265?mod=mw_rss_topstories",
    "sentiment_score": -0.2,
    "impact": "LOW",
    "keywords": [
      "value stocks",
      "inflation hedge",
      "equities"
    ],
    "fetched_at": "2026-06-30T05:51:24.126547+00:00"
  },
  {
    "source": "Investing.com Comm",
    "headline": "Asia stocks rise on upbeat China PMI; tech spurs bumper quarter",
    "url": "https://www.investing.com/news/stock-market-news/asian-stocks-mixed-as-china-pmi-offsets-caution-ahead-of-us-jobs-data-4766836",
    "sentiment_score": -0.4,
    "impact": "MEDIUM",
    "keywords": [
      "risk appetite",
      "China growth",
      "equities rally"
    ],
    "fetched_at": "2026-06-30T05:51:24.126547+00:00"
  },
  {
    "source": "Investing.com Comm",
    "headline": "Warren Buffett skips donation to Gates Foundation amid Epstein review, WSJ reports",
    "url": "https://www.investing.com/news/stock-market-news/warren-buffett-skips-donation-to-gates-foundation-amid-epstein-review-wsj-reports-4766827",
    "sentiment_score": 0.0,
    "impact": "LOW",
    "keywords": [
      "Buffett charity",
      "billionaire news",
      "unrelated"
    ],
    "fetched_at": "2026-06-30T05:51:24.126547+00:00"
  },
  {
    "source": "Investing.com Forex",
    "headline": "Yen hits 40-year low amid intervention fears; yuan steadies after China PMI",
    "url": "https://www.investing.com/news/forex-news/yen-hits-40year-low-on-intervention-fears-yuan-steadies-after-china-pmi-4766858",
    "sentiment_score": 0.5,
    "impact": "MEDIUM",
    "keywords": [
      "yen weakness",
      "dollar strength",
      "FX intervention"
    ],
    "fetched_at": "2026-06-30T05:51:24.126547+00:00"
  },
  {
    "source": "Investing.com Forex",
    "headline": "Dollar snaps two-week win streak as traders eye labor market data for rate cues",
    "url": "https://www.investing.com/news/forex-news/asia-fx-steady-as-traders-weigh-fragile-iran-ceasefire-busy-data-week-4764221",
    "sentiment_score": 0.3,
    "impact": "MEDIUM",
    "keywords": [
      "dollar weakness",
      "labor data",
      "rate expectations"
    ],
    "fetched_at": "2026-06-30T05:51:24.126547+00:00"
  },
  {
    "source": "Investing.com Forex",
    "headline": "Natixis says dollar rally has peaked, recommends selling greenback",
    "url": "https://www.investing.com/news/forex-news/natixis-says-dollar-rally-has-peaked-recommends-selling-greenback-93CH-4766005",
    "sentiment_score": 0.5,
    "impact": "MEDIUM",
    "keywords": [
      "dollar peak",
      "dollar weakness",
      "FX reversal"
    ],
    "fetched_at": "2026-06-30T05:51:24.126547+00:00"
  },
  {
    "source": "Investing.com Forex",
    "headline": "Canadian dollar falls as speculators increase bearish bets",
    "url": "https://www.investing.com/news/forex-news/canadian-dollar-falls-as-speculators-increase-bearish-bets-93CH-4765929",
    "sentiment_score": 0.0,
    "impact": "LOW",
    "keywords": [
      "Canadian dollar",
      "currency",
      "minor impact"
    ],
    "fetched_at": "2026-06-30T05:51:24.126547+00:00"
  },
  {
    "source": "Investing.com Forex",
    "headline": "Japanese Yen falls to 40-year low against dollar",
    "url": "https://www.investing.com/news/forex-news/japanese-yen-falls-to-40year-low-against-dollar-4765727",
    "sentiment_score": 0.5,
    "impact": "MEDIUM",
    "keywords": [
      "yen weakness",
      "dollar strength",
      "BOJ policy"
    ],
    "fetched_at": "2026-06-30T05:51:24.126547+00:00"
  },
  {
    "source": "Investing.com Forex",
    "headline": "Yen falls to weakest level versus dollar since December 1986",
    "url": "https://www.investing.com/news/forex-news/yen-falls-to-weakest-level-versus-dollar-since-december-1986-93CH-4765678",
    "sentiment_score": 0.5,
    "impact": "MEDIUM",
    "keywords": [
      "yen weakness",
      "dollar strength",
      "currency volatility"
    ],
    "fetched_at": "2026-06-30T05:51:24.126547+00:00"
  },
  {
    "source": "Investing.com Forex",
    "headline": "Sterling today: Pound gains as dollar weakness persists",
    "url": "https://www.investing.com/news/forex-news/sterling-today-pound-gains-as-dollar-weakness-persists-4765416",
    "sentiment_score": -0.3,
    "impact": "MEDIUM",
    "keywords": [
      "dollar weakness",
      "currency",
      "USD"
    ],
    "fetched_at": "2026-06-30T05:51:24.126547+00:00"
  },
  {
    "source": "Investing.com Forex",
    "headline": "Euro yields edge up as Middle East tension fuels oil, inflation fears",
    "url": "https://www.investing.com/news/forex-news/euro-yields-edge-up-as-middle-east-tension-fuels-oil-inflation-fears-4764282",
    "sentiment_score": 0.4,
    "impact": "MEDIUM",
    "keywords": [
      "inflation fears",
      "geopolitical tension",
      "oil"
    ],
    "fetched_at": "2026-06-30T05:51:24.126547+00:00"
  },
  {
    "source": "Mining.com",
    "headline": "Gold price falls nearly 2% as rebound proves short-lived",
    "url": "https://www.mining.com/gold-price-falls-back-to-4000-on-renewed-mideast-tensions/",
    "sentiment_score": -0.6,
    "impact": "MEDIUM",
    "keywords": [
      "price decline",
      "rebound failure",
      "momentum"
    ],
    "fetched_at": "2026-06-30T05:51:24.126547+00:00"
  },
  {
    "source": "Mining.com",
    "headline": "Bunker Hill\u00a0rebuild\u00a0ships first Idaho ore,\u00a0eyes silver",
    "url": "https://www.mining.com/bunker-hill-rebuild-ships-first-idaho-ore-eyes-silver/",
    "sentiment_score": 0.1,
    "impact": "LOW",
    "keywords": [
      "mining production",
      "silver",
      "supply"
    ],
    "fetched_at": "2026-06-30T05:51:24.126547+00:00"
  },
  {
    "source": "Mining.com",
    "headline": "Freeman Gold triples Lemhi project value, builds 1Moz reserve",
    "url": "https://www.mining.com/freeman-gold-triples-lemhi-project-value-builds-1moz-reserve/",
    "sentiment_score": 0.2,
    "impact": "LOW",
    "keywords": [
      "reserve growth",
      "mining development",
      "supply"
    ],
    "fetched_at": "2026-06-30T05:51:24.126547+00:00"
  },
  {
    "source": "Mining.com",
    "headline": "Integra grows reserve by 74% at Florida Canyon gold mine",
    "url": "https://www.mining.com/integra-grows-reserve-74-at-florida-canyon-gold-mine/",
    "sentiment_score": 0.1,
    "impact": "LOW",
    "keywords": [
      "reserve expansion",
      "mining production",
      "supply"
    ],
    "fetched_at": "2026-06-30T05:51:24.126547+00:00"
  },
  {
    "source": "Forexlive",
    "headline": "Heads up: Germany states' CPI readings due later today",
    "url": "https://investinglive.com/news/heads-up-germany-states-cpi-readings-due-later-today-20260630/",
    "sentiment_score": 0.0,
    "impact": "LOW",
    "keywords": [
      "inflation data",
      "economic indicator",
      "CPI"
    ],
    "fetched_at": "2026-06-30T05:51:24.126547+00:00"
  },
  {
    "source": "Reuters",
    "headline": "Trump urges gasoline retailers to lower prices, warns of 'big problems' if they don't - Reuters",
    "url": "https://news.google.com/rss/articles/CBMixgFBVV95cUxQVlowVWxKdUhheXVNdWdVeDNkb1k2MHJFaExPdFVyMVVqNU1MZW9sQXhzaTNmdi1qNlFHamhFalRkcHo4TEdOZnMzLW5xVmZGZVdtbkp6NHJBVWNhS0FwVTQ3NmNVclk4YVpkYmM4T1pDZU1BLXk3a2p1SnBEOWxGSG9MUnpCWlc1U2kzZ2lwbEhOOWpHVW9wZFd2dDd2cXJOU0otR19CbEtCTW9HMXZqX0JvZ0RjNDFMQnBscUExQzFObUw0Mmc?oc=5",
    "sentiment_score": -0.4,
    "impact": "MEDIUM",
    "keywords": [
      "inflation control",
      "price stability",
      "policy"
    ],
    "fetched_at": "2026-06-30T05:51:24.126547+00:00"
  },
  {
    "source": "CNBC",
    "headline": "Chip stocks rebound, and Goldman racks up a series of M&A wins",
    "url": "https://www.cnbc.com/2026/06/29/chip-stocks-rebound-and-goldman-racks-up-a-series-of-ma-wins-.html",
    "sentiment_score": 0.0,
    "impact": "LOW",
    "keywords": [
      "equity markets",
      "stocks",
      "M&A"
    ],
    "fetched_at": "2026-06-30T05:51:24.126547+00:00"
  },
  {
    "source": "Reuters",
    "headline": "Israel-Lebanon deal may entrench stalemate rather than end war, analysts say - Reuters",
    "url": "https://news.google.com/rss/articles/CBMiyAFBVV95cUxOQzVPS3VRVGFsSElBdURJN0sxVEZaalUtNGpETS1FQXJLNkhkeTJ5M1VaR19HcmpoZXpWY3FhX0F2S2RLWjlMNVM1UWJzbllJcGZic3VnLVJYMWMtRk1GcVFGa2RZREpvY3JadXJScDZCVVdwRmYwY0lPVGRiOVQyLWI4MUJnY28zWW43TmJoRUM5dkRaUUpwRGhUNFB5MWVDV3hCY1lDUHJzUVpsSXI3QUlwR0puQkU0R3BMMXFHTm9hUmU0QURWTQ?oc=5",
    "sentiment_score": 0.2,
    "impact": "LOW",
    "keywords": [
      "geopolitical risk",
      "Middle East",
      "uncertainty"
    ],
    "fetched_at": "2026-06-30T05:51:24.126547+00:00"
  },
  {
    "source": "Reuters",
    "headline": "Senior Lebanese official slams US-brokered deal with Israel, warns of divisions - Reuters",
    "url": "https://news.google.com/rss/articles/CBMiyAFBVV95cUxNdEcxa2lmSEt3VTljemt3NzlwaGdLWVZCTHdjYUJEVjlzZkNSTDUzUXRaQThvc1d1MTJBVVdERzF2Qno3YWthLWRDVGtKbHZxQ2xuVmNkWG43Ri1mWHM0TGJrX3F4TXlyaTdwYXBxQzRDaHNSOFhSZDhtS04tRGRIejNOZTdLSHBaS293OWNIMC12bV83anZQdDRra204aU0wSFI4NGZ1LTdHRHBfM1pSYWdXOHpZMUZzUnlwd0tGS3p6N3dsYzRxYQ?oc=5",
    "sentiment_score": 0.3,
    "impact": "MEDIUM",
    "keywords": [
      "regional tension",
      "political risk",
      "Middle East"
    ],
    "fetched_at": "2026-06-30T05:51:24.126547+00:00"
  },
  {
    "source": "Reuters",
    "headline": "How 5 weeks of war shattered some of Iran\u2019s cherished monuments - Reuters",
    "url": "https://news.google.com/rss/articles/CBMiigFBVV95cUxQZDF2cmU1OXB5Q1VfV0ZUM1VhZE51WVlXTnlrS2VUaC1oMldhNUYzUkFpRGdTNDg3b1RRSEZtYUVHamtJODBvMUFkMnpwZkhGS1NPMFp3TUlkdWs1VUhzN1Z4dEpybndfNDJEN1YtUnJXYXVlMDlkdVQ4d0JxRUxtdEx5QXE1NTN5OHc?oc=5",
    "sentiment_score": 0.2,
    "impact": "LOW",
    "keywords": [
      "geopolitical conflict",
      "war impact",
      "instability"
    ],
    "fetched_at": "2026-06-30T05:51:24.126547+00:00"
  },
  {
    "source": "Reuters",
    "headline": "Gold slips as US-Iran tensions spark inflation, rate hike fears - Reuters",
    "url": "https://news.google.com/rss/articles/CBMitgFBVV95cUxPSTVKRTRyZTc4cndMX2E0Mzd3UlROU1FJMWFsaWpkbDVuSUFiVldPeE1GRVFLbDVYeTZ5RTFXd08wUkYwU205amR5a1BIOTFTNGE1T01qMjNGSkJ2OXpjQVhWQ1JXSTdOeDBGb3I5czNDQ1VYck9ENEZJNVZMQk5Rc19tTWgzM3hGaC1uSlltSktpNWtyM3AtTTk3RkZJaFNpNjVFRXJUSWhuWEJGcnNUb1ZGVWstUQ?oc=5",
    "sentiment_score": 0.5,
    "impact": "MEDIUM",
    "keywords": [
      "inflation risk",
      "geopolitical tension",
      "rate hike"
    ],
    "fetched_at": "2026-06-30T05:51:24.126547+00:00"
  },
  {
    "source": "Reuters",
    "headline": "Stocks and oil prices rise with eyes on Iran; yen touches 40-year low vs dollar - Reuters",
    "url": "https://news.google.com/rss/articles/CBMigAFBVV95cUxPYUFwVXVYYUk3ZXZGYUhac1BmQjhYN1JiSHM5SlhvWW9taHVTRkFZeVlrNFVfTl8wQVY0VTc3ekNEd1EyX2NMYjdNZXFwWi1WMFJWTHVIaE8yNTNNVWR4NkFHelBmSFlwYWdjRTZQREo4elhtYnNhZ3RMMjg2ckttSw?oc=5",
    "sentiment_score": -0.3,
    "impact": "MEDIUM",
    "keywords": [
      "risk appetite",
      "inflation concerns",
      "yen weakness"
    ],
    "fetched_at": "2026-06-30T05:51:24.126547+00:00"
  },
  {
    "source": "Reuters",
    "headline": "Iran war developments, Fed rate path cues in focus for Indian rupee and bonds - Reuters",
    "url": "https://news.google.com/rss/articles/CBMiuwFBVV95cUxNU0tnYmloaHpIVTVmYUZHSUljRy1XNHN2VU8wSDVxSk5DRmJFUkNDWjNzOXJ6ejd0a0hGWmoxMWJncnZOQm5taGpMU09TMjBTMEFkUWlTZXVDMXRoUkhoZGRTWVdUTnVzaXhoRHlQUmloSnpPUTVBYU9rbFV0ZE1VTUFnZGZ2RkRTTWRjQ1dqVE9Telg2c285TlBTRFYyVDNFc1pxcUExa0lkZ3ZUTy1MZEp0N2pOTzg4ZFo4?oc=5",
    "sentiment_score": 0.3,
    "impact": "MEDIUM",
    "keywords": [
      "geopolitical risk",
      "inflation expectations",
      "monetary policy"
    ],
    "fetched_at": "2026-06-30T05:51:24.126547+00:00"
  },
  {
    "source": "CNBC",
    "headline": "Trading in these two ETFs suggests inflation fears are overblown",
    "url": "https://www.cnbc.com/2026/06/27/trading-in-these-two-etfs-suggests-inflation-fears-are-overblown.html",
    "sentiment_score": -0.5,
    "impact": "MEDIUM",
    "keywords": [
      "inflation deflation",
      "deflation narrative",
      "sentiment"
    ],
    "fetched_at": "2026-06-30T05:51:24.126547+00:00"
  },
  {
    "source": "Reuters",
    "headline": "Gold gains as dollar weakens; still on track for fourth straight weekly loss - Reuters",
    "url": "https://news.google.com/rss/articles/CBMipwFBVV95cUxQRXc4NjVKdS0yVG1sdzYzZEIwNno3QXhNVzFKRktkSHJZa3l0dUZFTmd2blZtbVVSM2MzR0dNX0VTR1VzMEd2d3NxQjROYU5LdF9zMVY3SkNsZzRSSUVPOFdnMEZ6Qm9CdmlNVWx4V2Z6UlhianlDVUZxMGw4WlNOUjlhS2VwcGRqZmEtTHJMTXlhUG1CdWhUR0w1WmhxZ1ZOSTFNdUI2NA?oc=5",
    "sentiment_score": 0.4,
    "impact": "MEDIUM",
    "keywords": [
      "dollar weakness",
      "weekly trend",
      "technical"
    ],
    "fetched_at": "2026-06-30T05:51:24.126547+00:00"
  },
  {
    "source": "Reuters",
    "headline": "US diesel refining economics remain firm despite Iran war truce - Reuters",
    "url": "https://news.google.com/rss/articles/CBMitgFBVV95cUxQaktNajNVTlRkTm1nVkRyMHNDc3FBTk5BRjRVVy16cjRNbFdhSFhYWkYtcy1wNlJkMzRjTWhnakNiUmJjZ3V1c2luUG9lNVcyaG1Semg3UkhQOHEtY2tFS1lQbkkwZll4U3MzU2J3QmJuQnRKUzFuVVJPQXpJNzRjNmd2Rzc2aC1XRDMxck1OcXlxd3dNM1pJQnFHb3Z1S2U5VmVMYWtNY190WmdtNmtKd29fQm8zZw?oc=5",
    "sentiment_score": -0.2,
    "impact": "LOW",
    "keywords": [
      "oil supply",
      "inflation outlook",
      "energy"
    ],
    "fetched_at": "2026-06-30T05:51:24.126547+00:00"
  },
  {
    "source": "Reuters",
    "headline": "UAE stresses Hormuz security in rare call with Iran after war tensions - Reuters",
    "url": "https://news.google.com/rss/articles/CBMivgFBVV95cUxOTFhOWjA0b0NFVmItV25IVHhmdUw2WmtfeGU1SXZ1ZjFsaHF4bnJrTVVVR0M5QlFfS3Z1Vk5Scm5CTjFCaXB3SVREeXctT1h4QlhwaDJKc2dQNGhTbTV2U243Q0kwUjhzUEJnak5RdzdLNkpyMUNVcjNOdWFsRXFYVUFlZFpzMm9fMmR3dXJpem1wMWhOWm5OVDJfd3NzX1hhOFlnYjJZMzNId2UyOUxMS3VrdmJCWmxsVnlpZ3NB?oc=5",
    "sentiment_score": 0.2,
    "impact": "LOW",
    "keywords": [
      "geopolitical risk",
      "strait security",
      "supply"
    ],
    "fetched_at": "2026-06-30T05:51:24.126547+00:00"
  },
  {
    "source": "Reuters",
    "headline": "UAE says false public warning caused by technical malfunction - Reuters",
    "url": "https://news.google.com/rss/articles/CBMitwFBVV95cUxQYTA4WmxkQjRfQjJKWUlDVzZuU0p0Sm8wS2g5c3JXay1qSXdTVHpsdVdDN3NwVEV3TnJZQ0RaV0htWm5xcnZ6LU96bXAza1RXeEhJUEN5UzNYN1IzTWZCeEFrUVdYNzRmdTNzaFAzNW9LWGQ1akpXOFlOdXI2NjA0UjVaSVJnenlsa2xmQ1lSTGZ3LTNVbWRJTG40aERIMjF4TGloTVcxRGFYMUhrMjdVdWExZHQyVW8?oc=5",
    "sentiment_score": 0.0,
    "impact": "LOW",
    "keywords": [
      "technical issue",
      "false alarm",
      "alert"
    ],
    "fetched_at": "2026-06-30T05:51:24.126547+00:00"
  },
  {
    "source": "ForexLive",
    "headline": "UK Q1 final GDP +0.6% vs +0.6% q/q prelim",
    "url": "https://investinglive.com/news/uk-q1-final-gdp-06-vs-06-qq-prelim-20260630/",
    "sentiment_score": 0.0,
    "impact": "LOW",
    "keywords": [
      "GDP",
      "UK",
      "no surprise"
    ],
    "fetched_at": "2026-06-30T06:06:36.351664+00:00"
  },
  {
    "source": "ForexLive",
    "headline": "Heads up: Germany states' CPI readings due later today",
    "url": "https://investinglive.com/news/heads-up-germany-states-cpi-readings-due-later-today-20260630/",
    "sentiment_score": 0.0,
    "impact": "LOW",
    "keywords": [
      "CPI",
      "Germany",
      "upcoming data"
    ],
    "fetched_at": "2026-06-30T06:06:36.351664+00:00"
  },
  {
    "source": "ForexLive",
    "headline": "ECB may see a case for July move on a negative June inflation surprise - report",
    "url": "https://investinglive.com/centralbank/ecb-may-see-a-case-for-july-move-on-a-negative-june-inflation-surprise-report-20260630/",
    "sentiment_score": 0.6,
    "impact": "MEDIUM",
    "keywords": [
      "ECB",
      "rate cut",
      "dovish inflation"
    ],
    "fetched_at": "2026-06-30T06:06:36.351664+00:00"
  },
  {
    "source": "ForexLive",
    "headline": "Gold Analysis Today: Gold Futures Test 3,989-3,995 Decision Zone",
    "url": "https://investinglive.com/commodities/gold-analysis-today-gold-futures-test-3989-3995-decision-zone-20260630/",
    "sentiment_score": 0.0,
    "impact": "LOW",
    "keywords": [
      "technical analysis",
      "price levels",
      "neutral"
    ],
    "fetched_at": "2026-06-30T06:06:36.351664+00:00"
  },
  {
    "source": "ForexLive",
    "headline": "ING: China's domestic demand engine sputtering despite stronger headline PMI",
    "url": "https://investinglive.com/news/ing-chinas-domestic-demand-engine-sputtering-despite-stronger-headline-pmi-20260630/",
    "sentiment_score": 0.5,
    "impact": "MEDIUM",
    "keywords": [
      "China demand weakness",
      "growth concern",
      "bullish gold"
    ],
    "fetched_at": "2026-06-30T06:06:36.351664+00:00"
  },
  {
    "source": "ForexLive",
    "headline": "China factory PMI beats forecast at 50.3 as AI-linked exports drive expansion",
    "url": "https://investinglive.com/news/china-factory-pmi-beats-forecast-at-503-as-ai-linked-exports-drive-expansion-20260630/",
    "sentiment_score": -0.5,
    "impact": "MEDIUM",
    "keywords": [
      "China PMI",
      "economic expansion",
      "risk-on"
    ],
    "fetched_at": "2026-06-30T06:06:36.351664+00:00"
  },
  {
    "source": "ForexLive",
    "headline": "China June Manufacturing PMI 50.3 (expected 50.1) Services 50.2 (49.9)",
    "url": "https://investinglive.com/news/china-june-manufacturing-pmi-503-expected-501-services-502-499-20260630/",
    "sentiment_score": -0.4,
    "impact": "MEDIUM",
    "keywords": [
      "China PMI beat",
      "expansion",
      "growth optimism"
    ],
    "fetched_at": "2026-06-30T06:06:36.351664+00:00"
  },
  {
    "source": "ForexLive",
    "headline": "Bank of Japan board member Sato will speak with media at 0800 GMT / 0400 US Eastern time",
    "url": "https://investinglive.com/centralbank/bank-of-japan-board-member-sato-will-speak-with-media-at-0800-gmt-0400-us-eastern-time-20260630/",
    "sentiment_score": 0.0,
    "impact": "LOW",
    "keywords": [
      "BOJ",
      "speaker",
      "event preview"
    ],
    "fetched_at": "2026-06-30T06:06:36.351664+00:00"
  },
  {
    "source": "ForexLive",
    "headline": "Former BOJ insider flags potential inflation running at 3% as case for early hike builds",
    "url": "https://investinglive.com/centralbank/former-boj-insider-flags-potential-inflation-running-at-3-as-case-for-early-hike-builds-20260630/",
    "sentiment_score": 0.7,
    "impact": "HIGH",
    "keywords": [
      "BOJ inflation",
      "rate hike",
      "hawkish pressure"
    ],
    "fetched_at": "2026-06-30T06:06:36.351664+00:00"
  },
  {
    "source": "ForexLive",
    "headline": "Rare earths, export controls and WTO reform headline new EU-China trade framework",
    "url": "https://investinglive.com/news/rare-earths-export-controls-and-wto-reform-headline-new-eu-china-trade-framework-20260629/",
    "sentiment_score": 0.0,
    "impact": "LOW",
    "keywords": [
      "trade",
      "geopolitics",
      "neutral for gold"
    ],
    "fetched_at": "2026-06-30T06:06:36.351664+00:00"
  },
  {
    "source": "FinancialJuice",
    "headline": "German Real Retail Sales YoY Actual 1.8% (Forecast -, Previous -0.3%)",
    "url": "https://www.financialjuice.com/News/9657703/German-Real-Retail-Sales-YoY-Actual-18-Forecast---Previous--03.aspx?xy=rss",
    "sentiment_score": -0.4,
    "impact": "MEDIUM",
    "keywords": [
      "German retail sales",
      "growth strength",
      "bearish"
    ],
    "fetched_at": "2026-06-30T06:06:36.351664+00:00"
  },
  {
    "source": "FinancialJuice",
    "headline": "German Real Retail Sales MoM Actual 1.1% (Forecast 0%, Previous -0.3%)",
    "url": "https://www.financialjuice.com/News/9657702/German-Real-Retail-Sales-MoM-Actual-11-Forecast-0-Previous--03.aspx?xy=rss",
    "sentiment_score": -0.4,
    "impact": "MEDIUM",
    "keywords": [
      "German retail beat",
      "economic strength",
      "bearish"
    ],
    "fetched_at": "2026-06-30T06:06:36.351664+00:00"
  },
  {
    "source": "FinancialJuice",
    "headline": "German Imports Prices MoM Actual 0.7% (Forecast 0.4%, Previous 1.2%)",
    "url": "https://www.financialjuice.com/News/9657701/German-Imports-Prices-MoM-Actual-07-Forecast-04-Previous-12.aspx?xy=rss",
    "sentiment_score": -0.2,
    "impact": "LOW",
    "keywords": [
      "import prices",
      "inflation moderating",
      "slightly bearish"
    ],
    "fetched_at": "2026-06-30T06:06:36.351664+00:00"
  },
  {
    "source": "FinancialJuice",
    "headline": "UK Business Investment QoQ Actual 0.94% (Forecast 0.7%, Previous 0.7%)",
    "url": "https://www.financialjuice.com/News/9657700/UK-Business-Investment-QoQ-Actual-094-Forecast-07-Previous-07.aspx?xy=rss",
    "sentiment_score": -0.2,
    "impact": "LOW",
    "keywords": [
      "UK business investment",
      "growth positive",
      "slightly bearish"
    ],
    "fetched_at": "2026-06-30T06:06:36.351664+00:00"
  },
  {
    "source": "FinancialJuice",
    "headline": "UK GDP YoY Actual 0.9% (Forecast 1.1%, Previous 1.1%)",
    "url": "https://www.financialjuice.com/News/9657699/UK-GDP-YoY-Actual-09-Forecast-11-Previous-11.aspx?xy=rss",
    "sentiment_score": 0.3,
    "impact": "MEDIUM",
    "keywords": [
      "UK GDP miss",
      "growth concern",
      "bullish gold"
    ],
    "fetched_at": "2026-06-30T06:06:36.351664+00:00"
  },
  {
    "source": "FinancialJuice",
    "headline": "UK GDP QoQ Actual 0.6% (Forecast 0.6%, Previous 0.6%)",
    "url": "https://www.financialjuice.com/News/9657698/UK-GDP-QoQ-Actual-06-Forecast-06-Previous-06.aspx?xy=rss",
    "sentiment_score": 0.0,
    "impact": "LOW",
    "keywords": [
      "UK GDP",
      "in-line",
      "no surprise"
    ],
    "fetched_at": "2026-06-30T06:06:36.351664+00:00"
  },
  {
    "source": "FinancialJuice",
    "headline": "UK Current Account Actual -22.134B (Forecast -21.3B, Previous -18.392B)",
    "url": "https://www.financialjuice.com/News/9657697/UK-Current-Account-Actual--22134B-Forecast--213B-Previous--18392B.aspx?xy=rss",
    "sentiment_score": 0.4,
    "impact": "MEDIUM",
    "keywords": [
      "UK current account",
      "deficit widening",
      "currency weakness"
    ],
    "fetched_at": "2026-06-30T06:06:36.351664+00:00"
  },
  {
    "source": "FinancialJuice",
    "headline": "Finland May GDP rises 2.8% year on year: Statistics Finland",
    "url": "https://www.financialjuice.com/News/9657653/Finland-May-GDP-rises-28-year-on-year-Statistics-Finland.aspx?xy=rss",
    "sentiment_score": -0.3,
    "impact": "LOW",
    "keywords": [
      "Finland GDP growth",
      "economic strength",
      "risk-on"
    ],
    "fetched_at": "2026-06-30T06:06:36.351664+00:00"
  },
  {
    "source": "FinancialJuice",
    "headline": "Finland's May GDP growth at 2.8% year on year: Statistics Finland",
    "url": "https://www.financialjuice.com/News/9657652/Finlands-May-GDP-growth-at-28-year-on-year-Statistics-Finland.aspx?xy=rss",
    "sentiment_score": -0.3,
    "impact": "LOW",
    "keywords": [
      "Finland GDP growth",
      "economic expansion",
      "risk-on"
    ],
    "fetched_at": "2026-06-30T06:06:36.351664+00:00"
  },
  {
    "source": "FinancialJuice",
    "headline": "Japanese Housing Starts YoY Actual 33.86% (Forecast 31.8%, Previous 11.4%)",
    "url": "https://www.financialjuice.com/News/9657651/Japanese-Housing-Starts-YoY-Actual-3386-Forecast-318-Previous-114.aspx?xy=rss",
    "sentiment_score": -0.4,
    "impact": "MEDIUM",
    "keywords": [
      "Japan housing",
      "economic strength",
      "slightly bearish"
    ],
    "fetched_at": "2026-06-30T06:06:36.351664+00:00"
  },
  {
    "source": "FinancialJuice",
    "headline": "Central banks plan to boost euro holdings, but 60% hesitate over lower returns: OMFIF finds",
    "url": "https://www.financialjuice.com/News/9657650/Central-banks-plan-to-boost-euro-holdings-but-60-hesitate-over-lower-returns-OMFIF-finds.aspx?xy=rss",
    "sentiment_score": 0.6,
    "impact": "MEDIUM",
    "keywords": [
      "central banks",
      "diversification",
      "euro holdings"
    ],
    "fetched_at": "2026-06-30T06:06:36.351664+00:00"
  },
  {
    "source": "FinancialJuice",
    "headline": "For first time, more central banks plan to reduce dollar allocations than raise them in next decade: OMFIF survey finds",
    "url": "https://www.financialjuice.com/News/9657649/For-first-time-more-central-banks-plan-to-reduce-dollar-allocations-than-raise-them-in-next-decade-OMFIF-survey-finds.aspx?xy=rss",
    "sentiment_score": 0.7,
    "impact": "HIGH",
    "keywords": [
      "de-dollarisation",
      "dollar reduction",
      "reserve shift"
    ],
    "fetched_at": "2026-06-30T06:06:36.351664+00:00"
  },
  {
    "source": "FinancialJuice",
    "headline": "Survey finds 93% of central banks see renminbi as diversification tool, but market structure hinders uptake",
    "url": "https://www.financialjuice.com/News/9657648/Survey-finds-93-of-central-banks-see-renminbi-as-diversification-tool-but-market-structure-hinders-uptake.aspx?xy=rss",
    "sentiment_score": 0.5,
    "impact": "MEDIUM",
    "keywords": [
      "renminbi",
      "diversification",
      "central banks"
    ],
    "fetched_at": "2026-06-30T06:06:36.351664+00:00"
  },
  {
    "source": "FinancialJuice",
    "headline": "82% of central banks hold physical gold in 2026, up from 71% last year: OMFIF survey",
    "url": "https://www.financialjuice.com/News/9657647/82-of-central-banks-hold-physical-gold-in-2026-up-from-71-last-year-OMFIF-survey.aspx?xy=rss",
    "sentiment_score": 0.9,
    "impact": "HIGH",
    "keywords": [
      "gold holdings",
      "central banks",
      "physical gold demand"
    ],
    "fetched_at": "2026-06-30T06:06:36.351664+00:00"
  },
  {
    "source": "FinancialJuice",
    "headline": "Two-thirds of central banks plan to boost AI adoption in next one to two years, survey finds",
    "url": "https://www.financialjuice.com/News/9657646/Two-thirds-of-central-banks-plan-to-boost-AI-adoption-in-next-one-to-two-years-survey-finds.aspx?xy=rss",
    "sentiment_score": 0.0,
    "impact": "LOW",
    "keywords": [
      "AI adoption",
      "technology",
      "operations"
    ],
    "fetched_at": "2026-06-30T06:06:36.351664+00:00"
  },
  {
    "source": "FinancialJuice",
    "headline": "Central banks indicate gradual shift toward de-dollarisation: OMFIF survey finds",
    "url": "https://www.financialjuice.com/News/9657645/Central-banks-indicate-gradual-shift-toward-de-dollarisation-OMFIF-survey-finds.aspx?xy=rss",
    "sentiment_score": 0.8,
    "impact": "HIGH",
    "keywords": [
      "de-dollarisation",
      "reserve diversification",
      "dollar weakness"
    ],
    "fetched_at": "2026-06-30T06:06:36.351664+00:00"
  },
  {
    "source": "FinancialJuice",
    "headline": "Two Revolutionary Guards killed in attack by unidentified gunmen in western Iran: state media",
    "url": "https://www.financialjuice.com/News/9657644/Two-Revolutionary-Guards-killed-in-attack-by-unidentified-gunmen-in-western-Iran-state-media.aspx?xy=rss",
    "sentiment_score": 0.3,
    "impact": "LOW",
    "keywords": [
      "geopolitical risk",
      "Iran",
      "security"
    ],
    "fetched_at": "2026-06-30T06:06:36.351664+00:00"
  },
  {
    "source": "FinancialJuice",
    "headline": "Japan kerosene sales rise 10.6% year-on-year: Meti",
    "url": "https://www.financialjuice.com/News/9657614/Japan-kerosene-sales-rise-106-year-on-year-Meti.aspx?xy=rss",
    "sentiment_score": 0.0,
    "impact": "LOW",
    "keywords": [
      "Japan",
      "energy demand",
      "domestic"
    ],
    "fetched_at": "2026-06-30T06:06:36.351664+00:00"
  },
  {
    "source": "FinancialJuice",
    "headline": "Japan gasoline sales decline 0.9% yr/yr: Meti",
    "url": "https://www.financialjuice.com/News/9657613/Japan-gasoline-sales-decline-09-yryr-Meti.aspx?xy=rss",
    "sentiment_score": 0.0,
    "impact": "LOW",
    "keywords": [
      "Japan",
      "gasoline sales",
      "domestic"
    ],
    "fetched_at": "2026-06-30T06:06:36.351664+00:00"
  },
  {
    "source": "FinancialJuice",
    "headline": "Japan may crude oil imports drop 38.4% yr/yr: meti",
    "url": "https://www.financialjuice.com/News/9657612/Japan-may-crude-oil-imports-drop-384-yryr-meti.aspx?xy=rss",
    "sentiment_score": -0.2,
    "impact": "LOW",
    "keywords": [
      "oil demand",
      "Japan imports",
      "energy weakness"
    ],
    "fetched_at": "2026-06-30T06:06:36.351664+00:00"
  },
  {
    "source": "FinancialJuice",
    "headline": "Japan May total oil product sales drop 5.2% year on year: Meti",
    "url": "https://www.financialjuice.com/News/9657611/Japan-May-total-oil-product-sales-drop-52-year-on-year-Meti.aspx?xy=rss",
    "sentiment_score": 0.0,
    "impact": "LOW",
    "keywords": [
      "Japan",
      "energy sales",
      "domestic"
    ],
    "fetched_at": "2026-06-30T06:06:36.351664+00:00"
  },
  {
    "source": "FinancialJuice",
    "headline": "Russia downs 419 Ukrainian drones overnight: Russian newswires cite defense ministry",
    "url": "https://www.financialjuice.com/News/9657610/Russia-downs-419-Ukrainian-drones-overnight-Russian-newswires-cite-defense-ministry.aspx?xy=rss",
    "sentiment_score": 0.2,
    "impact": "LOW",
    "keywords": [
      "geopolitical risk",
      "Ukraine",
      "conflict"
    ],
    "fetched_at": "2026-06-30T06:06:36.351664+00:00"
  },
  {
    "source": "FinancialJuice",
    "headline": "Unisound AI Technology Co: Contract Price for AI Chip Innovation HQ Project Set at RMB253 Million",
    "url": "https://www.financialjuice.com/News/9657601/Unisound-AI-Technology-Co-Contract-Price-for-AI-Chip-Innovation-HQ-Project-Set-at-RMB253-Million.aspx?xy=rss",
    "sentiment_score": 0.0,
    "impact": "LOW",
    "keywords": [
      "AI technology",
      "China",
      "corporate"
    ],
    "fetched_at": "2026-06-30T06:06:36.351664+00:00"
  },
  {
    "source": "FinancialJuice",
    "headline": "Unisound AI Technology enters general contracting engineering agreement with Shuanglou Construction on June 30, 2026",
    "url": "https://www.financialjuice.com/News/9657600/Unisound-AI-Technology-enters-general-contracting-engineering-agreement-with-Shuanglou-Construction-on-June-30-2026.aspx?xy=rss",
    "sentiment_score": 0.0,
    "impact": "LOW",
    "keywords": [
      "construction contract",
      "China",
      "corporate"
    ],
    "fetched_at": "2026-06-30T06:06:36.351664+00:00"
  },
  {
    "source": "FinancialJuice",
    "headline": "ECB sources: sharp June inflation jump may refocus July rate increase",
    "url": "https://www.financialjuice.com/News/9657576/ECB-sources-sharp-June-inflation-jump-may-refocus-July-rate-increase.aspx?xy=rss",
    "sentiment_score": -0.5,
    "impact": "MEDIUM",
    "keywords": [
      "rate hike",
      "ECB hawkish",
      "inflation pressure"
    ],
    "fetched_at": "2026-06-30T06:06:36.351664+00:00"
  },
  {
    "source": "FinancialJuice",
    "headline": "ECB sources: second-round inflation impacts minimal so far",
    "url": "https://www.financialjuice.com/News/9657575/ECB-sources-second-round-inflation-impacts-minimal-so-far.aspx?xy=rss",
    "sentiment_score": -0.3,
    "impact": "MEDIUM",
    "keywords": [
      "inflation moderate",
      "rate uncertainty",
      "second-round effects"
    ],
    "fetched_at": "2026-06-30T06:06:36.351664+00:00"
  },
  {
    "source": "FinancialJuice",
    "headline": "ECB sources: swift oil price drop reduces pressure for July rate increase; September hike now more probable",
    "url": "https://www.financialjuice.com/News/9657574/ECB-sources-swift-oil-price-drop-reduces-pressure-for-July-rate-increase-September-hike-now-more-probable.aspx?xy=rss",
    "sentiment_score": 0.3,
    "impact": "MEDIUM",
    "keywords": [
      "oil price decline",
      "rate postponement",
      "dovish signal"
    ],
    "fetched_at": "2026-06-30T06:06:36.351664+00:00"
  },
  {
    "source": "FinancialJuice",
    "headline": "ECB sources: rate increase remains possible, even if timing could be postponed",
    "url": "https://www.financialjuice.com/News/9657573/ECB-sources-rate-increase-remains-possible-even-if-timing-could-be-postponed.aspx?xy=rss",
    "sentiment_score": -0.4,
    "impact": "MEDIUM",
    "keywords": [
      "rate increase",
      "ECB tightening",
      "monetary policy"
    ],
    "fetched_at": "2026-06-30T06:06:36.351664+00:00"
  },
  {
    "source": "FinancialJuice",
    "headline": "China\u2019s central bank conducts overnight reverse repos Tuesday, keeps borrowing cost at 1.25%, sources say",
    "url": "https://www.financialjuice.com/News/9657512/Chinas-central-bank-conducts-overnight-reverse-repos-Tuesday-keeps-borrowing-cost-at-125-sources-say.aspx?xy=rss",
    "sentiment_score": 0.0,
    "impact": "LOW",
    "keywords": [
      "PBOC",
      "reverse repos",
      "liquidity management"
    ],
    "fetched_at": "2026-06-30T06:06:36.351664+00:00"
  },
  {
    "source": "FinancialJuice",
    "headline": "Japan finmin katayama: declines to comment on particular fx rates",
    "url": "https://www.financialjuice.com/News/9657404/Japan-finmin-katayama-declines-to-comment-on-particular-fx-rates.aspx?xy=rss",
    "sentiment_score": 0.0,
    "impact": "LOW",
    "keywords": [
      "Japan",
      "FX policy",
      "commentary"
    ],
    "fetched_at": "2026-06-30T06:06:36.351664+00:00"
  },
  {
    "source": "FinancialJuice",
    "headline": "Japan finance minister Katayama: measures could feature decisive steps as agreed in recent virtual meeting with U.S. (not in joint statement with U.S.)",
    "url": "https://www.financialjuice.com/News/9657403/Japan-finance-minister-Katayama-measures-could-feature-decisive-steps-as-agreed-in-recent-virtual-meeting-with-US-not-in-joint-statement-with-US.aspx?xy=rss",
    "sentiment_score": -0.3,
    "impact": "MEDIUM",
    "keywords": [
      "Japan",
      "fiscal measures",
      "USD strength"
    ],
    "fetched_at": "2026-06-30T06:06:36.351664+00:00"
  },
  {
    "source": "FinancialJuice",
    "headline": "RBA: ongoing weak productivity may hinder progress in bringing inflation back to target",
    "url": "https://www.financialjuice.com/News/9657373/RBA-ongoing-weak-productivity-may-hinder-progress-in-bringing-inflation-back-to-target.aspx?xy=rss",
    "sentiment_score": 0.4,
    "impact": "MEDIUM",
    "keywords": [
      "RBA",
      "inflation persistence",
      "rate hold"
    ],
    "fetched_at": "2026-06-30T06:06:36.351664+00:00"
  },
  {
    "source": "FinancialJuice",
    "headline": "Chinese NBS Non-Manufacturing PMI Actual 50.2 (Forecast 49.9, Previous 50.1)",
    "url": "https://www.financialjuice.com/News/9657363/Chinese-NBS-Non-Manufacturing-PMI-Actual-502-Forecast-499-Previous-501.aspx?xy=rss",
    "sentiment_score": 0.2,
    "impact": "LOW",
    "keywords": [
      "China PMI",
      "manufacturing",
      "beat forecast"
    ],
    "fetched_at": "2026-06-30T06:06:36.351664+00:00"
  },
  {
    "source": "FinancialJuice",
    "headline": "Australian Housing Credit Actual 0.5% (Forecast -, Previous 0.6%)",
    "url": "https://www.financialjuice.com/News/9657360/Australian-Housing-Credit-Actual-05-Forecast---Previous-06.aspx?xy=rss",
    "sentiment_score": 0.1,
    "impact": "LOW",
    "keywords": [
      "Australia",
      "housing credit",
      "slowdown"
    ],
    "fetched_at": "2026-06-30T06:06:36.351664+00:00"
  },
  {
    "source": "FinancialJuice",
    "headline": "China June official non-manufacturing PMI climbs to 50.2 from 50.1 in May",
    "url": "https://www.financialjuice.com/News/9657368/China-June-official-non-manufacturing-PMI-climbs-to-502-from-501-in-May.aspx?xy=rss",
    "sentiment_score": 0.2,
    "impact": "LOW",
    "keywords": [
      "China PMI",
      "non-manufacturing",
      "beat"
    ],
    "fetched_at": "2026-06-30T06:06:36.351664+00:00"
  },
  {
    "source": "FinancialJuice",
    "headline": "China June official composite PMI at 50.6",
    "url": "https://www.financialjuice.com/News/9657367/China-June-official-composite-PMI-at-506.aspx?xy=rss",
    "sentiment_score": 0.2,
    "impact": "LOW",
    "keywords": [
      "China composite",
      "PMI expansion",
      "stability"
    ],
    "fetched_at": "2026-06-30T06:06:36.351664+00:00"
  },
  {
    "source": "FinancialJuice",
    "headline": "Chinese Composite PMI Actual 50.6 (Forecast -, Previous 50.5)",
    "url": "https://www.financialjuice.com/News/9657365/Chinese-Composite-PMI-Actual-506-Forecast---Previous-505.aspx?xy=rss",
    "sentiment_score": 0.2,
    "impact": "LOW",
    "keywords": [
      "China PMI",
      "manufacturing",
      "beat forecast"
    ],
    "fetched_at": "2026-06-30T06:06:36.351664+00:00"
  },
  {
    "source": "FinancialJuice",
    "headline": "Chinese NBS Manufacturing PMI Actual 50.3 (Forecast 50.1, Previous 50.0)",
    "url": "https://www.financialjuice.com/News/9657364/Chinese-NBS-Manufacturing-PMI-Actual-503-Forecast-501-Previous-500.aspx?xy=rss",
    "sentiment_score": 0.1,
    "impact": "LOW",
    "keywords": [
      "Australia",
      "credit growth",
      "modest"
    ],
    "fetched_at": "2026-06-30T06:06:36.351664+00:00"
  },
  {
    "source": "FinancialJuice",
    "headline": "Australia May housing credit rises 0.5% month-on-month, seasonally adjusted: central bank",
    "url": "https://www.financialjuice.com/News/9657362/Australia-May-housing-credit-rises-05-month-on-month-seasonally-adjusted-central-bank.aspx?xy=rss",
    "sentiment_score": 0.1,
    "impact": "LOW",
    "keywords": [
      "Australia",
      "private credit",
      "stable"
    ],
    "fetched_at": "2026-06-30T06:06:36.351664+00:00"
  },
  {
    "source": "FinancialJuice",
    "headline": "Australia may see private-sector credit rise 0.7% month on month, seasonally adjusted: central bank",
    "url": "https://www.financialjuice.com/News/9657361/Australia-may-see-private-sector-credit-rise-07-month-on-month-seasonally-adjusted-central-bank.aspx?xy=rss",
    "sentiment_score": 0.0,
    "impact": "LOW",
    "keywords": [
      "Australia",
      "spending",
      "resilience"
    ],
    "fetched_at": "2026-06-30T06:06:36.351664+00:00"
  },
  {
    "source": "FinancialJuice",
    "headline": "Australian Private Sector Credit Actual 0.7% (Forecast 0.6%, Previous 0.7%)",
    "url": "https://www.financialjuice.com/News/9657359/Australian-Private-Sector-Credit-Actual-07-Forecast-06-Previous-07.aspx?xy=rss",
    "sentiment_score": -0.4,
    "impact": "MEDIUM",
    "keywords": [
      "RBA",
      "oil inflation",
      "hawkish"
    ],
    "fetched_at": "2026-06-30T06:06:36.351664+00:00"
  },
  {
    "source": "FinancialJuice",
    "headline": "Rba: Household spending increase has not eased significantly",
    "url": "https://www.financialjuice.com/News/9657358/Rba-Household-spending-increase-has-not-eased-significantly.aspx?xy=rss",
    "sentiment_score": 0.3,
    "impact": "MEDIUM",
    "keywords": [
      "RBA",
      "housing risks",
      "growth concerns"
    ],
    "fetched_at": "2026-06-30T06:06:36.351664+00:00"
  },
  {
    "source": "FinancialJuice",
    "headline": "RBA: sustained high oil prices may influence price and wage-setting behavior",
    "url": "https://www.financialjuice.com/News/9657357/RBA-sustained-high-oil-prices-may-influence-price-and-wage-setting-behavior.aspx?xy=rss",
    "sentiment_score": -0.2,
    "impact": "LOW",
    "keywords": [
      "RBA",
      "data centres",
      "capacity"
    ],
    "fetched_at": "2026-06-30T06:06:36.351664+00:00"
  },
  {
    "source": "FinancialJuice",
    "headline": "RBA: members highlight risks of possible significant decline in housing markets",
    "url": "https://www.financialjuice.com/News/9657356/RBA-members-highlight-risks-of-possible-significant-decline-in-housing-markets.aspx?xy=rss",
    "sentiment_score": -0.6,
    "impact": "HIGH",
    "keywords": [
      "RBA",
      "rate hikes",
      "hawkish"
    ],
    "fetched_at": "2026-06-30T06:06:36.351664+00:00"
  },
  {
    "source": "FinancialJuice",
    "headline": "RBA Discussed Whether Robust Data Centre Activity Might Worsen Capacity Strains in Economy",
    "url": "https://www.financialjuice.com/News/9657355/RBA-Discussed-Whether-Robust-Data-Centre-Activity-Might-Worsen-Capacity-Strains-in-Economy.aspx?xy=rss",
    "sentiment_score": 0.5,
    "impact": "HIGH",
    "keywords": [
      "geopolitical",
      "Middle East",
      "inflation risk"
    ],
    "fetched_at": "2026-06-30T06:06:36.351664+00:00"
  },
  {
    "source": "FinancialJuice",
    "headline": "RBA: Will take necessary steps to ensure price stability, including potential rate hikes",
    "url": "https://www.financialjuice.com/News/9657354/RBA-Will-take-necessary-steps-to-ensure-price-stability-including-potential-rate-hikes.aspx?xy=rss",
    "sentiment_score": -0.5,
    "impact": "HIGH",
    "keywords": [
      "RBA",
      "excess demand",
      "hawkish"
    ],
    "fetched_at": "2026-06-30T06:06:36.351664+00:00"
  },
  {
    "source": "FinancialJuice",
    "headline": "RBA: Middle East conflict continues to present significant upside risks for inflation, downside risks for growth",
    "url": "https://www.financialjuice.com/News/9657353/RBA-Middle-East-conflict-continues-to-present-significant-upside-risks-for-inflation-downside-risks-for-growth.aspx?xy=rss",
    "sentiment_score": -0.4,
    "impact": "MEDIUM",
    "keywords": [
      "RBA",
      "tighter conditions",
      "rate cycle"
    ],
    "fetched_at": "2026-06-30T06:06:36.351664+00:00"
  },
  {
    "source": "FinancialJuice",
    "headline": "Rba: Economy running with excess demand, broad inflationary pressures",
    "url": "https://www.financialjuice.com/News/9657352/Rba-Economy-running-with-excess-demand-broad-inflationary-pressures.aspx?xy=rss",
    "sentiment_score": 0.3,
    "impact": "MEDIUM",
    "keywords": [
      "RBA",
      "housing softness",
      "growth risk"
    ],
    "fetched_at": "2026-06-30T06:06:36.351664+00:00"
  },
  {
    "source": "FinancialJuice",
    "headline": "Rba: weakening housing market, anticipated slowdown in housing credit indicate tighter conditions",
    "url": "https://www.financialjuice.com/News/9657351/Rba-weakening-housing-market-anticipated-slowdown-in-housing-credit-indicate-tighter-conditions.aspx?xy=rss",
    "sentiment_score": 0.6,
    "impact": "MEDIUM",
    "keywords": [
      "economic slowdown",
      "RBA dovish",
      "rate cut signal"
    ],
    "fetched_at": "2026-06-30T06:06:36.351664+00:00"
  },
  {
    "source": "FinancialJuice",
    "headline": "RBA board noted housing market softer than expected amid rate increases, tax adjustments",
    "url": "https://www.financialjuice.com/News/9657350/RBA-board-noted-housing-market-softer-than-expected-amid-rate-increases-tax-adjustments.aspx?xy=rss",
    "sentiment_score": 0.5,
    "impact": "MEDIUM",
    "keywords": [
      "tight conditions",
      "RBA hawkish",
      "monetary policy"
    ],
    "fetched_at": "2026-06-30T06:06:36.351664+00:00"
  },
  {
    "source": "FinancialJuice",
    "headline": "RBA: Recent data varied, indicates economy slowing broadly as anticipated",
    "url": "https://www.financialjuice.com/News/9657349/RBA-Recent-data-varied-indicates-economy-slowing-broadly-as-anticipated.aspx?xy=rss",
    "sentiment_score": 0.7,
    "impact": "MEDIUM",
    "keywords": [
      "liquidity support",
      "China stimulus",
      "yuan weakness"
    ],
    "fetched_at": "2026-06-30T06:06:36.351664+00:00"
  },
  {
    "source": "FinancialJuice",
    "headline": "RBA board agrees financial conditions are likely somewhat tight",
    "url": "https://www.financialjuice.com/News/9657348/RBA-board-agrees-financial-conditions-are-likely-somewhat-tight.aspx?xy=rss",
    "sentiment_score": 0.6,
    "impact": "MEDIUM",
    "keywords": [
      "liquidity injection",
      "reverse repos",
      "credit easing"
    ],
    "fetched_at": "2026-06-30T06:06:36.351664+00:00"
  },
  {
    "source": "FinancialJuice",
    "headline": "China\u2019s central bank pumps 600 billion yuan via overnight reverse repos: statement",
    "url": "https://www.financialjuice.com/News/9657347/Chinas-central-bank-pumps-600-billion-yuan-via-overnight-reverse-repos-statement.aspx?xy=rss",
    "sentiment_score": -0.3,
    "impact": "LOW",
    "keywords": [
      "trade friction",
      "China restrictions",
      "risk sentiment"
    ],
    "fetched_at": "2026-06-30T06:06:36.351664+00:00"
  },
  {
    "source": "FinancialJuice",
    "headline": "China c.bank pumps 69.5 billion yuan through 7-day reverse repos at 1.40%: statement",
    "url": "https://www.financialjuice.com/News/9657346/China-cbank-pumps-695-billion-yuan-through-7-day-reverse-repos-at-140-statement.aspx?xy=rss",
    "sentiment_score": 0.5,
    "impact": "MEDIUM",
    "keywords": [
      "dollar liquidity",
      "interbank conditions",
      "risk-on"
    ],
    "fetched_at": "2026-06-30T06:06:36.351664+00:00"
  },
  {
    "source": "FinancialJuice",
    "headline": "Japan Industry Minister: China's export restrictions affecting Japanese firms with delayed approvals and extended customs checks",
    "url": "https://www.financialjuice.com/News/9657345/Japan-Industry-Minister-Chinas-export-restrictions-affecting-Japanese-firms-with-delayed-approvals-and-extended-customs-checks.aspx?xy=rss",
    "sentiment_score": -0.4,
    "impact": "MEDIUM",
    "keywords": [
      "yen intervention",
      "currency support",
      "dollar strength"
    ],
    "fetched_at": "2026-06-30T06:06:36.351664+00:00"
  },
  {
    "source": "FinancialJuice",
    "headline": "China's interbank dollar lending sentiment index climbs to record-high 74, indicating improved liquidity conditions",
    "url": "https://www.financialjuice.com/News/9657344/Chinas-interbank-dollar-lending-sentiment-index-climbs-to-record-high-74-indicating-improved-liquidity-conditions.aspx?xy=rss",
    "sentiment_score": -0.5,
    "impact": "MEDIUM",
    "keywords": [
      "yen intervention",
      "currency defense",
      "dollar strength"
    ],
    "fetched_at": "2026-06-30T06:06:36.351664+00:00"
  },
  {
    "source": "FinancialJuice",
    "headline": "Japan finance minister Katayama: measures could include decisive steps as agreed in joint statement with US",
    "url": "https://www.financialjuice.com/News/9657327/Japan-finance-minister-Katayama-measures-could-include-decisive-steps-as-agreed-in-joint-statement-with-US.aspx?xy=rss",
    "sentiment_score": 0.0,
    "impact": "LOW",
    "keywords": [
      "non-committal",
      "no guidance",
      "neutral"
    ],
    "fetched_at": "2026-06-30T06:06:36.351664+00:00"
  },
  {
    "source": "FinancialJuice",
    "headline": "Japan Finmin Katayama: will act suitably on currency fluctuations whenever required",
    "url": "https://www.financialjuice.com/News/9657326/Japan-Finmin-Katayama-will-act-suitably-on-currency-fluctuations-whenever-required.aspx?xy=rss",
    "sentiment_score": 0.0,
    "impact": "LOW",
    "keywords": [
      "geopolitical",
      "shipping",
      "unrelated"
    ],
    "fetched_at": "2026-06-30T06:06:36.351664+00:00"
  },
  {
    "source": "FinancialJuice",
    "headline": "Japan Finance Minister Katayama: declines to comment on specific currency levels",
    "url": "https://www.financialjuice.com/News/9657325/Japan-Finance-Minister-Katayama-declines-to-comment-on-specific-currency-levels.aspx?xy=rss",
    "sentiment_score": 0.0,
    "impact": "LOW",
    "keywords": [
      "social security",
      "taxes",
      "unrelated"
    ],
    "fetched_at": "2026-06-30T06:06:36.351664+00:00"
  },
  {
    "source": "FinancialJuice",
    "headline": "South Korea President Lee: all ships but two leave Strait of Hormuz",
    "url": "https://www.financialjuice.com/News/9657324/South-Korea-President-Lee-all-ships-but-two-leave-Strait-of-Hormuz.aspx?xy=rss",
    "sentiment_score": 0.0,
    "impact": "LOW",
    "keywords": [
      "equity strategy",
      "stock picking",
      "unrelated"
    ],
    "fetched_at": "2026-06-30T06:06:36.351664+00:00"
  },
  {
    "source": "MarketWatch Top",
    "headline": "\u2018I claimed Social Security at 62\u2019: At 76, I\u2019m working at Walmart. Why do I still owe payroll taxes?",
    "url": "https://www.marketwatch.com/story/i-claimed-social-security-at-62-at-76-im-working-at-walmart-why-do-i-still-owe-payroll-taxes-8e22a97c?mod=mw_rss_topstories",
    "sentiment_score": 0.3,
    "impact": "LOW",
    "keywords": [
      "risk appetite",
      "China recovery",
      "equity strength"
    ],
    "fetched_at": "2026-06-30T06:06:36.351664+00:00"
  },
  {
    "source": "MarketWatch Top",
    "headline": "Value stocks beat growth when inflation is high. Here are 13 stocks top newsletters are betting on now.",
    "url": "https://www.marketwatch.com/story/value-stocks-beat-growth-when-inflation-is-high-here-are-13-stocks-top-newsletters-are-betting-on-now-f6f4a265?mod=mw_rss_topstories",
    "sentiment_score": 0.0,
    "impact": "LOW",
    "keywords": [
      "philanthropy",
      "Buffett",
      "unrelated"
    ],
    "fetched_at": "2026-06-30T06:06:36.351664+00:00"
  },
  {
    "source": "Investing.com Comm",
    "headline": "Asia stocks rise on upbeat China PMI; tech spurs bumper quarter",
    "url": "https://www.investing.com/news/stock-market-news/asian-stocks-mixed-as-china-pmi-offsets-caution-ahead-of-us-jobs-data-4766836",
    "sentiment_score": -0.7,
    "impact": "HIGH",
    "keywords": [
      "yen weakness",
      "dollar strength",
      "BOJ inaction"
    ],
    "fetched_at": "2026-06-30T06:06:36.351664+00:00"
  },
  {
    "source": "Investing.com Comm",
    "headline": "Warren Buffett skips donation to Gates Foundation amid Epstein review, WSJ reports",
    "url": "https://www.investing.com/news/stock-market-news/warren-buffett-skips-donation-to-gates-foundation-amid-epstein-review-wsj-reports-4766827",
    "sentiment_score": -0.5,
    "impact": "MEDIUM",
    "keywords": [
      "dollar weakness",
      "rate expectations",
      "Fed pause"
    ],
    "fetched_at": "2026-06-30T06:06:36.351664+00:00"
  },
  {
    "source": "Investing.com Forex",
    "headline": "Yen hits 40-year low amid intervention fears; yuan steadies after China PMI",
    "url": "https://www.investing.com/news/forex-news/yen-hits-40year-low-on-intervention-fears-yuan-steadies-after-china-pmi-4766858",
    "sentiment_score": -0.6,
    "impact": "MEDIUM",
    "keywords": [
      "dollar decline",
      "peak dollar",
      "sell signal"
    ],
    "fetched_at": "2026-06-30T06:06:36.351664+00:00"
  },
  {
    "source": "Investing.com Forex",
    "headline": "Dollar snaps two-week win streak as traders eye labor market data for rate cues",
    "url": "https://www.investing.com/news/forex-news/asia-fx-steady-as-traders-weigh-fragile-iran-ceasefire-busy-data-week-4764221",
    "sentiment_score": -0.4,
    "impact": "MEDIUM",
    "keywords": [
      "CAD weakness",
      "commodity pressure",
      "risk-off"
    ],
    "fetched_at": "2026-06-30T06:06:36.351664+00:00"
  },
  {
    "source": "Investing.com Forex",
    "headline": "Natixis says dollar rally has peaked, recommends selling greenback",
    "url": "https://www.investing.com/news/forex-news/natixis-says-dollar-rally-has-peaked-recommends-selling-greenback-93CH-4766005",
    "sentiment_score": -0.7,
    "impact": "HIGH",
    "keywords": [
      "yen weakness",
      "dollar strength",
      "carry trade"
    ],
    "fetched_at": "2026-06-30T06:06:36.351664+00:00"
  },
  {
    "source": "Investing.com Forex",
    "headline": "Canadian dollar falls as speculators increase bearish bets",
    "url": "https://www.investing.com/news/forex-news/canadian-dollar-falls-as-speculators-increase-bearish-bets-93CH-4765929",
    "sentiment_score": -0.8,
    "impact": "HIGH",
    "keywords": [
      "yen collapse",
      "dollar strength",
      "deflationary pressure"
    ],
    "fetched_at": "2026-06-30T06:06:36.351664+00:00"
  },
  {
    "source": "Investing.com Forex",
    "headline": "Japanese Yen falls to 40-year low against dollar",
    "url": "https://www.investing.com/news/forex-news/japanese-yen-falls-to-40year-low-against-dollar-4765727",
    "sentiment_score": 0.3,
    "impact": "LOW",
    "keywords": [
      "dollar weakness",
      "pound strength",
      "currency"
    ],
    "fetched_at": "2026-06-30T06:06:36.351664+00:00"
  },
  {
    "source": "Investing.com Forex",
    "headline": "Yen falls to weakest level versus dollar since December 1986",
    "url": "https://www.investing.com/news/forex-news/yen-falls-to-weakest-level-versus-dollar-since-december-1986-93CH-4765678",
    "sentiment_score": 0.6,
    "impact": "MEDIUM",
    "keywords": [
      "geopolitical tension",
      "inflation fears",
      "Middle East"
    ],
    "fetched_at": "2026-06-30T06:06:36.351664+00:00"
  },
  {
    "source": "Investing.com Forex",
    "headline": "Sterling today: Pound gains as dollar weakness persists",
    "url": "https://www.investing.com/news/forex-news/sterling-today-pound-gains-as-dollar-weakness-persists-4765416",
    "sentiment_score": -0.7,
    "impact": "MEDIUM",
    "keywords": [
      "price decline",
      "momentum loss",
      "technical"
    ],
    "fetched_at": "2026-06-30T06:06:36.351664+00:00"
  },
  {
    "source": "Investing.com Forex",
    "headline": "Euro yields edge up as Middle East tension fuels oil, inflation fears",
    "url": "https://www.investing.com/news/forex-news/euro-yields-edge-up-as-middle-east-tension-fuels-oil-inflation-fears-4764282",
    "sentiment_score": 0.1,
    "impact": "LOW",
    "keywords": [
      "mining production",
      "silver",
      "supply"
    ],
    "fetched_at": "2026-06-30T06:06:36.351664+00:00"
  },
  {
    "source": "Mining.com",
    "headline": "Gold price falls nearly 2% as rebound proves short-lived",
    "url": "https://www.mining.com/gold-price-falls-back-to-4000-on-renewed-mideast-tensions/",
    "sentiment_score": 0.2,
    "impact": "LOW",
    "keywords": [
      "reserve growth",
      "exploration",
      "mining"
    ],
    "fetched_at": "2026-06-30T06:06:36.351664+00:00"
  },
  {
    "source": "Mining.com",
    "headline": "Bunker Hill\u00a0rebuild\u00a0ships first Idaho ore,\u00a0eyes silver",
    "url": "https://www.mining.com/bunker-hill-rebuild-ships-first-idaho-ore-eyes-silver/",
    "sentiment_score": 0.1,
    "impact": "LOW",
    "keywords": [
      "reserve expansion",
      "mining output",
      "supply"
    ],
    "fetched_at": "2026-06-30T06:06:36.351664+00:00"
  },
  {
    "source": "Mining.com",
    "headline": "Freeman Gold triples Lemhi project value, builds 1Moz reserve",
    "url": "https://www.mining.com/freeman-gold-triples-lemhi-project-value-builds-1moz-reserve/",
    "sentiment_score": -0.4,
    "impact": "MEDIUM",
    "keywords": [
      "price controls",
      "dollar strength",
      "demand"
    ],
    "fetched_at": "2026-06-30T06:06:36.351664+00:00"
  },
  {
    "source": "Mining.com",
    "headline": "Integra grows reserve by 74% at Florida Canyon gold mine",
    "url": "https://www.mining.com/integra-grows-reserve-74-at-florida-canyon-gold-mine/",
    "sentiment_score": -0.3,
    "impact": "LOW",
    "keywords": [
      "risk appetite",
      "stocks rally",
      "equities"
    ],
    "fetched_at": "2026-06-30T06:06:36.351664+00:00"
  },
  {
    "source": "Reuters",
    "headline": "Trump urges gasoline retailers to lower prices, warns of 'big problems' if they don't - Reuters",
    "url": "https://news.google.com/rss/articles/CBMixgFBVV95cUxQVlowVWxKdUhheXVNdWdVeDNkb1k2MHJFaExPdFVyMVVqNU1MZW9sQXhzaTNmdi1qNlFHamhFalRkcHo4TEdOZnMzLW5xVmZGZVdtbkp6NHJBVWNhS0FwVTQ3NmNVclk4YVpkYmM4T1pDZU1BLXk3a2p1SnBEOWxGSG9MUnpCWlc1U2kzZ2lwbEhOOWpHVW9wZFd2dDd2cXJOU0otR19CbEtCTW9HMXZqX0JvZ0RjNDFMQnBscUExQzFObUw0Mmc?oc=5",
    "sentiment_score": 0.4,
    "impact": "MEDIUM",
    "keywords": [
      "geopolitical risk",
      "safe haven",
      "Middle East"
    ],
    "fetched_at": "2026-06-30T06:06:36.351664+00:00"
  },
  {
    "source": "CNBC",
    "headline": "Chip stocks rebound, and Goldman racks up a series of M&A wins",
    "url": "https://www.cnbc.com/2026/06/29/chip-stocks-rebound-and-goldman-racks-up-a-series-of-ma-wins-.html",
    "sentiment_score": 0.5,
    "impact": "MEDIUM",
    "keywords": [
      "conflict escalation",
      "geopolitical tension",
      "safe haven"
    ],
    "fetched_at": "2026-06-30T06:06:36.351664+00:00"
  },
  {
    "source": "Reuters",
    "headline": "Israel-Lebanon deal may entrench stalemate rather than end war, analysts say - Reuters",
    "url": "https://news.google.com/rss/articles/CBMiyAFBVV95cUxOQzVPS3VRVGFsSElBdURJN0sxVEZaalUtNGpETS1FQXJLNkhkeTJ5M1VaR19HcmpoZXpWY3FhX0F2S2RLWjlMNVM1UWJzbllJcGZic3VnLVJYMWMtRk1GcVFGa2RZREpvY3JadXJScDZCVVdwRmYwY0lPVGRiOVQyLWI4MUJnY28zWW43TmJoRUM5dkRaUUpwRGhUNFB5MWVDV3hCY1lDUHJzUVpsSXI3QUlwR0puQkU0R3BMMXFHTm9hUmU0QURWTQ?oc=5",
    "sentiment_score": 0.4,
    "impact": "MEDIUM",
    "keywords": [
      "war damage",
      "geopolitical",
      "regional tension"
    ],
    "fetched_at": "2026-06-30T06:06:36.351664+00:00"
  },
  {
    "source": "Reuters",
    "headline": "Senior Lebanese official slams US-brokered deal with Israel, warns of divisions - Reuters",
    "url": "https://news.google.com/rss/articles/CBMiyAFBVV95cUxNdEcxa2lmSEt3VTljemt3NzlwaGdLWVZCTHdjYUJEVjlzZkNSTDUzUXRaQThvc1d1MTJBVVdERzF2Qno3YWthLWRDVGtKbHZxQ2xuVmNkWG43Ri1mWHM0TGJrX3F4TXlyaTdwYXBxQzRDaHNSOFhSZDhtS04tRGRIejNOZTdLSHBaS293OWNIMC12bV83anZQdDRra204aU0wSFI4NGZ1LTdHRHBfM1pSYWdXOHpZMUZzUnlwd0tGS3p6N3dsYzRxYQ?oc=5",
    "sentiment_score": 0.6,
    "impact": "MEDIUM",
    "keywords": [
      "US-Iran tension",
      "inflation risk",
      "safe haven"
    ],
    "fetched_at": "2026-06-30T06:06:36.351664+00:00"
  },
  {
    "source": "Reuters",
    "headline": "How 5 weeks of war shattered some of Iran\u2019s cherished monuments - Reuters",
    "url": "https://news.google.com/rss/articles/CBMiigFBVV95cUxQZDF2cmU1OXB5Q1VfV0ZUM1VhZE51WVlXTnlrS2VUaC1oMldhNUYzUkFpRGdTNDg3b1RRSEZtYUVHamtJODBvMUFkMnpwZkhGS1NPMFp3TUlkdWs1VUhzN1Z4dEpybndfNDJEN1YtUnJXYXVlMDlkdVQ4d0JxRUxtdEx5QXE1NTN5OHc?oc=5",
    "sentiment_score": -0.5,
    "impact": "MEDIUM",
    "keywords": [
      "risk appetite",
      "oil strength",
      "equities"
    ],
    "fetched_at": "2026-06-30T06:06:36.351664+00:00"
  },
  {
    "source": "Reuters",
    "headline": "Gold slips as US-Iran tensions spark inflation, rate hike fears - Reuters",
    "url": "https://news.google.com/rss/articles/CBMitgFBVV95cUxPSTVKRTRyZTc4cndMX2E0Mzd3UlROU1FJMWFsaWpkbDVuSUFiVldPeE1GRVFLbDVYeTZ5RTFXd08wUkYwU205amR5a1BIOTFTNGE1T01qMjNGSkJ2OXpjQVhWQ1JXSTdOeDBGb3I5czNDQ1VYck9ENEZJNVZMQk5Rc19tTWgzM3hGaC1uSlltSktpNWtyM3AtTTk3RkZJaFNpNjVFRXJUSWhuWEJGcnNUb1ZGVWstUQ?oc=5",
    "sentiment_score": 0.5,
    "impact": "MEDIUM",
    "keywords": [
      "geopolitical risk",
      "rate expectations",
      "central bank"
    ],
    "fetched_at": "2026-06-30T06:06:36.351664+00:00"
  },
  {
    "source": "Reuters",
    "headline": "Stocks and oil prices rise with eyes on Iran; yen touches 40-year low vs dollar - Reuters",
    "url": "https://news.google.com/rss/articles/CBMigAFBVV95cUxPYUFwVXVYYUk3ZXZGYUhac1BmQjhYN1JiSHM5SlhvWW9taHVTRkFZeVlrNFVfTl8wQVY0VTc3ekNEd1EyX2NMYjdNZXFwWi1WMFJWTHVIaE8yNTNNVWR4NkFHelBmSFlwYWdjRTZQREo4elhtYnNhZ3RMMjg2ckttSw?oc=5",
    "sentiment_score": -0.6,
    "impact": "MEDIUM",
    "keywords": [
      "inflation transitory",
      "rate hike unlikely",
      "demand"
    ],
    "fetched_at": "2026-06-30T06:06:36.351664+00:00"
  },
  {
    "source": "Reuters",
    "headline": "Iran war developments, Fed rate path cues in focus for Indian rupee and bonds - Reuters",
    "url": "https://news.google.com/rss/articles/CBMiuwFBVV95cUxNU0tnYmloaHpIVTVmYUZHSUljRy1XNHN2VU8wSDVxSk5DRmJFUkNDWjNzOXJ6ejd0a0hGWmoxMWJncnZOQm5taGpMU09TMjBTMEFkUWlTZXVDMXRoUkhoZGRTWVdUTnVzaXhoRHlQUmloSnpPUTVBYU9rbFV0ZE1VTUFnZGZ2RkRTTWRjQ1dqVE9Telg2c285TlBTRFYyVDNFc1pxcUExa0lkZ3ZUTy1MZEp0N2pOTzg4ZFo4?oc=5",
    "sentiment_score": 0.4,
    "impact": "MEDIUM",
    "keywords": [
      "dollar weakness",
      "technical support",
      "safe haven"
    ],
    "fetched_at": "2026-06-30T06:06:36.351664+00:00"
  },
  {
    "source": "CNBC",
    "headline": "Trading in these two ETFs suggests inflation fears are overblown",
    "url": "https://www.cnbc.com/2026/06/27/trading-in-these-two-etfs-suggests-inflation-fears-are-overblown.html",
    "sentiment_score": -0.3,
    "impact": "LOW",
    "keywords": [
      "inflation contained",
      "energy stable",
      "economic data"
    ],
    "fetched_at": "2026-06-30T06:06:36.351664+00:00"
  },
  {
    "source": "Reuters",
    "headline": "Gold gains as dollar weakens; still on track for fourth straight weekly loss - Reuters",
    "url": "https://news.google.com/rss/articles/CBMipwFBVV95cUxQRXc4NjVKdS0yVG1sdzYzZEIwNno3QXhNVzFKRktkSHJZa3l0dUZFTmd2blZtbVVSM2MzR0dNX0VTR1VzMEd2d3NxQjROYU5LdF9zMVY3SkNsZzRSSUVPOFdnMEZ6Qm9CdmlNVWx4V2Z6UlhianlDVUZxMGw4WlNOUjlhS2VwcGRqZmEtTHJMTXlhUG1CdWhUR0w1WmhxZ1ZOSTFNdUI2NA?oc=5",
    "sentiment_score": 0.3,
    "impact": "MEDIUM",
    "keywords": [
      "geopolitical risk",
      "Hormuz strait",
      "security"
    ],
    "fetched_at": "2026-06-30T06:06:36.351664+00:00"
  },
  {
    "source": "Reuters",
    "headline": "US diesel refining economics remain firm despite Iran war truce - Reuters",
    "url": "https://news.google.com/rss/articles/CBMitgFBVV95cUxQaktNajNVTlRkTm1nVkRyMHNDc3FBTk5BRjRVVy16cjRNbFdhSFhYWkYtcy1wNlJkMzRjTWhnakNiUmJjZ3V1c2luUG9lNVcyaG1Semg3UkhQOHEtY2tFS1lQbkkwZll4U3MzU2J3QmJuQnRKUzFuVVJPQXpJNzRjNmd2Rzc2aC1XRDMxck1OcXlxd3dNM1pJQnFHb3Z1S2U5VmVMYWtNY190WmdtNmtKd29fQm8zZw?oc=5",
    "sentiment_score": -0.2,
    "impact": "LOW",
    "keywords": [
      "false alarm",
      "technical issue",
      "risk off"
    ],
    "fetched_at": "2026-06-30T06:06:36.351664+00:00"
  },
  {
    "source": "Reuters",
    "headline": "UAE stresses Hormuz security in rare call with Iran after war tensions - Reuters",
    "url": "https://news.google.com/rss/articles/CBMivgFBVV95cUxOTFhOWjA0b0NFVmItV25IVHhmdUw2WmtfeGU1SXZ1ZjFsaHF4bnJrTVVVR0M5QlFfS3Z1Vk5Scm5CTjFCaXB3SVREeXctT1h4QlhwaDJKc2dQNGhTbTV2U243Q0kwUjhzUEJnak5RdzdLNkpyMUNVcjNOdWFsRXFYVUFlZFpzMm9fMmR3dXJpem1wMWhOWm5OVDJfd3NzX1hhOFlnYjJZMzNId2UyOUxMS3VrdmJCWmxsVnlpZ3NB?oc=5",
    "sentiment_score": 0.0,
    "impact": "LOW",
    "keywords": [],
    "fetched_at": "2026-06-30T06:06:36.351664+00:00"
  },
  {
    "source": "Reuters",
    "headline": "UAE says false public warning caused by technical malfunction - Reuters",
    "url": "https://news.google.com/rss/articles/CBMitwFBVV95cUxQYTA4WmxkQjRfQjJKWUlDVzZuU0p0Sm8wS2g5c3JXay1qSXdTVHpsdVdDN3NwVEV3TnJZQ0RaV0htWm5xcnZ6LU96bXAza1RXeEhJUEN5UzNYN1IzTWZCeEFrUVdYNzRmdTNzaFAzNW9LWGQ1akpXOFlOdXI2NjA0UjVaSVJnenlsa2xmQ1lSTGZ3LTNVbWRJTG40aERIMjF4TGloTVcxRGFYMUhrMjdVdWExZHQyVW8?oc=5",
    "sentiment_score": 0.0,
    "impact": "LOW",
    "keywords": [],
    "fetched_at": "2026-06-30T06:06:36.351664+00:00"
  }
]