[
  {
    "symbol": "XAUUSD",
    "direction": "SHORT",
    "trigger": "FVG",
    "entry_price": 4204.54,
    "exit_price": 4309.08,
    "outcome": "LOSS",
    "ml_outcome": "LOSS",
    "mfe": -63.73,
    "tp_stage": "SL",
    "timeframe": "15",
    "pnl_pct": -2.4864,
    "ml_bull_score": 0.625,
    "regime": "TRENDING_BEAR",
    "session": "OFF",
    "f1_rsi": -0.113,
    "f2_adx": -0.4529,
    "f3_atr": -0.3685,
    "f4_bb": -0.8678,
    "f5_macd": -1.0,
    "f6_willr": 0.8412,
    "f7_cmo": -0.3566,
    "f8_ema_dist": 0.3797,
    "f9_fvg": -1.0,
    "f10_ob": 0.0,
    "f11_bos": 0.0,
    "f12_liq": 0.0,
    "f13_pd": -0.049,
    "f14_choch": 0.0,
    "f15_sess": 0.3,
    "f16_mtf": -1.0,
    "f17_dxy": -1.0,
    "f18_vold": -0.1938,
    "f19_rsidiv": 0.0,
    "f20_fib": 0.2697,
    "f21_vwap": 0.0022,
    "f22_body": -0.5044,
    "f23_rsiacc": -0.1614,
    "f24_fvgq": 0.0,
    "f25_tod": -0.9205,
    "f26_stoch": -0.2196,
    "id": "8bd8b348",
    "pool": "XAUUSD_15M",
    "created_at": "2026-06-14T22:17:02.979111+00:00"
  },
  {
    "symbol": "XAUUSD",
    "direction": "LONG",
    "trigger": "FVG",
    "entry_price": 4301.07,
    "exit_price": 4330.8114,
    "outcome": "WIN",
    "ml_outcome": "TP1_HIT",
    "mfe": 31.06,
    "tp_stage": "TP1",
    "timeframe": "15",
    "pnl_pct": 0.6915,
    "ml_bull_score": 0.5,
    "regime": "NORMAL",
    "session": "ASIAN",
    "f1_rsi": 0.602,
    "f2_adx": 0.4295,
    "f3_atr": 0.4215,
    "f4_bb": 1.0,
    "f5_macd": 1.0,
    "f6_willr": -0.8506,
    "f7_cmo": 0.6026,
    "f8_ema_dist": 1.0,
    "f9_fvg": 1.0,
    "f10_ob": 0.0,
    "f11_bos": 1.0,
    "f12_liq": 0.0,
    "f13_pd": -0.8786,
    "f14_choch": 0.0,
    "f15_sess": -0.5,
    "f16_mtf": 0.0,
    "f17_dxy": 1.0,
    "f18_vold": 0.864,
    "f19_rsidiv": 0.0,
    "f20_fib": 0.8845,
    "f21_vwap": 0.1852,
    "f22_body": 0.792,
    "f23_rsiacc": 0.6675,
    "f24_fvgq": 0.0,
    "f25_tod": -0.4924,
    "f26_stoch": 1.0,
    "id": "e58d41af",
    "pool": "XAUUSD_15M",
    "created_at": "2026-06-15T02:32:02.125041+00:00"
  },
  {
    "symbol": "XAUUSD",
    "direction": "LONG",
    "trigger": "FVG",
    "entry_price": 4301.07,
    "exit_price": 4321.97,
    "outcome": "PARTIAL",
    "ml_outcome": "WIN",
    "mfe": 34.41,
    "tp_stage": "SL_TP1",
    "timeframe": "15",
    "pnl_pct": 0.4859,
    "ml_bull_score": 0.625,
    "regime": "NORMAL",
    "session": "ASIAN",
    "f1_rsi": 0.602,
    "f2_adx": 0.4295,
    "f3_atr": 0.4215,
    "f4_bb": 1.0,
    "f5_macd": 1.0,
    "f6_willr": -0.8506,
    "f7_cmo": 0.6026,
    "f8_ema_dist": 1.0,
    "f9_fvg": 1.0,
    "f10_ob": 0.0,
    "f11_bos": 1.0,
    "f12_liq": 0.0,
    "f13_pd": -0.8786,
    "f14_choch": 0.0,
    "f15_sess": -0.5,
    "f16_mtf": 0.0,
    "f17_dxy": 1.0,
    "f18_vold": 0.864,
    "f19_rsidiv": 0.0,
    "f20_fib": 0.8845,
    "f21_vwap": 0.1852,
    "f22_body": 0.792,
    "f23_rsiacc": 0.6675,
    "f24_fvgq": 0.0,
    "f25_tod": -0.4924,
    "f26_stoch": 1.0,
    "id": "ad391fcf",
    "pool": "XAUUSD_15M",
    "created_at": "2026-06-15T03:17:01.521545+00:00"
  }
]